Workbook
Name Berlin_Feiertage: 'Listen'!$E$2:$E$82
Name MitarbeiterListe: 'Listen'!$B$2:$B$29
Name GewerkeListe: 'Listen'!$A$2:$A$13
Name Stundenexport_Druckbereich: 'Zeiterfassung Export'!$A$1:INDEX('Zeiterfassung Export'!$J:$J,MAX(5,IFERROR(MATCH(9.99999999999999E+307,'Zeiterfassung Export'!$K:$K),5)))
Name NUGewerkeListe: 'Listen'!$N$2:$N$8
Name LieferantenListe: 'Listen'!$P$2:$P$12
Name RechnungsartenListe: 'Listen'!$X$2:$X$4
Name ErfassungDatumListe: 'Listen'!$AB$2:$AB$367
Name ErfassungKWListe: 'Listen'!$AC$2:$AC$54

Sheet Projektübersicht
B2: BAUABLAUFMAPPE | N2: COCKPIT
B5: Projektsteuerung · Personal · Stunden · Material · Abrechnung
B7: PROJEKTSTAMMDATEN
B8: BAUVORHABEN | F8: GEWERKE
B10: PROJEKTVERANTWORTLICHER | F10: BAUBEGINN
B12: AUFTRAGGEBER | F12: BAUENDE
B15: PROJEKTCOCKPIT
B16: MARGE NACHUNTERNEHMER | F16: MARGE EIGENLEISTUNG | J16: PROJEKTMARGE TOTAL
B17: ='KPI-Basis'!$C$9 | F17: ='KPI-Basis'!$C$15 | J17: ='KPI-Basis'!$C$20
B19: ='Nachunternehmer'!$E$4
B21: STUNDEN SOLL | F21: STUNDEN IST | J21: RESTBUDGET STUNDEN
B22: 0 | F22: =SUM(Zeiterfassung!$H$6:$H$3665) | J22: =IF(B22="","",B22-F22)
N25: Kategorie | O25: Fakturiert | P25: Unfertige Leistungen | Q25: Restleistung
B26: PROJEKTFORTSCHRITT / AUFTRAGSVOLUMEN | N26: Auftragssumme | O26: =IF($B$28="",0,$F$28) | P26: =IF($B$28="",0,$J$28) | Q26: =IF($B$28="",0,MAX(0,$B$28-$F$28-$J$28))
B27: AUFTRAGSSUMME NETTO | F27: IN RECHNUNG GESTELLT | J27: UNFERTIGE LEISTUNGEN
B28: 0 | F28: =SUM(Rechnungsstand!$F$6:$F$305) | J28: ='Rechnungsstand'!$M$5
B30: Auftragssumme und Stunden-Soll werden im Cockpit gepflegt · Unfertige Leistungen werden im Rechnungsstand erfasst.

Sheet Zeiterfassung
A1: ZEITERFASSUNG · PROJEKTVERLAUF | L1: ← ZUM COCKPIT | O1: STUNDENEXPORT →
A3: Kalenderwochen und Tage automatisch aus Baubeginn/Bauende · Leistungen einmal je Tag erfassen · Mitarbeiterzeiten darunter dokumentieren | L3: SCHNELLNAVIGATION
A4: =IF('Projektübersicht'!B9="","BAUVORHABEN","BAUVORHABEN · "&'Projektübersicht'!B9) | D4: =IF('Projektübersicht'!B13="","AUFTRAGGEBER","AUFTRAGGEBER · "&'Projektübersicht'!B13) | G4: =IF(AND('Projektübersicht'!$F$11="",'Projektübersicht'!$F$13=""),"BAUZEIT",IF(OR('Projektübersicht'!$F$11="",'Projektübersicht'!$F$13=""),"BAUZEIT · Stammdaten unvollständig","BAUZEIT · "&TEXT(DAY('Projektübersicht'!$F$11),"00")&"."&TEXT(MONTH('Projektübersicht'!$F$11),"00")&"."&YEAR('Projektübersicht'!$F$11)&" – "&TEXT(DAY('Projektübersicht'!$F$13),"00")&"."&TEXT(MONTH('Projektübersicht'!$F$13),"00")&"."&YEAR('Projektübersicht'!$F$13))) | L4: DATUM | N4: =IF($M$4="","TAG AUSWÄHLEN",HYPERLINK("#'Zeiterfassung'!A"&(MATCH($M$4,$K$6:$K$3665,0)+5),"→ ZUM TAG"))
A5: KW | B5: DATUM | C5: TAG | D5: MITARBEITER | E5: GEWERK | F5: ARBEITSANFANG | G5: ARBEITSENDE | H5: ARBEITSSTUNDEN | I5: ARBEITEN / LEISTUNGEN DES TAGES | J5: TAGESBEMERKUNG | K5: DATUM INTERN | L5: KW | N5: =IF($M$5="","KW AUSWÄHLEN",HYPERLINK("#'Zeiterfassung'!A"&(MATCH($M$5,$A$6:$A$3665,0)+5),"→ ZUR KW"))
A6: =IF($K6="","",WEEKNUM($K6,21)) | B6: =IF($K6="","",$K6) | C6: =IF($K6="","",$K6) | H6: =IF(OR(F6="",G6=""),"",ROUND(MOD(G6-F6,1)*24,2)) | K6: =IF(OR('Projektübersicht'!$F$11="",'Projektübersicht'!$F$13="",'Projektübersicht'!$F$11>'Projektübersicht'!$F$13),"",IF(WORKDAY.INTL('Projektübersicht'!$F$11-1,1,"0000001")<='Projektübersicht'!$F$13,WORKDAY.INTL('Projektübersicht'!$F$11-1,1,"0000001"),""))
H7: =IF(OR(F7="",G7=""),"",ROUND(MOD(G7-F7,1)*24,2)) | K7: =IF(OR('Projektübersicht'!$F$11="",'Projektübersicht'!$F$13="",'Projektübersicht'!$F$11>'Projektübersicht'!$F$13),"",IF(WORKDAY.INTL('Projektübersicht'!$F$11-1,1,"0000001")<='Projektübersicht'!$F$13,WORKDAY.INTL('Projektübersicht'!$F$11-1,1,"0000001"),"")) | L7: MEHR ALS 5 MITARBEITER? Links am Tagesblock auf + klicken.
H8: =IF(OR(F8="",G8=""),"",ROUND(MOD(G8-F8,1)*24,2)) | K8: =IF(OR('Projektübersicht'!$F$11="",'Projektübersicht'!$F$13="",'Projektübersicht'!$F$11>'Projektübersicht'!$F$13),"",IF(WORKDAY.INTL('Projektübersicht'!$F$11-1,1,"0000001")<='Projektübersicht'!$F$13,WORKDAY.INTL('Projektübersicht'!$F$11-1,1,"0000001"),""))
H9: =IF(OR(F9="",G9=""),"",ROUND(MOD(G9-F9,1)*24,2)) | K9: =IF(OR('Projektübersicht'!$F$11="",'Projektübersicht'!$F$13="",'Projektübersicht'!$F$11>'Projektübersicht'!$F$13),"",IF(WORKDAY.INTL('Projektübersicht'!$F$11-1,1,"0000001")<='Projektübersicht'!$F$13,WORKDAY.INTL('Projektübersicht'!$F$11-1,1,"0000001"),""))
H10: =IF(OR(F10="",G10=""),"",ROUND(MOD(G10-F10,1)*24,2)) | K10: =IF(OR('Projektübersicht'!$F$11="",'Projektübersicht'!$F$13="",'Projektübersicht'!$F$11>'Projektübersicht'!$F$13),"",IF(WORKDAY.INTL('Projektübersicht'!$F$11-1,1,"0000001")<='Projektübersicht'!$F$13,WORKDAY.INTL('Projektübersicht'!$F$11-1,1,"0000001"),""))
H11: =IF(OR(F11="",G11=""),"",ROUND(MOD(G11-F11,1)*24,2)) | K11: =IF(OR('Projektübersicht'!$F$11="",'Projektübersicht'!$F$13="",'Projektübersicht'!$F$11>'Projektübersicht'!$F$13),"",IF(WORKDAY.INTL('Projektübersicht'!$F$11-1,1,"0000001")<='Projektübersicht'!$F$13,WORKDAY.INTL('Projektübersicht'!$F$11-1,1,"0000001"),""))
H12: =IF(OR(F12="",G12=""),"",ROUND(MOD(G12-F12,1)*24,2)) | K12: =IF(OR('Projektübersicht'!$F$11="",'Projektübersicht'!$F$13="",'Projektübersicht'!$F$11>'Projektübersicht'!$F$13),"",IF(WORKDAY.INTL('Projektübersicht'!$F$11-1,1,"0000001")<='Projektübersicht'!$F$13,WORKDAY.INTL('Projektübersicht'!$F$11-1,1,"0000001"),""))
H13: =IF(OR(F13="",G13=""),"",ROUND(MOD(G13-F13,1)*24,2)) | K13: =IF(OR('Projektübersicht'!$F$11="",'Projektübersicht'!$F$13="",'Projektübersicht'!$F$11>'Projektübersicht'!$F$13),"",IF(WORKDAY.INTL('Projektübersicht'!$F$11-1,1,"0000001")<='Projektübersicht'!$F$13,WORKDAY.INTL('Projektübersicht'!$F$11-1,1,"0000001"),""))
H14: =IF(OR(F14="",G14=""),"",ROUND(MOD(G14-F14,1)*24,2)) | K14: =IF(OR('Projektübersicht'!$F$11="",'Projektübersicht'!$F$13="",'Projektübersicht'!$F$11>'Projektübersicht'!$F$13),"",IF(WORKDAY.INTL('Projektübersicht'!$F$11-1,1,"0000001")<='Projektübersicht'!$F$13,WORKDAY.INTL('Projektübersicht'!$F$11-1,1,"0000001"),""))
H15: =IF(OR(F15="",G15=""),"",ROUND(MOD(G15-F15,1)*24,2)) | K15: =IF(OR('Projektübersicht'!$F$11="",'Projektübersicht'!$F$13="",'Projektübersicht'!$F$11>'Projektübersicht'!$F$13),"",IF(WORKDAY.INTL('Projektübersicht'!$F$11-1,1,"0000001")<='Projektübersicht'!$F$13,WORKDAY.INTL('Projektübersicht'!$F$11-1,1,"0000001"),""))
A16: =IF($K16="","",WEEKNUM($K16,21)) | B16: =IF($K16="","",$K16) | C16: =IF($K16="","",$K16) | H16: =IF(OR(F16="",G16=""),"",ROUND(MOD(G16-F16,1)*24,2)) | K16: =IF(OR('Projektübersicht'!$F$11="",'Projektübersicht'!$F$13="",'Projektübersicht'!$F$11>'Projektübersicht'!$F$13),"",IF(WORKDAY.INTL('Projektübersicht'!$F$11-1,2,"0000001")<='Projektübersicht'!$F$13,WORKDAY.INTL('Projektübersicht'!$F$11-1,2,"0000001"),""))
H17: =IF(OR(F17="",G17=""),"",ROUND(MOD(G17-F17,1)*24,2)) | K17: =IF(OR('Projektübersicht'!$F$11="",'Projektübersicht'!$F$13="",'Projektübersicht'!$F$11>'Projektübersicht'!$F$13),"",IF(WORKDAY.INTL('Projektübersicht'!$F$11-1,2,"0000001")<='Projektübersicht'!$F$13,WORKDAY.INTL('Projektübersicht'!$F$11-1,2,"0000001"),""))
H18: =IF(OR(F18="",G18=""),"",ROUND(MOD(G18-F18,1)*24,2)) | K18: =IF(OR('Projektübersicht'!$F$11="",'Projektübersicht'!$F$13="",'Projektübersicht'!$F$11>'Projektübersicht'!$F$13),"",IF(WORKDAY.INTL('Projektübersicht'!$F$11-1,2,"0000001")<='Projektübersicht'!$F$13,WORKDAY.INTL('Projektübersicht'!$F$11-1,2,"0000001"),""))
H19: =IF(OR(F19="",G19=""),"",ROUND(MOD(G19-F19,1)*24,2)) | K19: =IF(OR('Projektübersicht'!$F$11="",'Projektübersicht'!$F$13="",'Projektübersicht'!$F$11>'Projektübersicht'!$F$13),"",IF(WORKDAY.INTL('Projektübersicht'!$F$11-1,2,"0000001")<='Projektübersicht'!$F$13,WORKDAY.INTL('Projektübersicht'!$F$11-1,2,"0000001"),""))
H20: =IF(OR(F20="",G20=""),"",ROUND(MOD(G20-F20,1)*24,2)) | K20: =IF(OR('Projektübersicht'!$F$11="",'Projektübersicht'!$F$13="",'Projektübersicht'!$F$11>'Projektübersicht'!$F$13),"",IF(WORKDAY.INTL('Projektübersicht'!$F$11-1,2,"0000001")<='Projektübersicht'!$F$13,WORKDAY.INTL('Projektübersicht'!$F$11-1,2,"0000001"),""))
H21: =IF(OR(F21="",G21=""),"",ROUND(MOD(G21-F21,1)*24,2)) | K21: =IF(OR('Projektübersicht'!$F$11="",'Projektübersicht'!$F$13="",'Projektübersicht'!$F$11>'Projektübersicht'!$F$13),"",IF(WORKDAY.INTL('Projektübersicht'!$F$11-1,2,"0000001")<='Projektübersicht'!$F$13,WORKDAY.INTL('Projektübersicht'!$F$11-1,2,"0000001"),""))
H22: =IF(OR(F22="",G22=""),"",ROUND(MOD(G22-F22,1)*24,2)) | K22: =IF(OR('Projektübersicht'!$F$11="",'Projektübersicht'!$F$13="",'Projektübersicht'!$F$11>'Projektübersicht'!$F$13),"",IF(WORKDAY.INTL('Projektübersicht'!$F$11-1,2,"0000001")<='Projektübersicht'!$F$13,WORKDAY.INTL('Projektübersicht'!$F$11-1,2,"0000001"),""))
H23: =IF(OR(F23="",G23=""),"",ROUND(MOD(G23-F23,1)*24,2)) | K23: =IF(OR('Projektübersicht'!$F$11="",'Projektübersicht'!$F$13="",'Projektübersicht'!$F$11>'Projektübersicht'!$F$13),"",IF(WORKDAY.INTL('Projektübersicht'!$F$11-1,2,"0000001")<='Projektübersicht'!$F$13,WORKDAY.INTL('Projektübersicht'!$F$11-1,2,"0000001"),""))
H24: =IF(OR(F24="",G24=""),"",ROUND(MOD(G24-F24,1)*24,2)) | K24: =IF(OR('Projektübersicht'!$F$11="",'Projektübersicht'!$F$13="",'Projektübersicht'!$F$11>'Projektübersicht'!$F$13),"",IF(WORKDAY.INTL('Projektübersicht'!$F$11-1,2,"0000001")<='Projektübersicht'!$F$13,WORKDAY.INTL('Projektübersicht'!$F$11-1,2,"0000001"),""))
H25: =IF(OR(F25="",G25=""),"",ROUND(MOD(G25-F25,1)*24,2)) | K25: =IF(OR('Projektübersicht'!$F$11="",'Projektübersicht'!$F$13="",'Projektübersicht'!$F$11>'Projektübersicht'!$F$13),"",IF(WORKDAY.INTL('Projektübersicht'!$F$11-1,2,"0000001")<='Projektübersicht'!$F$13,WORKDAY.INTL('Projektübersicht'!$F$11-1,2,"0000001"),""))
A26: =IF($K26="","",WEEKNUM($K26,21)) | B26: =IF($K26="","",$K26) | C26: =IF($K26="","",$K26) | H26: =IF(OR(F26="",G26=""),"",ROUND(MOD(G26-F26,1)*24,2)) | K26: =IF(OR('Projektübersicht'!$F$11="",'Projektübersicht'!$F$13="",'Projektübersicht'!$F$11>'Projektübersicht'!$F$13),"",IF(WORKDAY.INTL('Projektübersicht'!$F$11-1,3,"0000001")<='Projektübersicht'!$F$13,WORKDAY.INTL('Projektübersicht'!$F$11-1,3,"0000001"),""))
H27: =IF(OR(F27="",G27=""),"",ROUND(MOD(G27-F27,1)*24,2)) | K27: =IF(OR('Projektübersicht'!$F$11="",'Projektübersicht'!$F$13="",'Projektübersicht'!$F$11>'Projektübersicht'!$F$13),"",IF(WORKDAY.INTL('Projektübersicht'!$F$11-1,3,"0000001")<='Projektübersicht'!$F$13,WORKDAY.INTL('Projektübersicht'!$F$11-1,3,"0000001"),""))
H28: =IF(OR(F28="",G28=""),"",ROUND(MOD(G28-F28,1)*24,2)) | K28: =IF(OR('Projektübersicht'!$F$11="",'Projektübersicht'!$F$13="",'Projektübersicht'!$F$11>'Projektübersicht'!$F$13),"",IF(WORKDAY.INTL('Projektübersicht'!$F$11-1,3,"0000001")<='Projektübersicht'!$F$13,WORKDAY.INTL('Projektübersicht'!$F$11-1,3,"0000001"),""))
H29: =IF(OR(F29="",G29=""),"",ROUND(MOD(G29-F29,1)*24,2)) | K29: =IF(OR('Projektübersicht'!$F$11="",'Projektübersicht'!$F$13="",'Projektübersicht'!$F$11>'Projektübersicht'!$F$13),"",IF(WORKDAY.INTL('Projektübersicht'!$F$11-1,3,"0000001")<='Projektübersicht'!$F$13,WORKDAY.INTL('Projektübersicht'!$F$11-1,3,"0000001"),""))
H30: =IF(OR(F30="",G30=""),"",ROUND(MOD(G30-F30,1)*24,2)) | K30: =IF(OR('Projektübersicht'!$F$11="",'Projektübersicht'!$F$13="",'Projektübersicht'!$F$11>'Projektübersicht'!$F$13),"",IF(WORKDAY.INTL('Projektübersicht'!$F$11-1,3,"0000001")<='Projektübersicht'!$F$13,WORKDAY.INTL('Projektübersicht'!$F$11-1,3,"0000001"),""))
H31: =IF(OR(F31="",G31=""),"",ROUND(MOD(G31-F31,1)*24,2)) | K31: =IF(OR('Projektübersicht'!$F$11="",'Projektübersicht'!$F$13="",'Projektübersicht'!$F$11>'Projektübersicht'!$F$13),"",IF(WORKDAY.INTL('Projektübersicht'!$F$11-1,3,"0000001")<='Projektübersicht'!$F$13,WORKDAY.INTL('Projektübersicht'!$F$11-1,3,"0000001"),""))
H32: =IF(OR(F32="",G32=""),"",ROUND(MOD(G32-F32,1)*24,2)) | K32: =IF(OR('Projektübersicht'!$F$11="",'Projektübersicht'!$F$13="",'Projektübersicht'!$F$11>'Projektübersicht'!$F$13),"",IF(WORKDAY.INTL('Projektübersicht'!$F$11-1,3,"0000001")<='Projektübersicht'!$F$13,WORKDAY.INTL('Projektübersicht'!$F$11-1,3,"0000001"),""))
H33: =IF(OR(F33="",G33=""),"",ROUND(MOD(G33-F33,1)*24,2)) | K33: =IF(OR('Projektübersicht'!$F$11="",'Projektübersicht'!$F$13="",'Projektübersicht'!$F$11>'Projektübersicht'!$F$13),"",IF(WORKDAY.INTL('Projektübersicht'!$F$11-1,3,"0000001")<='Projektübersicht'!$F$13,WORKDAY.INTL('Projektübersicht'!$F$11-1,3,"0000001"),""))
H34: =IF(OR(F34="",G34=""),"",ROUND(MOD(G34-F34,1)*24,2)) | K34: =IF(OR('Projektübersicht'!$F$11="",'Projektübersicht'!$F$13="",'Projektübersicht'!$F$11>'Projektübersicht'!$F$13),"",IF(WORKDAY.INTL('Projektübersicht'!$F$11-1,3,"0000001")<='Projektübersicht'!$F$13,WORKDAY.INTL('Projektübersicht'!$F$11-1,3,"0000001"),""))
H35: =IF(OR(F35="",G35=""),"",ROUND(MOD(G35-F35,1)*24,2)) | K35: =IF(OR('Projektübersicht'!$F$11="",'Projektübersicht'!$F$13="",'Projektübersicht'!$F$11>'Projektübersicht'!$F$13),"",IF(WORKDAY.INTL('Projektübersicht'!$F$11-1,3,"0000001")<='Projektübersicht'!$F$13,WORKDAY.INTL('Projektübersicht'!$F$11-1,3,"0000001"),""))
A36: =IF($K36="","",WEEKNUM($K36,21)) | B36: =IF($K36="","",$K36) | C36: =IF($K36="","",$K36) | H36: =IF(OR(F36="",G36=""),"",ROUND(MOD(G36-F36,1)*24,2)) | K36: =IF(OR('Projektübersicht'!$F$11="",'Projektübersicht'!$F$13="",'Projektübersicht'!$F$11>'Projektübersicht'!$F$13),"",IF(WORKDAY.INTL('Projektübersicht'!$F$11-1,4,"0000001")<='Projektübersicht'!$F$13,WORKDAY.INTL('Projektübersicht'!$F$11-1,4,"0000001"),""))
H37: =IF(OR(F37="",G37=""),"",ROUND(MOD(G37-F37,1)*24,2)) | K37: =IF(OR('Projektübersicht'!$F$11="",'Projektübersicht'!$F$13="",'Projektübersicht'!$F$11>'Projektübersicht'!$F$13),"",IF(WORKDAY.INTL('Projektübersicht'!$F$11-1,4,"0000001")<='Projektübersicht'!$F$13,WORKDAY.INTL('Projektübersicht'!$F$11-1,4,"0000001"),""))
H38: =IF(OR(F38="",G38=""),"",ROUND(MOD(G38-F38,1)*24,2)) | K38: =IF(OR('Projektübersicht'!$F$11="",'Projektübersicht'!$F$13="",'Projektübersicht'!$F$11>'Projektübersicht'!$F$13),"",IF(WORKDAY.INTL('Projektübersicht'!$F$11-1,4,"0000001")<='Projektübersicht'!$F$13,WORKDAY.INTL('Projektübersicht'!$F$11-1,4,"0000001"),""))
H39: =IF(OR(F39="",G39=""),"",ROUND(MOD(G39-F39,1)*24,2)) | K39: =IF(OR('Projektübersicht'!$F$11="",'Projektübersicht'!$F$13="",'Projektübersicht'!$F$11>'Projektübersicht'!$F$13),"",IF(WORKDAY.INTL('Projektübersicht'!$F$11-1,4,"0000001")<='Projektübersicht'!$F$13,WORKDAY.INTL('Projektübersicht'!$F$11-1,4,"0000001"),""))
H40: =IF(OR(F40="",G40=""),"",ROUND(MOD(G40-F40,1)*24,2)) | K40: =IF(OR('Projektübersicht'!$F$11="",'Projektübersicht'!$F$13="",'Projektübersicht'!$F$11>'Projektübersicht'!$F$13),"",IF(WORKDAY.INTL('Projektübersicht'!$F$11-1,4,"0000001")<='Projektübersicht'!$F$13,WORKDAY.INTL('Projektübersicht'!$F$11-1,4,"0000001"),""))
H41: =IF(OR(F41="",G41=""),"",ROUND(MOD(G41-F41,1)*24,2)) | K41: =IF(OR('Projektübersicht'!$F$11="",'Projektübersicht'!$F$13="",'Projektübersicht'!$F$11>'Projektübersicht'!$F$13),"",IF(WORKDAY.INTL('Projektübersicht'!$F$11-1,4,"0000001")<='Projektübersicht'!$F$13,WORKDAY.INTL('Projektübersicht'!$F$11-1,4,"0000001"),""))
H42: =IF(OR(F42="",G42=""),"",ROUND(MOD(G42-F42,1)*24,2)) | K42: =IF(OR('Projektübersicht'!$F$11="",'Projektübersicht'!$F$13="",'Projektübersicht'!$F$11>'Projektübersicht'!$F$13),"",IF(WORKDAY.INTL('Projektübersicht'!$F$11-1,4,"0000001")<='Projektübersicht'!$F$13,WORKDAY.INTL('Projektübersicht'!$F$11-1,4,"0000001"),""))
H43: =IF(OR(F43="",G43=""),"",ROUND(MOD(G43-F43,1)*24,2)) | K43: =IF(OR('Projektübersicht'!$F$11="",'Projektübersicht'!$F$13="",'Projektübersicht'!$F$11>'Projektübersicht'!$F$13),"",IF(WORKDAY.INTL('Projektübersicht'!$F$11-1,4,"0000001")<='Projektübersicht'!$F$13,WORKDAY.INTL('Projektübersicht'!$F$11-1,4,"0000001"),""))
H44: =IF(OR(F44="",G44=""),"",ROUND(MOD(G44-F44,1)*24,2)) | K44: =IF(OR('Projektübersicht'!$F$11="",'Projektübersicht'!$F$13="",'Projektübersicht'!$F$11>'Projektübersicht'!$F$13),"",IF(WORKDAY.INTL('Projektübersicht'!$F$11-1,4,"0000001")<='Projektübersicht'!$F$13,WORKDAY.INTL('Projektübersicht'!$F$11-1,4,"0000001"),""))
H45: =IF(OR(F45="",G45=""),"",ROUND(MOD(G45-F45,1)*24,2)) | K45: =IF(OR('Projektübersicht'!$F$11="",'Projektübersicht'!$F$13="",'Projektübersicht'!$F$11>'Projektübersicht'!$F$13),"",IF(WORKDAY.INTL('Projektübersicht'!$F$11-1,4,"0000001")<='Projektübersicht'!$F$13,WORKDAY.INTL('Projektübersicht'!$F$11-1,4,"0000001"),""))
A46: =IF($K46="","",WEEKNUM($K46,21)) | B46: =IF($K46="","",$K46) | C46: =IF($K46="","",$K46) | H46: =IF(OR(F46="",G46=""),"",ROUND(MOD(G46-F46,1)*24,2)) | K46: =IF(OR('Projektübersicht'!$F$11="",'Projektübersicht'!$F$13="",'Projektübersicht'!$F$11>'Projektübersicht'!$F$13),"",IF(WORKDAY.INTL('Projektübersicht'!$F$11-1,5,"0000001")<='Projektübersicht'!$F$13,WORKDAY.INTL('Projektübersicht'!$F$11-1,5,"0000001"),""))
H47: =IF(OR(F47="",G47=""),"",ROUND(MOD(G47-F47,1)*24,2)) | K47: =IF(OR('Projektübersicht'!$F$11="",'Projektübersicht'!$F$13="",'Projektübersicht'!$F$11>'Projektübersicht'!$F$13),"",IF(WORKDAY.INTL('Projektübersicht'!$F$11-1,5,"0000001")<='Projektübersicht'!$F$13,WORKDAY.INTL('Projektübersicht'!$F$11-1,5,"0000001"),""))
H48: =IF(OR(F48="",G48=""),"",ROUND(MOD(G48-F48,1)*24,2)) | K48: =IF(OR('Projektübersicht'!$F$11="",'Projektübersicht'!$F$13="",'Projektübersicht'!$F$11>'Projektübersicht'!$F$13),"",IF(WORKDAY.INTL('Projektübersicht'!$F$11-1,5,"0000001")<='Projektübersicht'!$F$13,WORKDAY.INTL('Projektübersicht'!$F$11-1,5,"0000001"),""))
H49: =IF(OR(F49="",G49=""),"",ROUND(MOD(G49-F49,1)*24,2)) | K49: =IF(OR('Projektübersicht'!$F$11="",'Projektübersicht'!$F$13="",'Projektübersicht'!$F$11>'Projektübersicht'!$F$13),"",IF(WORKDAY.INTL('Projektübersicht'!$F$11-1,5,"0000001")<='Projektübersicht'!$F$13,WORKDAY.INTL('Projektübersicht'!$F$11-1,5,"0000001"),""))
H50: =IF(OR(F50="",G50=""),"",ROUND(MOD(G50-F50,1)*24,2)) | K50: =IF(OR('Projektübersicht'!$F$11="",'Projektübersicht'!$F$13="",'Projektübersicht'!$F$11>'Projektübersicht'!$F$13),"",IF(WORKDAY.INTL('Projektübersicht'!$F$11-1,5,"0000001")<='Projektübersicht'!$F$13,WORKDAY.INTL('Projektübersicht'!$F$11-1,5,"0000001"),""))
H51: =IF(OR(F51="",G51=""),"",ROUND(MOD(G51-F51,1)*24,2)) | K51: =IF(OR('Projektübersicht'!$F$11="",'Projektübersicht'!$F$13="",'Projektübersicht'!$F$11>'Projektübersicht'!$F$13),"",IF(WORKDAY.INTL('Projektübersicht'!$F$11-1,5,"0000001")<='Projektübersicht'!$F$13,WORKDAY.INTL('Projektübersicht'!$F$11-1,5,"0000001"),""))
H52: =IF(OR(F52="",G52=""),"",ROUND(MOD(G52-F52,1)*24,2)) | K52: =IF(OR('Projektübersicht'!$F$11="",'Projektübersicht'!$F$13="",'Projektübersicht'!$F$11>'Projektübersicht'!$F$13),"",IF(WORKDAY.INTL('Projektübersicht'!$F$11-1,5,"0000001")<='Projektübersicht'!$F$13,WORKDAY.INTL('Projektübersicht'!$F$11-1,5,"0000001"),""))
H53: =IF(OR(F53="",G53=""),"",ROUND(MOD(G53-F53,1)*24,2)) | K53: =IF(OR('Projektübersicht'!$F$11="",'Projektübersicht'!$F$13="",'Projektübersicht'!$F$11>'Projektübersicht'!$F$13),"",IF(WORKDAY.INTL('Projektübersicht'!$F$11-1,5,"0000001")<='Projektübersicht'!$F$13,WORKDAY.INTL('Projektübersicht'!$F$11-1,5,"0000001"),""))
H54: =IF(OR(F54="",G54=""),"",ROUND(MOD(G54-F54,1)*24,2)) | K54: =IF(OR('Projektübersicht'!$F$11="",'Projektübersicht'!$F$13="",'Projektübersicht'!$F$11>'Projektübersicht'!$F$13),"",IF(WORKDAY.INTL('Projektübersicht'!$F$11-1,5,"0000001")<='Projektübersicht'!$F$13,WORKDAY.INTL('Projektübersicht'!$F$11-1,5,"0000001"),""))
H55: =IF(OR(F55="",G55=""),"",ROUND(MOD(G55-F55,1)*24,2)) | K55: =IF(OR('Projektübersicht'!$F$11="",'Projektübersicht'!$F$13="",'Projektübersicht'!$F$11>'Projektübersicht'!$F$13),"",IF(WORKDAY.INTL('Projektübersicht'!$F$11-1,5,"0000001")<='Projektübersicht'!$F$13,WORKDAY.INTL('Projektübersicht'!$F$11-1,5,"0000001"),""))
A56: =IF($K56="","",WEEKNUM($K56,21)) | B56: =IF($K56="","",$K56) | C56: =IF($K56="","",$K56) | H56: =IF(OR(F56="",G56=""),"",ROUND(MOD(G56-F56,1)*24,2)) | K56: =IF(OR('Projektübersicht'!$F$11="",'Projektübersicht'!$F$13="",'Projektübersicht'!$F$11>'Projektübersicht'!$F$13),"",IF(WORKDAY.INTL('Projektübersicht'!$F$11-1,6,"0000001")<='Projektübersicht'!$F$13,WORKDAY.INTL('Projektübersicht'!$F$11-1,6,"0000001"),""))
H57: =IF(OR(F57="",G57=""),"",ROUND(MOD(G57-F57,1)*24,2)) | K57: =IF(OR('Projektübersicht'!$F$11="",'Projektübersicht'!$F$13="",'Projektübersicht'!$F$11>'Projektübersicht'!$F$13),"",IF(WORKDAY.INTL('Projektübersicht'!$F$11-1,6,"0000001")<='Projektübersicht'!$F$13,WORKDAY.INTL('Projektübersicht'!$F$11-1,6,"0000001"),""))
H58: =IF(OR(F58="",G58=""),"",ROUND(MOD(G58-F58,1)*24,2)) | K58: =IF(OR('Projektübersicht'!$F$11="",'Projektübersicht'!$F$13="",'Projektübersicht'!$F$11>'Projektübersicht'!$F$13),"",IF(WORKDAY.INTL('Projektübersicht'!$F$11-1,6,"0000001")<='Projektübersicht'!$F$13,WORKDAY.INTL('Projektübersicht'!$F$11-1,6,"0000001"),""))
H59: =IF(OR(F59="",G59=""),"",ROUND(MOD(G59-F59,1)*24,2)) | K59: =IF(OR('Projektübersicht'!$F$11="",'Projektübersicht'!$F$13="",'Projektübersicht'!$F$11>'Projektübersicht'!$F$13),"",IF(WORKDAY.INTL('Projektübersicht'!$F$11-1,6,"0000001")<='Projektübersicht'!$F$13,WORKDAY.INTL('Projektübersicht'!$F$11-1,6,"0000001"),""))
H60: =IF(OR(F60="",G60=""),"",ROUND(MOD(G60-F60,1)*24,2)) | K60: =IF(OR('Projektübersicht'!$F$11="",'Projektübersicht'!$F$13="",'Projektübersicht'!$F$11>'Projektübersicht'!$F$13),"",IF(WORKDAY.INTL('Projektübersicht'!$F$11-1,6,"0000001")<='Projektübersicht'!$F$13,WORKDAY.INTL('Projektübersicht'!$F$11-1,6,"0000001"),""))
H61: =IF(OR(F61="",G61=""),"",ROUND(MOD(G61-F61,1)*24,2)) | K61: =IF(OR('Projektübersicht'!$F$11="",'Projektübersicht'!$F$13="",'Projektübersicht'!$F$11>'Projektübersicht'!$F$13),"",IF(WORKDAY.INTL('Projektübersicht'!$F$11-1,6,"0000001")<='Projektübersicht'!$F$13,WORKDAY.INTL('Projektübersicht'!$F$11-1,6,"0000001"),""))
H62: =IF(OR(F62="",G62=""),"",ROUND(MOD(G62-F62,1)*24,2)) | K62: =IF(OR('Projektübersicht'!$F$11="",'Projektübersicht'!$F$13="",'Projektübersicht'!$F$11>'Projektübersicht'!$F$13),"",IF(WORKDAY.INTL('Projektübersicht'!$F$11-1,6,"0000001")<='Projektübersicht'!$F$13,WORKDAY.INTL('Projektübersicht'!$F$11-1,6,"0000001"),""))
H63: =IF(OR(F63="",G63=""),"",ROUND(MOD(G63-F63,1)*24,2)) | K63: =IF(OR('Projektübersicht'!$F$11="",'Projektübersicht'!$F$13="",'Projektübersicht'!$F$11>'Projektübersicht'!$F$13),"",IF(WORKDAY.INTL('Projektübersicht'!$F$11-1,6,"0000001")<='Projektübersicht'!$F$13,WORKDAY.INTL('Projektübersicht'!$F$11-1,6,"0000001"),""))
H64: =IF(OR(F64="",G64=""),"",ROUND(MOD(G64-F64,1)*24,2)) | K64: =IF(OR('Projektübersicht'!$F$11="",'Projektübersicht'!$F$13="",'Projektübersicht'!$F$11>'Projektübersicht'!$F$13),"",IF(WORKDAY.INTL('Projektübersicht'!$F$11-1,6,"0000001")<='Projektübersicht'!$F$13,WORKDAY.INTL('Projektübersicht'!$F$11-1,6,"0000001"),""))
H65: =IF(OR(F65="",G65=""),"",ROUND(MOD(G65-F65,1)*24,2)) | K65: =IF(OR('Projektübersicht'!$F$11="",'Projektübersicht'!$F$13="",'Projektübersicht'!$F$11>'Projektübersicht'!$F$13),"",IF(WORKDAY.INTL('Projektübersicht'!$F$11-1,6,"0000001")<='Projektübersicht'!$F$13,WORKDAY.INTL('Projektübersicht'!$F$11-1,6,"0000001"),""))
A66: =IF($K66="","",WEEKNUM($K66,21)) | B66: =IF($K66="","",$K66) | C66: =IF($K66="","",$K66) | H66: =IF(OR(F66="",G66=""),"",ROUND(MOD(G66-F66,1)*24,2)) | K66: =IF(OR('Projektübersicht'!$F$11="",'Projektübersicht'!$F$13="",'Projektübersicht'!$F$11>'Projektübersicht'!$F$13),"",IF(WORKDAY.INTL('Projektübersicht'!$F$11-1,7,"0000001")<='Projektübersicht'!$F$13,WORKDAY.INTL('Projektübersicht'!$F$11-1,7,"0000001"),""))
H67: =IF(OR(F67="",G67=""),"",ROUND(MOD(G67-F67,1)*24,2)) | K67: =IF(OR('Projektübersicht'!$F$11="",'Projektübersicht'!$F$13="",'Projektübersicht'!$F$11>'Projektübersicht'!$F$13),"",IF(WORKDAY.INTL('Projektübersicht'!$F$11-1,7,"0000001")<='Projektübersicht'!$F$13,WORKDAY.INTL('Projektübersicht'!$F$11-1,7,"0000001"),""))
H68: =IF(OR(F68="",G68=""),"",ROUND(MOD(G68-F68,1)*24,2)) | K68: =IF(OR('Projektübersicht'!$F$11="",'Projektübersicht'!$F$13="",'Projektübersicht'!$F$11>'Projektübersicht'!$F$13),"",IF(WORKDAY.INTL('Projektübersicht'!$F$11-1,7,"0000001")<='Projektübersicht'!$F$13,WORKDAY.INTL('Projektübersicht'!$F$11-1,7,"0000001"),""))
H69: =IF(OR(F69="",G69=""),"",ROUND(MOD(G69-F69,1)*24,2)) | K69: =IF(OR('Projektübersicht'!$F$11="",'Projektübersicht'!$F$13="",'Projektübersicht'!$F$11>'Projektübersicht'!$F$13),"",IF(WORKDAY.INTL('Projektübersicht'!$F$11-1,7,"0000001")<='Projektübersicht'!$F$13,WORKDAY.INTL('Projektübersicht'!$F$11-1,7,"0000001"),""))
H70: =IF(OR(F70="",G70=""),"",ROUND(MOD(G70-F70,1)*24,2)) | K70: =IF(OR('Projektübersicht'!$F$11="",'Projektübersicht'!$F$13="",'Projektübersicht'!$F$11>'Projektübersicht'!$F$13),"",IF(WORKDAY.INTL('Projektübersicht'!$F$11-1,7,"0000001")<='Projektübersicht'!$F$13,WORKDAY.INTL('Projektübersicht'!$F$11-1,7,"0000001"),""))
H71: =IF(OR(F71="",G71=""),"",ROUND(MOD(G71-F71,1)*24,2)) | K71: =IF(OR('Projektübersicht'!$F$11="",'Projektübersicht'!$F$13="",'Projektübersicht'!$F$11>'Projektübersicht'!$F$13),"",IF(WORKDAY.INTL('Projektübersicht'!$F$11-1,7,"0000001")<='Projektübersicht'!$F$13,WORKDAY.INTL('Projektübersicht'!$F$11-1,7,"0000001"),""))
H72: =IF(OR(F72="",G72=""),"",ROUND(MOD(G72-F72,1)*24,2)) | K72: =IF(OR('Projektübersicht'!$F$11="",'Projektübersicht'!$F$13="",'Projektübersicht'!$F$11>'Projektübersicht'!$F$13),"",IF(WORKDAY.INTL('Projektübersicht'!$F$11-1,7,"0000001")<='Projektübersicht'!$F$13,WORKDAY.INTL('Projektübersicht'!$F$11-1,7,"0000001"),""))
H73: =IF(OR(F73="",G73=""),"",ROUND(MOD(G73-F73,1)*24,2)) | K73: =IF(OR('Projektübersicht'!$F$11="",'Projektübersicht'!$F$13="",'Projektübersicht'!$F$11>'Projektübersicht'!$F$13),"",IF(WORKDAY.INTL('Projektübersicht'!$F$11-1,7,"0000001")<='Projektübersicht'!$F$13,WORKDAY.INTL('Projektübersicht'!$F$11-1,7,"0000001"),""))
H74: =IF(OR(F74="",G74=""),"",ROUND(MOD(G74-F74,1)*24,2)) | K74: =IF(OR('Projektübersicht'!$F$11="",'Projektübersicht'!$F$13="",'Projektübersicht'!$F$11>'Projektübersicht'!$F$13),"",IF(WORKDAY.INTL('Projektübersicht'!$F$11-1,7,"0000001")<='Projektübersicht'!$F$13,WORKDAY.INTL('Projektübersicht'!$F$11-1,7,"0000001"),""))
H75: =IF(OR(F75="",G75=""),"",ROUND(MOD(G75-F75,1)*24,2)) | K75: =IF(OR('Projektübersicht'!$F$11="",'Projektübersicht'!$F$13="",'Projektübersicht'!$F$11>'Projektübersicht'!$F$13),"",IF(WORKDAY.INTL('Projektübersicht'!$F$11-1,7,"0000001")<='Projektübersicht'!$F$13,WORKDAY.INTL('Projektübersicht'!$F$11-1,7,"0000001"),""))
A76: =IF($K76="","",WEEKNUM($K76,21)) | B76: =IF($K76="","",$K76) | C76: =IF($K76="","",$K76) | H76: =IF(OR(F76="",G76=""),"",ROUND(MOD(G76-F76,1)*24,2)) | K76: =IF(OR('Projektübersicht'!$F$11="",'Projektübersicht'!$F$13="",'Projektübersicht'!$F$11>'Projektübersicht'!$F$13),"",IF(WORKDAY.INTL('Projektübersicht'!$F$11-1,8,"0000001")<='Projektübersicht'!$F$13,WORKDAY.INTL('Projektübersicht'!$F$11-1,8,"0000001"),""))
H77: =IF(OR(F77="",G77=""),"",ROUND(MOD(G77-F77,1)*24,2)) | K77: =IF(OR('Projektübersicht'!$F$11="",'Projektübersicht'!$F$13="",'Projektübersicht'!$F$11>'Projektübersicht'!$F$13),"",IF(WORKDAY.INTL('Projektübersicht'!$F$11-1,8,"0000001")<='Projektübersicht'!$F$13,WORKDAY.INTL('Projektübersicht'!$F$11-1,8,"0000001"),""))
H78: =IF(OR(F78="",G78=""),"",ROUND(MOD(G78-F78,1)*24,2)) | K78: =IF(OR('Projektübersicht'!$F$11="",'Projektübersicht'!$F$13="",'Projektübersicht'!$F$11>'Projektübersicht'!$F$13),"",IF(WORKDAY.INTL('Projektübersicht'!$F$11-1,8,"0000001")<='Projektübersicht'!$F$13,WORKDAY.INTL('Projektübersicht'!$F$11-1,8,"0000001"),""))
H79: =IF(OR(F79="",G79=""),"",ROUND(MOD(G79-F79,1)*24,2)) | K79: =IF(OR('Projektübersicht'!$F$11="",'Projektübersicht'!$F$13="",'Projektübersicht'!$F$11>'Projektübersicht'!$F$13),"",IF(WORKDAY.INTL('Projektübersicht'!$F$11-1,8,"0000001")<='Projektübersicht'!$F$13,WORKDAY.INTL('Projektübersicht'!$F$11-1,8,"0000001"),""))
H80: =IF(OR(F80="",G80=""),"",ROUND(MOD(G80-F80,1)*24,2)) | K80: =IF(OR('Projektübersicht'!$F$11="",'Projektübersicht'!$F$13="",'Projektübersicht'!$F$11>'Projektübersicht'!$F$13),"",IF(WORKDAY.INTL('Projektübersicht'!$F$11-1,8,"0000001")<='Projektübersicht'!$F$13,WORKDAY.INTL('Projektübersicht'!$F$11-1,8,"0000001"),""))
H81: =IF(OR(F81="",G81=""),"",ROUND(MOD(G81-F81,1)*24,2)) | K81: =IF(OR('Projektübersicht'!$F$11="",'Projektübersicht'!$F$13="",'Projektübersicht'!$F$11>'Projektübersicht'!$F$13),"",IF(WORKDAY.INTL('Projektübersicht'!$F$11-1,8,"0000001")<='Projektübersicht'!$F$13,WORKDAY.INTL('Projektübersicht'!$F$11-1,8,"0000001"),""))
H82: =IF(OR(F82="",G82=""),"",ROUND(MOD(G82-F82,1)*24,2)) | K82: =IF(OR('Projektübersicht'!$F$11="",'Projektübersicht'!$F$13="",'Projektübersicht'!$F$11>'Projektübersicht'!$F$13),"",IF(WORKDAY.INTL('Projektübersicht'!$F$11-1,8,"0000001")<='Projektübersicht'!$F$13,WORKDAY.INTL('Projektübersicht'!$F$11-1,8,"0000001"),""))
H83: =IF(OR(F83="",G83=""),"",ROUND(MOD(G83-F83,1)*24,2)) | K83: =IF(OR('Projektübersicht'!$F$11="",'Projektübersicht'!$F$13="",'Projektübersicht'!$F$11>'Projektübersicht'!$F$13),"",IF(WORKDAY.INTL('Projektübersicht'!$F$11-1,8,"0000001")<='Projektübersicht'!$F$13,WORKDAY.INTL('Projektübersicht'!$F$11-1,8,"0000001"),""))
H84: =IF(OR(F84="",G84=""),"",ROUND(MOD(G84-F84,1)*24,2)) | K84: =IF(OR('Projektübersicht'!$F$11="",'Projektübersicht'!$F$13="",'Projektübersicht'!$F$11>'Projektübersicht'!$F$13),"",IF(WORKDAY.INTL('Projektübersicht'!$F$11-1,8,"0000001")<='Projektübersicht'!$F$13,WORKDAY.INTL('Projektübersicht'!$F$11-1,8,"0000001"),""))
H85: =IF(OR(F85="",G85=""),"",ROUND(MOD(G85-F85,1)*24,2)) | K85: =IF(OR('Projektübersicht'!$F$11="",'Projektübersicht'!$F$13="",'Projektübersicht'!$F$11>'Projektübersicht'!$F$13),"",IF(WORKDAY.INTL('Projektübersicht'!$F$11-1,8,"0000001")<='Projektübersicht'!$F$13,WORKDAY.INTL('Projektübersicht'!$F$11-1,8,"0000001"),""))
A86: =IF($K86="","",WEEKNUM($K86,21)) | B86: =IF($K86="","",$K86) | C86: =IF($K86="","",$K86) | H86: =IF(OR(F86="",G86=""),"",ROUND(MOD(G86-F86,1)*24,2)) | K86: =IF(OR('Projektübersicht'!$F$11="",'Projektübersicht'!$F$13="",'Projektübersicht'!$F$11>'Projektübersicht'!$F$13),"",IF(WORKDAY.INTL('Projektübersicht'!$F$11-1,9,"0000001")<='Projektübersicht'!$F$13,WORKDAY.INTL('Projektübersicht'!$F$11-1,9,"0000001"),""))
H87: =IF(OR(F87="",G87=""),"",ROUND(MOD(G87-F87,1)*24,2)) | K87: =IF(OR('Projektübersicht'!$F$11="",'Projektübersicht'!$F$13="",'Projektübersicht'!$F$11>'Projektübersicht'!$F$13),"",IF(WORKDAY.INTL('Projektübersicht'!$F$11-1,9,"0000001")<='Projektübersicht'!$F$13,WORKDAY.INTL('Projektübersicht'!$F$11-1,9,"0000001"),""))
H88: =IF(OR(F88="",G88=""),"",ROUND(MOD(G88-F88,1)*24,2)) | K88: =IF(OR('Projektübersicht'!$F$11="",'Projektübersicht'!$F$13="",'Projektübersicht'!$F$11>'Projektübersicht'!$F$13),"",IF(WORKDAY.INTL('Projektübersicht'!$F$11-1,9,"0000001")<='Projektübersicht'!$F$13,WORKDAY.INTL('Projektübersicht'!$F$11-1,9,"0000001"),""))
H89: =IF(OR(F89="",G89=""),"",ROUND(MOD(G89-F89,1)*24,2)) | K89: =IF(OR('Projektübersicht'!$F$11="",'Projektübersicht'!$F$13="",'Projektübersicht'!$F$11>'Projektübersicht'!$F$13),"",IF(WORKDAY.INTL('Projektübersicht'!$F$11-1,9,"0000001")<='Projektübersicht'!$F$13,WORKDAY.INTL('Projektübersicht'!$F$11-1,9,"0000001"),""))
H90: =IF(OR(F90="",G90=""),"",ROUND(MOD(G90-F90,1)*24,2)) | K90: =IF(OR('Projektübersicht'!$F$11="",'Projektübersicht'!$F$13="",'Projektübersicht'!$F$11>'Projektübersicht'!$F$13),"",IF(WORKDAY.INTL('Projektübersicht'!$F$11-1,9,"0000001")<='Projektübersicht'!$F$13,WORKDAY.INTL('Projektübersicht'!$F$11-1,9,"0000001"),""))
H91: =IF(OR(F91="",G91=""),"",ROUND(MOD(G91-F91,1)*24,2)) | K91: =IF(OR('Projektübersicht'!$F$11="",'Projektübersicht'!$F$13="",'Projektübersicht'!$F$11>'Projektübersicht'!$F$13),"",IF(WORKDAY.INTL('Projektübersicht'!$F$11-1,9,"0000001")<='Projektübersicht'!$F$13,WORKDAY.INTL('Projektübersicht'!$F$11-1,9,"0000001"),""))
H92: =IF(OR(F92="",G92=""),"",ROUND(MOD(G92-F92,1)*24,2)) | K92: =IF(OR('Projektübersicht'!$F$11="",'Projektübersicht'!$F$13="",'Projektübersicht'!$F$11>'Projektübersicht'!$F$13),"",IF(WORKDAY.INTL('Projektübersicht'!$F$11-1,9,"0000001")<='Projektübersicht'!$F$13,WORKDAY.INTL('Projektübersicht'!$F$11-1,9,"0000001"),""))
H93: =IF(OR(F93="",G93=""),"",ROUND(MOD(G93-F93,1)*24,2)) | K93: =IF(OR('Projektübersicht'!$F$11="",'Projektübersicht'!$F$13="",'Projektübersicht'!$F$11>'Projektübersicht'!$F$13),"",IF(WORKDAY.INTL('Projektübersicht'!$F$11-1,9,"0000001")<='Projektübersicht'!$F$13,WORKDAY.INTL('Projektübersicht'!$F$11-1,9,"0000001"),""))
H94: =IF(OR(F94="",G94=""),"",ROUND(MOD(G94-F94,1)*24,2)) | K94: =IF(OR('Projektübersicht'!$F$11="",'Projektübersicht'!$F$13="",'Projektübersicht'!$F$11>'Projektübersicht'!$F$13),"",IF(WORKDAY.INTL('Projektübersicht'!$F$11-1,9,"0000001")<='Projektübersicht'!$F$13,WORKDAY.INTL('Projektübersicht'!$F$11-1,9,"0000001"),""))
H95: =IF(OR(F95="",G95=""),"",ROUND(MOD(G95-F95,1)*24,2)) | K95: =IF(OR('Projektübersicht'!$F$11="",'Projektübersicht'!$F$13="",'Projektübersicht'!$F$11>'Projektübersicht'!$F$13),"",IF(WORKDAY.INTL('Projektübersicht'!$F$11-1,9,"0000001")<='Projektübersicht'!$F$13,WORKDAY.INTL('Projektübersicht'!$F$11-1,9,"0000001"),""))
A96: =IF($K96="","",WEEKNUM($K96,21)) | B96: =IF($K96="","",$K96) | C96: =IF($K96="","",$K96) | H96: =IF(OR(F96="",G96=""),"",ROUND(MOD(G96-F96,1)*24,2)) | K96: =IF(OR('Projektübersicht'!$F$11="",'Projektübersicht'!$F$13="",'Projektübersicht'!$F$11>'Projektübersicht'!$F$13),"",IF(WORKDAY.INTL('Projektübersicht'!$F$11-1,10,"0000001")<='Projektübersicht'!$F$13,WORKDAY.INTL('Projektübersicht'!$F$11-1,10,"0000001"),""))
H97: =IF(OR(F97="",G97=""),"",ROUND(MOD(G97-F97,1)*24,2)) | K97: =IF(OR('Projektübersicht'!$F$11="",'Projektübersicht'!$F$13="",'Projektübersicht'!$F$11>'Projektübersicht'!$F$13),"",IF(WORKDAY.INTL('Projektübersicht'!$F$11-1,10,"0000001")<='Projektübersicht'!$F$13,WORKDAY.INTL('Projektübersicht'!$F$11-1,10,"0000001"),""))
H98: =IF(OR(F98="",G98=""),"",ROUND(MOD(G98-F98,1)*24,2)) | K98: =IF(OR('Projektübersicht'!$F$11="",'Projektübersicht'!$F$13="",'Projektübersicht'!$F$11>'Projektübersicht'!$F$13),"",IF(WORKDAY.INTL('Projektübersicht'!$F$11-1,10,"0000001")<='Projektübersicht'!$F$13,WORKDAY.INTL('Projektübersicht'!$F$11-1,10,"0000001"),""))
H99: =IF(OR(F99="",G99=""),"",ROUND(MOD(G99-F99,1)*24,2)) | K99: =IF(OR('Projektübersicht'!$F$11="",'Projektübersicht'!$F$13="",'Projektübersicht'!$F$11>'Projektübersicht'!$F$13),"",IF(WORKDAY.INTL('Projektübersicht'!$F$11-1,10,"0000001")<='Projektübersicht'!$F$13,WORKDAY.INTL('Projektübersicht'!$F$11-1,10,"0000001"),""))
H100: =IF(OR(F100="",G100=""),"",ROUND(MOD(G100-F100,1)*24,2)) | K100: =IF(OR('Projektübersicht'!$F$11="",'Projektübersicht'!$F$13="",'Projektübersicht'!$F$11>'Projektübersicht'!$F$13),"",IF(WORKDAY.INTL('Projektübersicht'!$F$11-1,10,"0000001")<='Projektübersicht'!$F$13,WORKDAY.INTL('Projektübersicht'!$F$11-1,10,"0000001"),""))
H101: =IF(OR(F101="",G101=""),"",ROUND(MOD(G101-F101,1)*24,2)) | K101: =IF(OR('Projektübersicht'!$F$11="",'Projektübersicht'!$F$13="",'Projektübersicht'!$F$11>'Projektübersicht'!$F$13),"",IF(WORKDAY.INTL('Projektübersicht'!$F$11-1,10,"0000001")<='Projektübersicht'!$F$13,WORKDAY.INTL('Projektübersicht'!$F$11-1,10,"0000001"),""))
...

Sheet Zeiterfassung Export
A1: ZEITERFASSUNG · EXPORT | L1: ← ZUM COCKPIT
A3: Hinweis: Der echte PDF-Export wird dynamisch aus der Zeiterfassung erzeugt (2 KW je Blatt, nur belegte Datensätze).
A4: =IF('Projektübersicht'!B9="","BAUVORHABEN","BAUVORHABEN · "&'Projektübersicht'!B9) | D4: =IF('Projektübersicht'!B13="","AUFTRAGGEBER","AUFTRAGGEBER · "&'Projektübersicht'!B13) | G4: =IF(AND('Projektübersicht'!$F$11="",'Projektübersicht'!$F$13=""),"BAUZEIT",IF(OR('Projektübersicht'!$F$11="",'Projektübersicht'!$F$13=""),"BAUZEIT · Stammdaten unvollständig","BAUZEIT · "&TEXT('Projektübersicht'!$F$11,"dd.mm.yyyy")&" – "&TEXT('Projektübersicht'!$F$13,"dd.mm.yyyy")))
A5: KW | B5: DATUM | C5: TAG | D5: MITARBEITER | E5: GEWERK | F5: ARBEITSANFANG | G5: ARBEITSENDE | H5: ARBEITSSTUNDEN | I5: ARBEITEN / LEISTUNGEN DES TAGES | J5: TAGESBEMERKUNG
A6: =IF($K6="","",WEEKNUM(INDEX(Zeiterfassung!$K$6:$K$3665,$K6),21)) | B6: =IF($K6="","",INDEX(Zeiterfassung!$K$6:$K$3665,$K6)) | C6: =IF($K6="","",INDEX(Zeiterfassung!$K$6:$K$3665,$K6)) | D6: =IF($K6="","",INDEX(Zeiterfassung!$D$6:$D$3665,$K6)) | E6: =IF($K6="","",INDEX(Zeiterfassung!$E$6:$E$3665,$K6)) | F6: =IF($K6="","",INDEX(Zeiterfassung!$F$6:$F$3665,$K6)) | G6: =IF($K6="","",INDEX(Zeiterfassung!$G$6:$G$3665,$K6)) | H6: =IF($K6="","",INDEX(Zeiterfassung!$H$6:$H$3665,$K6)) | I6: =IF($K6="","",INDEX(Zeiterfassung!$I$6:$I$3665,MATCH(INDEX(Zeiterfassung!$K$6:$K$3665,$K6),Zeiterfassung!$K$6:$K$3665,0))) | J6: =IF($K6="","",INDEX(Zeiterfassung!$J$6:$J$3665,MATCH(INDEX(Zeiterfassung!$K$6:$K$3665,$K6),Zeiterfassung!$K$6:$K$3665,0))) | K6: =IFERROR(AGGREGATE(15,6,(ROW(Zeiterfassung!$D$6:$D$3665)-ROW(Zeiterfassung!$D$6)+1)/(Zeiterfassung!$D$6:$D$3665<>""),1),"")
A7: =IF($K7="","",WEEKNUM(INDEX(Zeiterfassung!$K$6:$K$3665,$K7),21)) | B7: =IF($K7="","",INDEX(Zeiterfassung!$K$6:$K$3665,$K7)) | C7: =IF($K7="","",INDEX(Zeiterfassung!$K$6:$K$3665,$K7)) | D7: =IF($K7="","",INDEX(Zeiterfassung!$D$6:$D$3665,$K7)) | E7: =IF($K7="","",INDEX(Zeiterfassung!$E$6:$E$3665,$K7)) | F7: =IF($K7="","",INDEX(Zeiterfassung!$F$6:$F$3665,$K7)) | G7: =IF($K7="","",INDEX(Zeiterfassung!$G$6:$G$3665,$K7)) | H7: =IF($K7="","",INDEX(Zeiterfassung!$H$6:$H$3665,$K7)) | I7: =IF(B7=B6,"",IF($K7="","",INDEX(Zeiterfassung!$I$6:$I$3665,MATCH(INDEX(Zeiterfassung!$K$6:$K$3665,$K7),Zeiterfassung!$K$6:$K$3665,0)))) | J7: =IF(B7=B6,"",IF($K7="","",INDEX(Zeiterfassung!$J$6:$J$3665,MATCH(INDEX(Zeiterfassung!$K$6:$K$3665,$K7),Zeiterfassung!$K$6:$K$3665,0)))) | K7: =IFERROR(AGGREGATE(15,6,(ROW(Zeiterfassung!$D$6:$D$3665)-ROW(Zeiterfassung!$D$6)+1)/(Zeiterfassung!$D$6:$D$3665<>""),2),"")
A8: =IF($K8="","",WEEKNUM(INDEX(Zeiterfassung!$K$6:$K$3665,$K8),21)) | B8: =IF($K8="","",INDEX(Zeiterfassung!$K$6:$K$3665,$K8)) | C8: =IF($K8="","",INDEX(Zeiterfassung!$K$6:$K$3665,$K8)) | D8: =IF($K8="","",INDEX(Zeiterfassung!$D$6:$D$3665,$K8)) | E8: =IF($K8="","",INDEX(Zeiterfassung!$E$6:$E$3665,$K8)) | F8: =IF($K8="","",INDEX(Zeiterfassung!$F$6:$F$3665,$K8)) | G8: =IF($K8="","",INDEX(Zeiterfassung!$G$6:$G$3665,$K8)) | H8: =IF($K8="","",INDEX(Zeiterfassung!$H$6:$H$3665,$K8)) | I8: =IF(B8=B7,"",IF($K8="","",INDEX(Zeiterfassung!$I$6:$I$3665,MATCH(INDEX(Zeiterfassung!$K$6:$K$3665,$K8),Zeiterfassung!$K$6:$K$3665,0)))) | J8: =IF(B8=B7,"",IF($K8="","",INDEX(Zeiterfassung!$J$6:$J$3665,MATCH(INDEX(Zeiterfassung!$K$6:$K$3665,$K8),Zeiterfassung!$K$6:$K$3665,0)))) | K8: =IFERROR(AGGREGATE(15,6,(ROW(Zeiterfassung!$D$6:$D$3665)-ROW(Zeiterfassung!$D$6)+1)/(Zeiterfassung!$D$6:$D$3665<>""),3),"")
A9: =IF($K9="","",WEEKNUM(INDEX(Zeiterfassung!$K$6:$K$3665,$K9),21)) | B9: =IF($K9="","",INDEX(Zeiterfassung!$K$6:$K$3665,$K9)) | C9: =IF($K9="","",INDEX(Zeiterfassung!$K$6:$K$3665,$K9)) | D9: =IF($K9="","",INDEX(Zeiterfassung!$D$6:$D$3665,$K9)) | E9: =IF($K9="","",INDEX(Zeiterfassung!$E$6:$E$3665,$K9)) | F9: =IF($K9="","",INDEX(Zeiterfassung!$F$6:$F$3665,$K9)) | G9: =IF($K9="","",INDEX(Zeiterfassung!$G$6:$G$3665,$K9)) | H9: =IF($K9="","",INDEX(Zeiterfassung!$H$6:$H$3665,$K9)) | I9: =IF(B9=B8,"",IF($K9="","",INDEX(Zeiterfassung!$I$6:$I$3665,MATCH(INDEX(Zeiterfassung!$K$6:$K$3665,$K9),Zeiterfassung!$K$6:$K$3665,0)))) | J9: =IF(B9=B8,"",IF($K9="","",INDEX(Zeiterfassung!$J$6:$J$3665,MATCH(INDEX(Zeiterfassung!$K$6:$K$3665,$K9),Zeiterfassung!$K$6:$K$3665,0)))) | K9: =IFERROR(AGGREGATE(15,6,(ROW(Zeiterfassung!$D$6:$D$3665)-ROW(Zeiterfassung!$D$6)+1)/(Zeiterfassung!$D$6:$D$3665<>""),4),"")
A10: =IF($K10="","",WEEKNUM(INDEX(Zeiterfassung!$K$6:$K$3665,$K10),21)) | B10: =IF($K10="","",INDEX(Zeiterfassung!$K$6:$K$3665,$K10)) | C10: =IF($K10="","",INDEX(Zeiterfassung!$K$6:$K$3665,$K10)) | D10: =IF($K10="","",INDEX(Zeiterfassung!$D$6:$D$3665,$K10)) | E10: =IF($K10="","",INDEX(Zeiterfassung!$E$6:$E$3665,$K10)) | F10: =IF($K10="","",INDEX(Zeiterfassung!$F$6:$F$3665,$K10)) | G10: =IF($K10="","",INDEX(Zeiterfassung!$G$6:$G$3665,$K10)) | H10: =IF($K10="","",INDEX(Zeiterfassung!$H$6:$H$3665,$K10)) | I10: =IF(B10=B9,"",IF($K10="","",INDEX(Zeiterfassung!$I$6:$I$3665,MATCH(INDEX(Zeiterfassung!$K$6:$K$3665,$K10),Zeiterfassung!$K$6:$K$3665,0)))) | J10: =IF(B10=B9,"",IF($K10="","",INDEX(Zeiterfassung!$J$6:$J$3665,MATCH(INDEX(Zeiterfassung!$K$6:$K$3665,$K10),Zeiterfassung!$K$6:$K$3665,0)))) | K10: =IFERROR(AGGREGATE(15,6,(ROW(Zeiterfassung!$D$6:$D$3665)-ROW(Zeiterfassung!$D$6)+1)/(Zeiterfassung!$D$6:$D$3665<>""),5),"")
A11: =IF($K11="","",WEEKNUM(INDEX(Zeiterfassung!$K$6:$K$3665,$K11),21)) | B11: =IF($K11="","",INDEX(Zeiterfassung!$K$6:$K$3665,$K11)) | C11: =IF($K11="","",INDEX(Zeiterfassung!$K$6:$K$3665,$K11)) | D11: =IF($K11="","",INDEX(Zeiterfassung!$D$6:$D$3665,$K11)) | E11: =IF($K11="","",INDEX(Zeiterfassung!$E$6:$E$3665,$K11)) | F11: =IF($K11="","",INDEX(Zeiterfassung!$F$6:$F$3665,$K11)) | G11: =IF($K11="","",INDEX(Zeiterfassung!$G$6:$G$3665,$K11)) | H11: =IF($K11="","",INDEX(Zeiterfassung!$H$6:$H$3665,$K11)) | I11: =IF(B11=B10,"",IF($K11="","",INDEX(Zeiterfassung!$I$6:$I$3665,MATCH(INDEX(Zeiterfassung!$K$6:$K$3665,$K11),Zeiterfassung!$K$6:$K$3665,0)))) | J11: =IF(B11=B10,"",IF($K11="","",INDEX(Zeiterfassung!$J$6:$J$3665,MATCH(INDEX(Zeiterfassung!$K$6:$K$3665,$K11),Zeiterfassung!$K$6:$K$3665,0)))) | K11: =IFERROR(AGGREGATE(15,6,(ROW(Zeiterfassung!$D$6:$D$3665)-ROW(Zeiterfassung!$D$6)+1)/(Zeiterfassung!$D$6:$D$3665<>""),6),"")
A12: =IF($K12="","",WEEKNUM(INDEX(Zeiterfassung!$K$6:$K$3665,$K12),21)) | B12: =IF($K12="","",INDEX(Zeiterfassung!$K$6:$K$3665,$K12)) | C12: =IF($K12="","",INDEX(Zeiterfassung!$K$6:$K$3665,$K12)) | D12: =IF($K12="","",INDEX(Zeiterfassung!$D$6:$D$3665,$K12)) | E12: =IF($K12="","",INDEX(Zeiterfassung!$E$6:$E$3665,$K12)) | F12: =IF($K12="","",INDEX(Zeiterfassung!$F$6:$F$3665,$K12)) | G12: =IF($K12="","",INDEX(Zeiterfassung!$G$6:$G$3665,$K12)) | H12: =IF($K12="","",INDEX(Zeiterfassung!$H$6:$H$3665,$K12)) | I12: =IF(B12=B11,"",IF($K12="","",INDEX(Zeiterfassung!$I$6:$I$3665,MATCH(INDEX(Zeiterfassung!$K$6:$K$3665,$K12),Zeiterfassung!$K$6:$K$3665,0)))) | J12: =IF(B12=B11,"",IF($K12="","",INDEX(Zeiterfassung!$J$6:$J$3665,MATCH(INDEX(Zeiterfassung!$K$6:$K$3665,$K12),Zeiterfassung!$K$6:$K$3665,0)))) | K12: =IFERROR(AGGREGATE(15,6,(ROW(Zeiterfassung!$D$6:$D$3665)-ROW(Zeiterfassung!$D$6)+1)/(Zeiterfassung!$D$6:$D$3665<>""),7),"")
A13: =IF($K13="","",WEEKNUM(INDEX(Zeiterfassung!$K$6:$K$3665,$K13),21)) | B13: =IF($K13="","",INDEX(Zeiterfassung!$K$6:$K$3665,$K13)) | C13: =IF($K13="","",INDEX(Zeiterfassung!$K$6:$K$3665,$K13)) | D13: =IF($K13="","",INDEX(Zeiterfassung!$D$6:$D$3665,$K13)) | E13: =IF($K13="","",INDEX(Zeiterfassung!$E$6:$E$3665,$K13)) | F13: =IF($K13="","",INDEX(Zeiterfassung!$F$6:$F$3665,$K13)) | G13: =IF($K13="","",INDEX(Zeiterfassung!$G$6:$G$3665,$K13)) | H13: =IF($K13="","",INDEX(Zeiterfassung!$H$6:$H$3665,$K13)) | I13: =IF(B13=B12,"",IF($K13="","",INDEX(Zeiterfassung!$I$6:$I$3665,MATCH(INDEX(Zeiterfassung!$K$6:$K$3665,$K13),Zeiterfassung!$K$6:$K$3665,0)))) | J13: =IF(B13=B12,"",IF($K13="","",INDEX(Zeiterfassung!$J$6:$J$3665,MATCH(INDEX(Zeiterfassung!$K$6:$K$3665,$K13),Zeiterfassung!$K$6:$K$3665,0)))) | K13: =IFERROR(AGGREGATE(15,6,(ROW(Zeiterfassung!$D$6:$D$3665)-ROW(Zeiterfassung!$D$6)+1)/(Zeiterfassung!$D$6:$D$3665<>""),8),"")
A14: =IF($K14="","",WEEKNUM(INDEX(Zeiterfassung!$K$6:$K$3665,$K14),21)) | B14: =IF($K14="","",INDEX(Zeiterfassung!$K$6:$K$3665,$K14)) | C14: =IF($K14="","",INDEX(Zeiterfassung!$K$6:$K$3665,$K14)) | D14: =IF($K14="","",INDEX(Zeiterfassung!$D$6:$D$3665,$K14)) | E14: =IF($K14="","",INDEX(Zeiterfassung!$E$6:$E$3665,$K14)) | F14: =IF($K14="","",INDEX(Zeiterfassung!$F$6:$F$3665,$K14)) | G14: =IF($K14="","",INDEX(Zeiterfassung!$G$6:$G$3665,$K14)) | H14: =IF($K14="","",INDEX(Zeiterfassung!$H$6:$H$3665,$K14)) | I14: =IF(B14=B13,"",IF($K14="","",INDEX(Zeiterfassung!$I$6:$I$3665,MATCH(INDEX(Zeiterfassung!$K$6:$K$3665,$K14),Zeiterfassung!$K$6:$K$3665,0)))) | J14: =IF(B14=B13,"",IF($K14="","",INDEX(Zeiterfassung!$J$6:$J$3665,MATCH(INDEX(Zeiterfassung!$K$6:$K$3665,$K14),Zeiterfassung!$K$6:$K$3665,0)))) | K14: =IFERROR(AGGREGATE(15,6,(ROW(Zeiterfassung!$D$6:$D$3665)-ROW(Zeiterfassung!$D$6)+1)/(Zeiterfassung!$D$6:$D$3665<>""),9),"")
A15: =IF($K15="","",WEEKNUM(INDEX(Zeiterfassung!$K$6:$K$3665,$K15),21)) | B15: =IF($K15="","",INDEX(Zeiterfassung!$K$6:$K$3665,$K15)) | C15: =IF($K15="","",INDEX(Zeiterfassung!$K$6:$K$3665,$K15)) | D15: =IF($K15="","",INDEX(Zeiterfassung!$D$6:$D$3665,$K15)) | E15: =IF($K15="","",INDEX(Zeiterfassung!$E$6:$E$3665,$K15)) | F15: =IF($K15="","",INDEX(Zeiterfassung!$F$6:$F$3665,$K15)) | G15: =IF($K15="","",INDEX(Zeiterfassung!$G$6:$G$3665,$K15)) | H15: =IF($K15="","",INDEX(Zeiterfassung!$H$6:$H$3665,$K15)) | I15: =IF(B15=B14,"",IF($K15="","",INDEX(Zeiterfassung!$I$6:$I$3665,MATCH(INDEX(Zeiterfassung!$K$6:$K$3665,$K15),Zeiterfassung!$K$6:$K$3665,0)))) | J15: =IF(B15=B14,"",IF($K15="","",INDEX(Zeiterfassung!$J$6:$J$3665,MATCH(INDEX(Zeiterfassung!$K$6:$K$3665,$K15),Zeiterfassung!$K$6:$K$3665,0)))) | K15: =IFERROR(AGGREGATE(15,6,(ROW(Zeiterfassung!$D$6:$D$3665)-ROW(Zeiterfassung!$D$6)+1)/(Zeiterfassung!$D$6:$D$3665<>""),10),"")
A16: =IF($K16="","",WEEKNUM(INDEX(Zeiterfassung!$K$6:$K$3665,$K16),21)) | B16: =IF($K16="","",INDEX(Zeiterfassung!$K$6:$K$3665,$K16)) | C16: =IF($K16="","",INDEX(Zeiterfassung!$K$6:$K$3665,$K16)) | D16: =IF($K16="","",INDEX(Zeiterfassung!$D$6:$D$3665,$K16)) | E16: =IF($K16="","",INDEX(Zeiterfassung!$E$6:$E$3665,$K16)) | F16: =IF($K16="","",INDEX(Zeiterfassung!$F$6:$F$3665,$K16)) | G16: =IF($K16="","",INDEX(Zeiterfassung!$G$6:$G$3665,$K16)) | H16: =IF($K16="","",INDEX(Zeiterfassung!$H$6:$H$3665,$K16)) | I16: =IF(B16=B15,"",IF($K16="","",INDEX(Zeiterfassung!$I$6:$I$3665,MATCH(INDEX(Zeiterfassung!$K$6:$K$3665,$K16),Zeiterfassung!$K$6:$K$3665,0)))) | J16: =IF(B16=B15,"",IF($K16="","",INDEX(Zeiterfassung!$J$6:$J$3665,MATCH(INDEX(Zeiterfassung!$K$6:$K$3665,$K16),Zeiterfassung!$K$6:$K$3665,0)))) | K16: =IFERROR(AGGREGATE(15,6,(ROW(Zeiterfassung!$D$6:$D$3665)-ROW(Zeiterfassung!$D$6)+1)/(Zeiterfassung!$D$6:$D$3665<>""),11),"")
A17: =IF($K17="","",WEEKNUM(INDEX(Zeiterfassung!$K$6:$K$3665,$K17),21)) | B17: =IF($K17="","",INDEX(Zeiterfassung!$K$6:$K$3665,$K17)) | C17: =IF($K17="","",INDEX(Zeiterfassung!$K$6:$K$3665,$K17)) | D17: =IF($K17="","",INDEX(Zeiterfassung!$D$6:$D$3665,$K17)) | E17: =IF($K17="","",INDEX(Zeiterfassung!$E$6:$E$3665,$K17)) | F17: =IF($K17="","",INDEX(Zeiterfassung!$F$6:$F$3665,$K17)) | G17: =IF($K17="","",INDEX(Zeiterfassung!$G$6:$G$3665,$K17)) | H17: =IF($K17="","",INDEX(Zeiterfassung!$H$6:$H$3665,$K17)) | I17: =IF(B17=B16,"",IF($K17="","",INDEX(Zeiterfassung!$I$6:$I$3665,MATCH(INDEX(Zeiterfassung!$K$6:$K$3665,$K17),Zeiterfassung!$K$6:$K$3665,0)))) | J17: =IF(B17=B16,"",IF($K17="","",INDEX(Zeiterfassung!$J$6:$J$3665,MATCH(INDEX(Zeiterfassung!$K$6:$K$3665,$K17),Zeiterfassung!$K$6:$K$3665,0)))) | K17: =IFERROR(AGGREGATE(15,6,(ROW(Zeiterfassung!$D$6:$D$3665)-ROW(Zeiterfassung!$D$6)+1)/(Zeiterfassung!$D$6:$D$3665<>""),12),"")
A18: =IF($K18="","",WEEKNUM(INDEX(Zeiterfassung!$K$6:$K$3665,$K18),21)) | B18: =IF($K18="","",INDEX(Zeiterfassung!$K$6:$K$3665,$K18)) | C18: =IF($K18="","",INDEX(Zeiterfassung!$K$6:$K$3665,$K18)) | D18: =IF($K18="","",INDEX(Zeiterfassung!$D$6:$D$3665,$K18)) | E18: =IF($K18="","",INDEX(Zeiterfassung!$E$6:$E$3665,$K18)) | F18: =IF($K18="","",INDEX(Zeiterfassung!$F$6:$F$3665,$K18)) | G18: =IF($K18="","",INDEX(Zeiterfassung!$G$6:$G$3665,$K18)) | H18: =IF($K18="","",INDEX(Zeiterfassung!$H$6:$H$3665,$K18)) | I18: =IF(B18=B17,"",IF($K18="","",INDEX(Zeiterfassung!$I$6:$I$3665,MATCH(INDEX(Zeiterfassung!$K$6:$K$3665,$K18),Zeiterfassung!$K$6:$K$3665,0)))) | J18: =IF(B18=B17,"",IF($K18="","",INDEX(Zeiterfassung!$J$6:$J$3665,MATCH(INDEX(Zeiterfassung!$K$6:$K$3665,$K18),Zeiterfassung!$K$6:$K$3665,0)))) | K18: =IFERROR(AGGREGATE(15,6,(ROW(Zeiterfassung!$D$6:$D$3665)-ROW(Zeiterfassung!$D$6)+1)/(Zeiterfassung!$D$6:$D$3665<>""),13),"")
A19: =IF($K19="","",WEEKNUM(INDEX(Zeiterfassung!$K$6:$K$3665,$K19),21)) | B19: =IF($K19="","",INDEX(Zeiterfassung!$K$6:$K$3665,$K19)) | C19: =IF($K19="","",INDEX(Zeiterfassung!$K$6:$K$3665,$K19)) | D19: =IF($K19="","",INDEX(Zeiterfassung!$D$6:$D$3665,$K19)) | E19: =IF($K19="","",INDEX(Zeiterfassung!$E$6:$E$3665,$K19)) | F19: =IF($K19="","",INDEX(Zeiterfassung!$F$6:$F$3665,$K19)) | G19: =IF($K19="","",INDEX(Zeiterfassung!$G$6:$G$3665,$K19)) | H19: =IF($K19="","",INDEX(Zeiterfassung!$H$6:$H$3665,$K19)) | I19: =IF(B19=B18,"",IF($K19="","",INDEX(Zeiterfassung!$I$6:$I$3665,MATCH(INDEX(Zeiterfassung!$K$6:$K$3665,$K19),Zeiterfassung!$K$6:$K$3665,0)))) | J19: =IF(B19=B18,"",IF($K19="","",INDEX(Zeiterfassung!$J$6:$J$3665,MATCH(INDEX(Zeiterfassung!$K$6:$K$3665,$K19),Zeiterfassung!$K$6:$K$3665,0)))) | K19: =IFERROR(AGGREGATE(15,6,(ROW(Zeiterfassung!$D$6:$D$3665)-ROW(Zeiterfassung!$D$6)+1)/(Zeiterfassung!$D$6:$D$3665<>""),14),"")
A20: =IF($K20="","",WEEKNUM(INDEX(Zeiterfassung!$K$6:$K$3665,$K20),21)) | B20: =IF($K20="","",INDEX(Zeiterfassung!$K$6:$K$3665,$K20)) | C20: =IF($K20="","",INDEX(Zeiterfassung!$K$6:$K$3665,$K20)) | D20: =IF($K20="","",INDEX(Zeiterfassung!$D$6:$D$3665,$K20)) | E20: =IF($K20="","",INDEX(Zeiterfassung!$E$6:$E$3665,$K20)) | F20: =IF($K20="","",INDEX(Zeiterfassung!$F$6:$F$3665,$K20)) | G20: =IF($K20="","",INDEX(Zeiterfassung!$G$6:$G$3665,$K20)) | H20: =IF($K20="","",INDEX(Zeiterfassung!$H$6:$H$3665,$K20)) | I20: =IF(B20=B19,"",IF($K20="","",INDEX(Zeiterfassung!$I$6:$I$3665,MATCH(INDEX(Zeiterfassung!$K$6:$K$3665,$K20),Zeiterfassung!$K$6:$K$3665,0)))) | J20: =IF(B20=B19,"",IF($K20="","",INDEX(Zeiterfassung!$J$6:$J$3665,MATCH(INDEX(Zeiterfassung!$K$6:$K$3665,$K20),Zeiterfassung!$K$6:$K$3665,0)))) | K20: =IFERROR(AGGREGATE(15,6,(ROW(Zeiterfassung!$D$6:$D$3665)-ROW(Zeiterfassung!$D$6)+1)/(Zeiterfassung!$D$6:$D$3665<>""),15),"")
A21: =IF($K21="","",WEEKNUM(INDEX(Zeiterfassung!$K$6:$K$3665,$K21),21)) | B21: =IF($K21="","",INDEX(Zeiterfassung!$K$6:$K$3665,$K21)) | C21: =IF($K21="","",INDEX(Zeiterfassung!$K$6:$K$3665,$K21)) | D21: =IF($K21="","",INDEX(Zeiterfassung!$D$6:$D$3665,$K21)) | E21: =IF($K21="","",INDEX(Zeiterfassung!$E$6:$E$3665,$K21)) | F21: =IF($K21="","",INDEX(Zeiterfassung!$F$6:$F$3665,$K21)) | G21: =IF($K21="","",INDEX(Zeiterfassung!$G$6:$G$3665,$K21)) | H21: =IF($K21="","",INDEX(Zeiterfassung!$H$6:$H$3665,$K21)) | I21: =IF(B21=B20,"",IF($K21="","",INDEX(Zeiterfassung!$I$6:$I$3665,MATCH(INDEX(Zeiterfassung!$K$6:$K$3665,$K21),Zeiterfassung!$K$6:$K$3665,0)))) | J21: =IF(B21=B20,"",IF($K21="","",INDEX(Zeiterfassung!$J$6:$J$3665,MATCH(INDEX(Zeiterfassung!$K$6:$K$3665,$K21),Zeiterfassung!$K$6:$K$3665,0)))) | K21: =IFERROR(AGGREGATE(15,6,(ROW(Zeiterfassung!$D$6:$D$3665)-ROW(Zeiterfassung!$D$6)+1)/(Zeiterfassung!$D$6:$D$3665<>""),16),"")
A22: =IF($K22="","",WEEKNUM(INDEX(Zeiterfassung!$K$6:$K$3665,$K22),21)) | B22: =IF($K22="","",INDEX(Zeiterfassung!$K$6:$K$3665,$K22)) | C22: =IF($K22="","",INDEX(Zeiterfassung!$K$6:$K$3665,$K22)) | D22: =IF($K22="","",INDEX(Zeiterfassung!$D$6:$D$3665,$K22)) | E22: =IF($K22="","",INDEX(Zeiterfassung!$E$6:$E$3665,$K22)) | F22: =IF($K22="","",INDEX(Zeiterfassung!$F$6:$F$3665,$K22)) | G22: =IF($K22="","",INDEX(Zeiterfassung!$G$6:$G$3665,$K22)) | H22: =IF($K22="","",INDEX(Zeiterfassung!$H$6:$H$3665,$K22)) | I22: =IF(B22=B21,"",IF($K22="","",INDEX(Zeiterfassung!$I$6:$I$3665,MATCH(INDEX(Zeiterfassung!$K$6:$K$3665,$K22),Zeiterfassung!$K$6:$K$3665,0)))) | J22: =IF(B22=B21,"",IF($K22="","",INDEX(Zeiterfassung!$J$6:$J$3665,MATCH(INDEX(Zeiterfassung!$K$6:$K$3665,$K22),Zeiterfassung!$K$6:$K$3665,0)))) | K22: =IFERROR(AGGREGATE(15,6,(ROW(Zeiterfassung!$D$6:$D$3665)-ROW(Zeiterfassung!$D$6)+1)/(Zeiterfassung!$D$6:$D$3665<>""),17),"")
A23: =IF($K23="","",WEEKNUM(INDEX(Zeiterfassung!$K$6:$K$3665,$K23),21)) | B23: =IF($K23="","",INDEX(Zeiterfassung!$K$6:$K$3665,$K23)) | C23: =IF($K23="","",INDEX(Zeiterfassung!$K$6:$K$3665,$K23)) | D23: =IF($K23="","",INDEX(Zeiterfassung!$D$6:$D$3665,$K23)) | E23: =IF($K23="","",INDEX(Zeiterfassung!$E$6:$E$3665,$K23)) | F23: =IF($K23="","",INDEX(Zeiterfassung!$F$6:$F$3665,$K23)) | G23: =IF($K23="","",INDEX(Zeiterfassung!$G$6:$G$3665,$K23)) | H23: =IF($K23="","",INDEX(Zeiterfassung!$H$6:$H$3665,$K23)) | I23: =IF(B23=B22,"",IF($K23="","",INDEX(Zeiterfassung!$I$6:$I$3665,MATCH(INDEX(Zeiterfassung!$K$6:$K$3665,$K23),Zeiterfassung!$K$6:$K$3665,0)))) | J23: =IF(B23=B22,"",IF($K23="","",INDEX(Zeiterfassung!$J$6:$J$3665,MATCH(INDEX(Zeiterfassung!$K$6:$K$3665,$K23),Zeiterfassung!$K$6:$K$3665,0)))) | K23: =IFERROR(AGGREGATE(15,6,(ROW(Zeiterfassung!$D$6:$D$3665)-ROW(Zeiterfassung!$D$6)+1)/(Zeiterfassung!$D$6:$D$3665<>""),18),"")
A24: =IF($K24="","",WEEKNUM(INDEX(Zeiterfassung!$K$6:$K$3665,$K24),21)) | B24: =IF($K24="","",INDEX(Zeiterfassung!$K$6:$K$3665,$K24)) | C24: =IF($K24="","",INDEX(Zeiterfassung!$K$6:$K$3665,$K24)) | D24: =IF($K24="","",INDEX(Zeiterfassung!$D$6:$D$3665,$K24)) | E24: =IF($K24="","",INDEX(Zeiterfassung!$E$6:$E$3665,$K24)) | F24: =IF($K24="","",INDEX(Zeiterfassung!$F$6:$F$3665,$K24)) | G24: =IF($K24="","",INDEX(Zeiterfassung!$G$6:$G$3665,$K24)) | H24: =IF($K24="","",INDEX(Zeiterfassung!$H$6:$H$3665,$K24)) | I24: =IF(B24=B23,"",IF($K24="","",INDEX(Zeiterfassung!$I$6:$I$3665,MATCH(INDEX(Zeiterfassung!$K$6:$K$3665,$K24),Zeiterfassung!$K$6:$K$3665,0)))) | J24: =IF(B24=B23,"",IF($K24="","",INDEX(Zeiterfassung!$J$6:$J$3665,MATCH(INDEX(Zeiterfassung!$K$6:$K$3665,$K24),Zeiterfassung!$K$6:$K$3665,0)))) | K24: =IFERROR(AGGREGATE(15,6,(ROW(Zeiterfassung!$D$6:$D$3665)-ROW(Zeiterfassung!$D$6)+1)/(Zeiterfassung!$D$6:$D$3665<>""),19),"")
A25: =IF($K25="","",WEEKNUM(INDEX(Zeiterfassung!$K$6:$K$3665,$K25),21)) | B25: =IF($K25="","",INDEX(Zeiterfassung!$K$6:$K$3665,$K25)) | C25: =IF($K25="","",INDEX(Zeiterfassung!$K$6:$K$3665,$K25)) | D25: =IF($K25="","",INDEX(Zeiterfassung!$D$6:$D$3665,$K25)) | E25: =IF($K25="","",INDEX(Zeiterfassung!$E$6:$E$3665,$K25)) | F25: =IF($K25="","",INDEX(Zeiterfassung!$F$6:$F$3665,$K25)) | G25: =IF($K25="","",INDEX(Zeiterfassung!$G$6:$G$3665,$K25)) | H25: =IF($K25="","",INDEX(Zeiterfassung!$H$6:$H$3665,$K25)) | I25: =IF(B25=B24,"",IF($K25="","",INDEX(Zeiterfassung!$I$6:$I$3665,MATCH(INDEX(Zeiterfassung!$K$6:$K$3665,$K25),Zeiterfassung!$K$6:$K$3665,0)))) | J25: =IF(B25=B24,"",IF($K25="","",INDEX(Zeiterfassung!$J$6:$J$3665,MATCH(INDEX(Zeiterfassung!$K$6:$K$3665,$K25),Zeiterfassung!$K$6:$K$3665,0)))) | K25: =IFERROR(AGGREGATE(15,6,(ROW(Zeiterfassung!$D$6:$D$3665)-ROW(Zeiterfassung!$D$6)+1)/(Zeiterfassung!$D$6:$D$3665<>""),20),"")
A26: =IF($K26="","",WEEKNUM(INDEX(Zeiterfassung!$K$6:$K$3665,$K26),21)) | B26: =IF($K26="","",INDEX(Zeiterfassung!$K$6:$K$3665,$K26)) | C26: =IF($K26="","",INDEX(Zeiterfassung!$K$6:$K$3665,$K26)) | D26: =IF($K26="","",INDEX(Zeiterfassung!$D$6:$D$3665,$K26)) | E26: =IF($K26="","",INDEX(Zeiterfassung!$E$6:$E$3665,$K26)) | F26: =IF($K26="","",INDEX(Zeiterfassung!$F$6:$F$3665,$K26)) | G26: =IF($K26="","",INDEX(Zeiterfassung!$G$6:$G$3665,$K26)) | H26: =IF($K26="","",INDEX(Zeiterfassung!$H$6:$H$3665,$K26)) | I26: =IF(B26=B25,"",IF($K26="","",INDEX(Zeiterfassung!$I$6:$I$3665,MATCH(INDEX(Zeiterfassung!$K$6:$K$3665,$K26),Zeiterfassung!$K$6:$K$3665,0)))) | J26: =IF(B26=B25,"",IF($K26="","",INDEX(Zeiterfassung!$J$6:$J$3665,MATCH(INDEX(Zeiterfassung!$K$6:$K$3665,$K26),Zeiterfassung!$K$6:$K$3665,0)))) | K26: =IFERROR(AGGREGATE(15,6,(ROW(Zeiterfassung!$D$6:$D$3665)-ROW(Zeiterfassung!$D$6)+1)/(Zeiterfassung!$D$6:$D$3665<>""),21),"")
A27: =IF($K27="","",WEEKNUM(INDEX(Zeiterfassung!$K$6:$K$3665,$K27),21)) | B27: =IF($K27="","",INDEX(Zeiterfassung!$K$6:$K$3665,$K27)) | C27: =IF($K27="","",INDEX(Zeiterfassung!$K$6:$K$3665,$K27)) | D27: =IF($K27="","",INDEX(Zeiterfassung!$D$6:$D$3665,$K27)) | E27: =IF($K27="","",INDEX(Zeiterfassung!$E$6:$E$3665,$K27)) | F27: =IF($K27="","",INDEX(Zeiterfassung!$F$6:$F$3665,$K27)) | G27: =IF($K27="","",INDEX(Zeiterfassung!$G$6:$G$3665,$K27)) | H27: =IF($K27="","",INDEX(Zeiterfassung!$H$6:$H$3665,$K27)) | I27: =IF(B27=B26,"",IF($K27="","",INDEX(Zeiterfassung!$I$6:$I$3665,MATCH(INDEX(Zeiterfassung!$K$6:$K$3665,$K27),Zeiterfassung!$K$6:$K$3665,0)))) | J27: =IF(B27=B26,"",IF($K27="","",INDEX(Zeiterfassung!$J$6:$J$3665,MATCH(INDEX(Zeiterfassung!$K$6:$K$3665,$K27),Zeiterfassung!$K$6:$K$3665,0)))) | K27: =IFERROR(AGGREGATE(15,6,(ROW(Zeiterfassung!$D$6:$D$3665)-ROW(Zeiterfassung!$D$6)+1)/(Zeiterfassung!$D$6:$D$3665<>""),22),"")
A28: =IF($K28="","",WEEKNUM(INDEX(Zeiterfassung!$K$6:$K$3665,$K28),21)) | B28: =IF($K28="","",INDEX(Zeiterfassung!$K$6:$K$3665,$K28)) | C28: =IF($K28="","",INDEX(Zeiterfassung!$K$6:$K$3665,$K28)) | D28: =IF($K28="","",INDEX(Zeiterfassung!$D$6:$D$3665,$K28)) | E28: =IF($K28="","",INDEX(Zeiterfassung!$E$6:$E$3665,$K28)) | F28: =IF($K28="","",INDEX(Zeiterfassung!$F$6:$F$3665,$K28)) | G28: =IF($K28="","",INDEX(Zeiterfassung!$G$6:$G$3665,$K28)) | H28: =IF($K28="","",INDEX(Zeiterfassung!$H$6:$H$3665,$K28)) | I28: =IF(B28=B27,"",IF($K28="","",INDEX(Zeiterfassung!$I$6:$I$3665,MATCH(INDEX(Zeiterfassung!$K$6:$K$3665,$K28),Zeiterfassung!$K$6:$K$3665,0)))) | J28: =IF(B28=B27,"",IF($K28="","",INDEX(Zeiterfassung!$J$6:$J$3665,MATCH(INDEX(Zeiterfassung!$K$6:$K$3665,$K28),Zeiterfassung!$K$6:$K$3665,0)))) | K28: =IFERROR(AGGREGATE(15,6,(ROW(Zeiterfassung!$D$6:$D$3665)-ROW(Zeiterfassung!$D$6)+1)/(Zeiterfassung!$D$6:$D$3665<>""),23),"")
A29: =IF($K29="","",WEEKNUM(INDEX(Zeiterfassung!$K$6:$K$3665,$K29),21)) | B29: =IF($K29="","",INDEX(Zeiterfassung!$K$6:$K$3665,$K29)) | C29: =IF($K29="","",INDEX(Zeiterfassung!$K$6:$K$3665,$K29)) | D29: =IF($K29="","",INDEX(Zeiterfassung!$D$6:$D$3665,$K29)) | E29: =IF($K29="","",INDEX(Zeiterfassung!$E$6:$E$3665,$K29)) | F29: =IF($K29="","",INDEX(Zeiterfassung!$F$6:$F$3665,$K29)) | G29: =IF($K29="","",INDEX(Zeiterfassung!$G$6:$G$3665,$K29)) | H29: =IF($K29="","",INDEX(Zeiterfassung!$H$6:$H$3665,$K29)) | I29: =IF(B29=B28,"",IF($K29="","",INDEX(Zeiterfassung!$I$6:$I$3665,MATCH(INDEX(Zeiterfassung!$K$6:$K$3665,$K29),Zeiterfassung!$K$6:$K$3665,0)))) | J29: =IF(B29=B28,"",IF($K29="","",INDEX(Zeiterfassung!$J$6:$J$3665,MATCH(INDEX(Zeiterfassung!$K$6:$K$3665,$K29),Zeiterfassung!$K$6:$K$3665,0)))) | K29: =IFERROR(AGGREGATE(15,6,(ROW(Zeiterfassung!$D$6:$D$3665)-ROW(Zeiterfassung!$D$6)+1)/(Zeiterfassung!$D$6:$D$3665<>""),24),"")
A30: =IF($K30="","",WEEKNUM(INDEX(Zeiterfassung!$K$6:$K$3665,$K30),21)) | B30: =IF($K30="","",INDEX(Zeiterfassung!$K$6:$K$3665,$K30)) | C30: =IF($K30="","",INDEX(Zeiterfassung!$K$6:$K$3665,$K30)) | D30: =IF($K30="","",INDEX(Zeiterfassung!$D$6:$D$3665,$K30)) | E30: =IF($K30="","",INDEX(Zeiterfassung!$E$6:$E$3665,$K30)) | F30: =IF($K30="","",INDEX(Zeiterfassung!$F$6:$F$3665,$K30)) | G30: =IF($K30="","",INDEX(Zeiterfassung!$G$6:$G$3665,$K30)) | H30: =IF($K30="","",INDEX(Zeiterfassung!$H$6:$H$3665,$K30)) | I30: =IF(B30=B29,"",IF($K30="","",INDEX(Zeiterfassung!$I$6:$I$3665,MATCH(INDEX(Zeiterfassung!$K$6:$K$3665,$K30),Zeiterfassung!$K$6:$K$3665,0)))) | J30: =IF(B30=B29,"",IF($K30="","",INDEX(Zeiterfassung!$J$6:$J$3665,MATCH(INDEX(Zeiterfassung!$K$6:$K$3665,$K30),Zeiterfassung!$K$6:$K$3665,0)))) | K30: =IFERROR(AGGREGATE(15,6,(ROW(Zeiterfassung!$D$6:$D$3665)-ROW(Zeiterfassung!$D$6)+1)/(Zeiterfassung!$D$6:$D$3665<>""),25),"")
A31: =IF($K31="","",WEEKNUM(INDEX(Zeiterfassung!$K$6:$K$3665,$K31),21)) | B31: =IF($K31="","",INDEX(Zeiterfassung!$K$6:$K$3665,$K31)) | C31: =IF($K31="","",INDEX(Zeiterfassung!$K$6:$K$3665,$K31)) | D31: =IF($K31="","",INDEX(Zeiterfassung!$D$6:$D$3665,$K31)) | E31: =IF($K31="","",INDEX(Zeiterfassung!$E$6:$E$3665,$K31)) | F31: =IF($K31="","",INDEX(Zeiterfassung!$F$6:$F$3665,$K31)) | G31: =IF($K31="","",INDEX(Zeiterfassung!$G$6:$G$3665,$K31)) | H31: =IF($K31="","",INDEX(Zeiterfassung!$H$6:$H$3665,$K31)) | I31: =IF(B31=B30,"",IF($K31="","",INDEX(Zeiterfassung!$I$6:$I$3665,MATCH(INDEX(Zeiterfassung!$K$6:$K$3665,$K31),Zeiterfassung!$K$6:$K$3665,0)))) | J31: =IF(B31=B30,"",IF($K31="","",INDEX(Zeiterfassung!$J$6:$J$3665,MATCH(INDEX(Zeiterfassung!$K$6:$K$3665,$K31),Zeiterfassung!$K$6:$K$3665,0)))) | K31: =IFERROR(AGGREGATE(15,6,(ROW(Zeiterfassung!$D$6:$D$3665)-ROW(Zeiterfassung!$D$6)+1)/(Zeiterfassung!$D$6:$D$3665<>""),26),"")
A32: =IF($K32="","",WEEKNUM(INDEX(Zeiterfassung!$K$6:$K$3665,$K32),21)) | B32: =IF($K32="","",INDEX(Zeiterfassung!$K$6:$K$3665,$K32)) | C32: =IF($K32="","",INDEX(Zeiterfassung!$K$6:$K$3665,$K32)) | D32: =IF($K32="","",INDEX(Zeiterfassung!$D$6:$D$3665,$K32)) | E32: =IF($K32="","",INDEX(Zeiterfassung!$E$6:$E$3665,$K32)) | F32: =IF($K32="","",INDEX(Zeiterfassung!$F$6:$F$3665,$K32)) | G32: =IF($K32="","",INDEX(Zeiterfassung!$G$6:$G$3665,$K32)) | H32: =IF($K32="","",INDEX(Zeiterfassung!$H$6:$H$3665,$K32)) | I32: =IF(B32=B31,"",IF($K32="","",INDEX(Zeiterfassung!$I$6:$I$3665,MATCH(INDEX(Zeiterfassung!$K$6:$K$3665,$K32),Zeiterfassung!$K$6:$K$3665,0)))) | J32: =IF(B32=B31,"",IF($K32="","",INDEX(Zeiterfassung!$J$6:$J$3665,MATCH(INDEX(Zeiterfassung!$K$6:$K$3665,$K32),Zeiterfassung!$K$6:$K$3665,0)))) | K32: =IFERROR(AGGREGATE(15,6,(ROW(Zeiterfassung!$D$6:$D$3665)-ROW(Zeiterfassung!$D$6)+1)/(Zeiterfassung!$D$6:$D$3665<>""),27),"")
A33: =IF($K33="","",WEEKNUM(INDEX(Zeiterfassung!$K$6:$K$3665,$K33),21)) | B33: =IF($K33="","",INDEX(Zeiterfassung!$K$6:$K$3665,$K33)) | C33: =IF($K33="","",INDEX(Zeiterfassung!$K$6:$K$3665,$K33)) | D33: =IF($K33="","",INDEX(Zeiterfassung!$D$6:$D$3665,$K33)) | E33: =IF($K33="","",INDEX(Zeiterfassung!$E$6:$E$3665,$K33)) | F33: =IF($K33="","",INDEX(Zeiterfassung!$F$6:$F$3665,$K33)) | G33: =IF($K33="","",INDEX(Zeiterfassung!$G$6:$G$3665,$K33)) | H33: =IF($K33="","",INDEX(Zeiterfassung!$H$6:$H$3665,$K33)) | I33: =IF(B33=B32,"",IF($K33="","",INDEX(Zeiterfassung!$I$6:$I$3665,MATCH(INDEX(Zeiterfassung!$K$6:$K$3665,$K33),Zeiterfassung!$K$6:$K$3665,0)))) | J33: =IF(B33=B32,"",IF($K33="","",INDEX(Zeiterfassung!$J$6:$J$3665,MATCH(INDEX(Zeiterfassung!$K$6:$K$3665,$K33),Zeiterfassung!$K$6:$K$3665,0)))) | K33: =IFERROR(AGGREGATE(15,6,(ROW(Zeiterfassung!$D$6:$D$3665)-ROW(Zeiterfassung!$D$6)+1)/(Zeiterfassung!$D$6:$D$3665<>""),28),"")
A34: =IF($K34="","",WEEKNUM(INDEX(Zeiterfassung!$K$6:$K$3665,$K34),21)) | B34: =IF($K34="","",INDEX(Zeiterfassung!$K$6:$K$3665,$K34)) | C34: =IF($K34="","",INDEX(Zeiterfassung!$K$6:$K$3665,$K34)) | D34: =IF($K34="","",INDEX(Zeiterfassung!$D$6:$D$3665,$K34)) | E34: =IF($K34="","",INDEX(Zeiterfassung!$E$6:$E$3665,$K34)) | F34: =IF($K34="","",INDEX(Zeiterfassung!$F$6:$F$3665,$K34)) | G34: =IF($K34="","",INDEX(Zeiterfassung!$G$6:$G$3665,$K34)) | H34: =IF($K34="","",INDEX(Zeiterfassung!$H$6:$H$3665,$K34)) | I34: =IF(B34=B33,"",IF($K34="","",INDEX(Zeiterfassung!$I$6:$I$3665,MATCH(INDEX(Zeiterfassung!$K$6:$K$3665,$K34),Zeiterfassung!$K$6:$K$3665,0)))) | J34: =IF(B34=B33,"",IF($K34="","",INDEX(Zeiterfassung!$J$6:$J$3665,MATCH(INDEX(Zeiterfassung!$K$6:$K$3665,$K34),Zeiterfassung!$K$6:$K$3665,0)))) | K34: =IFERROR(AGGREGATE(15,6,(ROW(Zeiterfassung!$D$6:$D$3665)-ROW(Zeiterfassung!$D$6)+1)/(Zeiterfassung!$D$6:$D$3665<>""),29),"")
A35: =IF($K35="","",WEEKNUM(INDEX(Zeiterfassung!$K$6:$K$3665,$K35),21)) | B35: =IF($K35="","",INDEX(Zeiterfassung!$K$6:$K$3665,$K35)) | C35: =IF($K35="","",INDEX(Zeiterfassung!$K$6:$K$3665,$K35)) | D35: =IF($K35="","",INDEX(Zeiterfassung!$D$6:$D$3665,$K35)) | E35: =IF($K35="","",INDEX(Zeiterfassung!$E$6:$E$3665,$K35)) | F35: =IF($K35="","",INDEX(Zeiterfassung!$F$6:$F$3665,$K35)) | G35: =IF($K35="","",INDEX(Zeiterfassung!$G$6:$G$3665,$K35)) | H35: =IF($K35="","",INDEX(Zeiterfassung!$H$6:$H$3665,$K35)) | I35: =IF(B35=B34,"",IF($K35="","",INDEX(Zeiterfassung!$I$6:$I$3665,MATCH(INDEX(Zeiterfassung!$K$6:$K$3665,$K35),Zeiterfassung!$K$6:$K$3665,0)))) | J35: =IF(B35=B34,"",IF($K35="","",INDEX(Zeiterfassung!$J$6:$J$3665,MATCH(INDEX(Zeiterfassung!$K$6:$K$3665,$K35),Zeiterfassung!$K$6:$K$3665,0)))) | K35: =IFERROR(AGGREGATE(15,6,(ROW(Zeiterfassung!$D$6:$D$3665)-ROW(Zeiterfassung!$D$6)+1)/(Zeiterfassung!$D$6:$D$3665<>""),30),"")
A36: =IF($K36="","",WEEKNUM(INDEX(Zeiterfassung!$K$6:$K$3665,$K36),21)) | B36: =IF($K36="","",INDEX(Zeiterfassung!$K$6:$K$3665,$K36)) | C36: =IF($K36="","",INDEX(Zeiterfassung!$K$6:$K$3665,$K36)) | D36: =IF($K36="","",INDEX(Zeiterfassung!$D$6:$D$3665,$K36)) | E36: =IF($K36="","",INDEX(Zeiterfassung!$E$6:$E$3665,$K36)) | F36: =IF($K36="","",INDEX(Zeiterfassung!$F$6:$F$3665,$K36)) | G36: =IF($K36="","",INDEX(Zeiterfassung!$G$6:$G$3665,$K36)) | H36: =IF($K36="","",INDEX(Zeiterfassung!$H$6:$H$3665,$K36)) | I36: =IF(B36=B35,"",IF($K36="","",INDEX(Zeiterfassung!$I$6:$I$3665,MATCH(INDEX(Zeiterfassung!$K$6:$K$3665,$K36),Zeiterfassung!$K$6:$K$3665,0)))) | J36: =IF(B36=B35,"",IF($K36="","",INDEX(Zeiterfassung!$J$6:$J$3665,MATCH(INDEX(Zeiterfassung!$K$6:$K$3665,$K36),Zeiterfassung!$K$6:$K$3665,0)))) | K36: =IFERROR(AGGREGATE(15,6,(ROW(Zeiterfassung!$D$6:$D$3665)-ROW(Zeiterfassung!$D$6)+1)/(Zeiterfassung!$D$6:$D$3665<>""),31),"")
A37: =IF($K37="","",WEEKNUM(INDEX(Zeiterfassung!$K$6:$K$3665,$K37),21)) | B37: =IF($K37="","",INDEX(Zeiterfassung!$K$6:$K$3665,$K37)) | C37: =IF($K37="","",INDEX(Zeiterfassung!$K$6:$K$3665,$K37)) | D37: =IF($K37="","",INDEX(Zeiterfassung!$D$6:$D$3665,$K37)) | E37: =IF($K37="","",INDEX(Zeiterfassung!$E$6:$E$3665,$K37)) | F37: =IF($K37="","",INDEX(Zeiterfassung!$F$6:$F$3665,$K37)) | G37: =IF($K37="","",INDEX(Zeiterfassung!$G$6:$G$3665,$K37)) | H37: =IF($K37="","",INDEX(Zeiterfassung!$H$6:$H$3665,$K37)) | I37: =IF(B37=B36,"",IF($K37="","",INDEX(Zeiterfassung!$I$6:$I$3665,MATCH(INDEX(Zeiterfassung!$K$6:$K$3665,$K37),Zeiterfassung!$K$6:$K$3665,0)))) | J37: =IF(B37=B36,"",IF($K37="","",INDEX(Zeiterfassung!$J$6:$J$3665,MATCH(INDEX(Zeiterfassung!$K$6:$K$3665,$K37),Zeiterfassung!$K$6:$K$3665,0)))) | K37: =IFERROR(AGGREGATE(15,6,(ROW(Zeiterfassung!$D$6:$D$3665)-ROW(Zeiterfassung!$D$6)+1)/(Zeiterfassung!$D$6:$D$3665<>""),32),"")
A38: =IF($K38="","",WEEKNUM(INDEX(Zeiterfassung!$K$6:$K$3665,$K38),21)) | B38: =IF($K38="","",INDEX(Zeiterfassung!$K$6:$K$3665,$K38)) | C38: =IF($K38="","",INDEX(Zeiterfassung!$K$6:$K$3665,$K38)) | D38: =IF($K38="","",INDEX(Zeiterfassung!$D$6:$D$3665,$K38)) | E38: =IF($K38="","",INDEX(Zeiterfassung!$E$6:$E$3665,$K38)) | F38: =IF($K38="","",INDEX(Zeiterfassung!$F$6:$F$3665,$K38)) | G38: =IF($K38="","",INDEX(Zeiterfassung!$G$6:$G$3665,$K38)) | H38: =IF($K38="","",INDEX(Zeiterfassung!$H$6:$H$3665,$K38)) | I38: =IF(B38=B37,"",IF($K38="","",INDEX(Zeiterfassung!$I$6:$I$3665,MATCH(INDEX(Zeiterfassung!$K$6:$K$3665,$K38),Zeiterfassung!$K$6:$K$3665,0)))) | J38: =IF(B38=B37,"",IF($K38="","",INDEX(Zeiterfassung!$J$6:$J$3665,MATCH(INDEX(Zeiterfassung!$K$6:$K$3665,$K38),Zeiterfassung!$K$6:$K$3665,0)))) | K38: =IFERROR(AGGREGATE(15,6,(ROW(Zeiterfassung!$D$6:$D$3665)-ROW(Zeiterfassung!$D$6)+1)/(Zeiterfassung!$D$6:$D$3665<>""),33),"")
A39: =IF($K39="","",WEEKNUM(INDEX(Zeiterfassung!$K$6:$K$3665,$K39),21)) | B39: =IF($K39="","",INDEX(Zeiterfassung!$K$6:$K$3665,$K39)) | C39: =IF($K39="","",INDEX(Zeiterfassung!$K$6:$K$3665,$K39)) | D39: =IF($K39="","",INDEX(Zeiterfassung!$D$6:$D$3665,$K39)) | E39: =IF($K39="","",INDEX(Zeiterfassung!$E$6:$E$3665,$K39)) | F39: =IF($K39="","",INDEX(Zeiterfassung!$F$6:$F$3665,$K39)) | G39: =IF($K39="","",INDEX(Zeiterfassung!$G$6:$G$3665,$K39)) | H39: =IF($K39="","",INDEX(Zeiterfassung!$H$6:$H$3665,$K39)) | I39: =IF(B39=B38,"",IF($K39="","",INDEX(Zeiterfassung!$I$6:$I$3665,MATCH(INDEX(Zeiterfassung!$K$6:$K$3665,$K39),Zeiterfassung!$K$6:$K$3665,0)))) | J39: =IF(B39=B38,"",IF($K39="","",INDEX(Zeiterfassung!$J$6:$J$3665,MATCH(INDEX(Zeiterfassung!$K$6:$K$3665,$K39),Zeiterfassung!$K$6:$K$3665,0)))) | K39: =IFERROR(AGGREGATE(15,6,(ROW(Zeiterfassung!$D$6:$D$3665)-ROW(Zeiterfassung!$D$6)+1)/(Zeiterfassung!$D$6:$D$3665<>""),34),"")
A40: =IF($K40="","",WEEKNUM(INDEX(Zeiterfassung!$K$6:$K$3665,$K40),21)) | B40: =IF($K40="","",INDEX(Zeiterfassung!$K$6:$K$3665,$K40)) | C40: =IF($K40="","",INDEX(Zeiterfassung!$K$6:$K$3665,$K40)) | D40: =IF($K40="","",INDEX(Zeiterfassung!$D$6:$D$3665,$K40)) | E40: =IF($K40="","",INDEX(Zeiterfassung!$E$6:$E$3665,$K40)) | F40: =IF($K40="","",INDEX(Zeiterfassung!$F$6:$F$3665,$K40)) | G40: =IF($K40="","",INDEX(Zeiterfassung!$G$6:$G$3665,$K40)) | H40: =IF($K40="","",INDEX(Zeiterfassung!$H$6:$H$3665,$K40)) | I40: =IF(B40=B39,"",IF($K40="","",INDEX(Zeiterfassung!$I$6:$I$3665,MATCH(INDEX(Zeiterfassung!$K$6:$K$3665,$K40),Zeiterfassung!$K$6:$K$3665,0)))) | J40: =IF(B40=B39,"",IF($K40="","",INDEX(Zeiterfassung!$J$6:$J$3665,MATCH(INDEX(Zeiterfassung!$K$6:$K$3665,$K40),Zeiterfassung!$K$6:$K$3665,0)))) | K40: =IFERROR(AGGREGATE(15,6,(ROW(Zeiterfassung!$D$6:$D$3665)-ROW(Zeiterfassung!$D$6)+1)/(Zeiterfassung!$D$6:$D$3665<>""),35),"")
A41: =IF($K41="","",WEEKNUM(INDEX(Zeiterfassung!$K$6:$K$3665,$K41),21)) | B41: =IF($K41="","",INDEX(Zeiterfassung!$K$6:$K$3665,$K41)) | C41: =IF($K41="","",INDEX(Zeiterfassung!$K$6:$K$3665,$K41)) | D41: =IF($K41="","",INDEX(Zeiterfassung!$D$6:$D$3665,$K41)) | E41: =IF($K41="","",INDEX(Zeiterfassung!$E$6:$E$3665,$K41)) | F41: =IF($K41="","",INDEX(Zeiterfassung!$F$6:$F$3665,$K41)) | G41: =IF($K41="","",INDEX(Zeiterfassung!$G$6:$G$3665,$K41)) | H41: =IF($K41="","",INDEX(Zeiterfassung!$H$6:$H$3665,$K41)) | I41: =IF(B41=B40,"",IF($K41="","",INDEX(Zeiterfassung!$I$6:$I$3665,MATCH(INDEX(Zeiterfassung!$K$6:$K$3665,$K41),Zeiterfassung!$K$6:$K$3665,0)))) | J41: =IF(B41=B40,"",IF($K41="","",INDEX(Zeiterfassung!$J$6:$J$3665,MATCH(INDEX(Zeiterfassung!$K$6:$K$3665,$K41),Zeiterfassung!$K$6:$K$3665,0)))) | K41: =IFERROR(AGGREGATE(15,6,(ROW(Zeiterfassung!$D$6:$D$3665)-ROW(Zeiterfassung!$D$6)+1)/(Zeiterfassung!$D$6:$D$3665<>""),36),"")
A42: =IF($K42="","",WEEKNUM(INDEX(Zeiterfassung!$K$6:$K$3665,$K42),21)) | B42: =IF($K42="","",INDEX(Zeiterfassung!$K$6:$K$3665,$K42)) | C42: =IF($K42="","",INDEX(Zeiterfassung!$K$6:$K$3665,$K42)) | D42: =IF($K42="","",INDEX(Zeiterfassung!$D$6:$D$3665,$K42)) | E42: =IF($K42="","",INDEX(Zeiterfassung!$E$6:$E$3665,$K42)) | F42: =IF($K42="","",INDEX(Zeiterfassung!$F$6:$F$3665,$K42)) | G42: =IF($K42="","",INDEX(Zeiterfassung!$G$6:$G$3665,$K42)) | H42: =IF($K42="","",INDEX(Zeiterfassung!$H$6:$H$3665,$K42)) | I42: =IF(B42=B41,"",IF($K42="","",INDEX(Zeiterfassung!$I$6:$I$3665,MATCH(INDEX(Zeiterfassung!$K$6:$K$3665,$K42),Zeiterfassung!$K$6:$K$3665,0)))) | J42: =IF(B42=B41,"",IF($K42="","",INDEX(Zeiterfassung!$J$6:$J$3665,MATCH(INDEX(Zeiterfassung!$K$6:$K$3665,$K42),Zeiterfassung!$K$6:$K$3665,0)))) | K42: =IFERROR(AGGREGATE(15,6,(ROW(Zeiterfassung!$D$6:$D$3665)-ROW(Zeiterfassung!$D$6)+1)/(Zeiterfassung!$D$6:$D$3665<>""),37),"")
A43: =IF($K43="","",WEEKNUM(INDEX(Zeiterfassung!$K$6:$K$3665,$K43),21)) | B43: =IF($K43="","",INDEX(Zeiterfassung!$K$6:$K$3665,$K43)) | C43: =IF($K43="","",INDEX(Zeiterfassung!$K$6:$K$3665,$K43)) | D43: =IF($K43="","",INDEX(Zeiterfassung!$D$6:$D$3665,$K43)) | E43: =IF($K43="","",INDEX(Zeiterfassung!$E$6:$E$3665,$K43)) | F43: =IF($K43="","",INDEX(Zeiterfassung!$F$6:$F$3665,$K43)) | G43: =IF($K43="","",INDEX(Zeiterfassung!$G$6:$G$3665,$K43)) | H43: =IF($K43="","",INDEX(Zeiterfassung!$H$6:$H$3665,$K43)) | I43: =IF(B43=B42,"",IF($K43="","",INDEX(Zeiterfassung!$I$6:$I$3665,MATCH(INDEX(Zeiterfassung!$K$6:$K$3665,$K43),Zeiterfassung!$K$6:$K$3665,0)))) | J43: =IF(B43=B42,"",IF($K43="","",INDEX(Zeiterfassung!$J$6:$J$3665,MATCH(INDEX(Zeiterfassung!$K$6:$K$3665,$K43),Zeiterfassung!$K$6:$K$3665,0)))) | K43: =IFERROR(AGGREGATE(15,6,(ROW(Zeiterfassung!$D$6:$D$3665)-ROW(Zeiterfassung!$D$6)+1)/(Zeiterfassung!$D$6:$D$3665<>""),38),"")
A44: =IF($K44="","",WEEKNUM(INDEX(Zeiterfassung!$K$6:$K$3665,$K44),21)) | B44: =IF($K44="","",INDEX(Zeiterfassung!$K$6:$K$3665,$K44)) | C44: =IF($K44="","",INDEX(Zeiterfassung!$K$6:$K$3665,$K44)) | D44: =IF($K44="","",INDEX(Zeiterfassung!$D$6:$D$3665,$K44)) | E44: =IF($K44="","",INDEX(Zeiterfassung!$E$6:$E$3665,$K44)) | F44: =IF($K44="","",INDEX(Zeiterfassung!$F$6:$F$3665,$K44)) | G44: =IF($K44="","",INDEX(Zeiterfassung!$G$6:$G$3665,$K44)) | H44: =IF($K44="","",INDEX(Zeiterfassung!$H$6:$H$3665,$K44)) | I44: =IF(B44=B43,"",IF($K44="","",INDEX(Zeiterfassung!$I$6:$I$3665,MATCH(INDEX(Zeiterfassung!$K$6:$K$3665,$K44),Zeiterfassung!$K$6:$K$3665,0)))) | J44: =IF(B44=B43,"",IF($K44="","",INDEX(Zeiterfassung!$J$6:$J$3665,MATCH(INDEX(Zeiterfassung!$K$6:$K$3665,$K44),Zeiterfassung!$K$6:$K$3665,0)))) | K44: =IFERROR(AGGREGATE(15,6,(ROW(Zeiterfassung!$D$6:$D$3665)-ROW(Zeiterfassung!$D$6)+1)/(Zeiterfassung!$D$6:$D$3665<>""),39),"")
A45: =IF($K45="","",WEEKNUM(INDEX(Zeiterfassung!$K$6:$K$3665,$K45),21)) | B45: =IF($K45="","",INDEX(Zeiterfassung!$K$6:$K$3665,$K45)) | C45: =IF($K45="","",INDEX(Zeiterfassung!$K$6:$K$3665,$K45)) | D45: =IF($K45="","",INDEX(Zeiterfassung!$D$6:$D$3665,$K45)) | E45: =IF($K45="","",INDEX(Zeiterfassung!$E$6:$E$3665,$K45)) | F45: =IF($K45="","",INDEX(Zeiterfassung!$F$6:$F$3665,$K45)) | G45: =IF($K45="","",INDEX(Zeiterfassung!$G$6:$G$3665,$K45)) | H45: =IF($K45="","",INDEX(Zeiterfassung!$H$6:$H$3665,$K45)) | I45: =IF(B45=B44,"",IF($K45="","",INDEX(Zeiterfassung!$I$6:$I$3665,MATCH(INDEX(Zeiterfassung!$K$6:$K$3665,$K45),Zeiterfassung!$K$6:$K$3665,0)))) | J45: =IF(B45=B44,"",IF($K45="","",INDEX(Zeiterfassung!$J$6:$J$3665,MATCH(INDEX(Zeiterfassung!$K$6:$K$3665,$K45),Zeiterfassung!$K$6:$K$3665,0)))) | K45: =IFERROR(AGGREGATE(15,6,(ROW(Zeiterfassung!$D$6:$D$3665)-ROW(Zeiterfassung!$D$6)+1)/(Zeiterfassung!$D$6:$D$3665<>""),40),"")
A46: =IF($K46="","",WEEKNUM(INDEX(Zeiterfassung!$K$6:$K$3665,$K46),21)) | B46: =IF($K46="","",INDEX(Zeiterfassung!$K$6:$K$3665,$K46)) | C46: =IF($K46="","",INDEX(Zeiterfassung!$K$6:$K$3665,$K46)) | D46: =IF($K46="","",INDEX(Zeiterfassung!$D$6:$D$3665,$K46)) | E46: =IF($K46="","",INDEX(Zeiterfassung!$E$6:$E$3665,$K46)) | F46: =IF($K46="","",INDEX(Zeiterfassung!$F$6:$F$3665,$K46)) | G46: =IF($K46="","",INDEX(Zeiterfassung!$G$6:$G$3665,$K46)) | H46: =IF($K46="","",INDEX(Zeiterfassung!$H$6:$H$3665,$K46)) | I46: =IF(B46=B45,"",IF($K46="","",INDEX(Zeiterfassung!$I$6:$I$3665,MATCH(INDEX(Zeiterfassung!$K$6:$K$3665,$K46),Zeiterfassung!$K$6:$K$3665,0)))) | J46: =IF(B46=B45,"",IF($K46="","",INDEX(Zeiterfassung!$J$6:$J$3665,MATCH(INDEX(Zeiterfassung!$K$6:$K$3665,$K46),Zeiterfassung!$K$6:$K$3665,0)))) | K46: =IFERROR(AGGREGATE(15,6,(ROW(Zeiterfassung!$D$6:$D$3665)-ROW(Zeiterfassung!$D$6)+1)/(Zeiterfassung!$D$6:$D$3665<>""),41),"")
A47: =IF($K47="","",WEEKNUM(INDEX(Zeiterfassung!$K$6:$K$3665,$K47),21)) | B47: =IF($K47="","",INDEX(Zeiterfassung!$K$6:$K$3665,$K47)) | C47: =IF($K47="","",INDEX(Zeiterfassung!$K$6:$K$3665,$K47)) | D47: =IF($K47="","",INDEX(Zeiterfassung!$D$6:$D$3665,$K47)) | E47: =IF($K47="","",INDEX(Zeiterfassung!$E$6:$E$3665,$K47)) | F47: =IF($K47="","",INDEX(Zeiterfassung!$F$6:$F$3665,$K47)) | G47: =IF($K47="","",INDEX(Zeiterfassung!$G$6:$G$3665,$K47)) | H47: =IF($K47="","",INDEX(Zeiterfassung!$H$6:$H$3665,$K47)) | I47: =IF(B47=B46,"",IF($K47="","",INDEX(Zeiterfassung!$I$6:$I$3665,MATCH(INDEX(Zeiterfassung!$K$6:$K$3665,$K47),Zeiterfassung!$K$6:$K$3665,0)))) | J47: =IF(B47=B46,"",IF($K47="","",INDEX(Zeiterfassung!$J$6:$J$3665,MATCH(INDEX(Zeiterfassung!$K$6:$K$3665,$K47),Zeiterfassung!$K$6:$K$3665,0)))) | K47: =IFERROR(AGGREGATE(15,6,(ROW(Zeiterfassung!$D$6:$D$3665)-ROW(Zeiterfassung!$D$6)+1)/(Zeiterfassung!$D$6:$D$3665<>""),42),"")
A48: =IF($K48="","",WEEKNUM(INDEX(Zeiterfassung!$K$6:$K$3665,$K48),21)) | B48: =IF($K48="","",INDEX(Zeiterfassung!$K$6:$K$3665,$K48)) | C48: =IF($K48="","",INDEX(Zeiterfassung!$K$6:$K$3665,$K48)) | D48: =IF($K48="","",INDEX(Zeiterfassung!$D$6:$D$3665,$K48)) | E48: =IF($K48="","",INDEX(Zeiterfassung!$E$6:$E$3665,$K48)) | F48: =IF($K48="","",INDEX(Zeiterfassung!$F$6:$F$3665,$K48)) | G48: =IF($K48="","",INDEX(Zeiterfassung!$G$6:$G$3665,$K48)) | H48: =IF($K48="","",INDEX(Zeiterfassung!$H$6:$H$3665,$K48)) | I48: =IF(B48=B47,"",IF($K48="","",INDEX(Zeiterfassung!$I$6:$I$3665,MATCH(INDEX(Zeiterfassung!$K$6:$K$3665,$K48),Zeiterfassung!$K$6:$K$3665,0)))) | J48: =IF(B48=B47,"",IF($K48="","",INDEX(Zeiterfassung!$J$6:$J$3665,MATCH(INDEX(Zeiterfassung!$K$6:$K$3665,$K48),Zeiterfassung!$K$6:$K$3665,0)))) | K48: =IFERROR(AGGREGATE(15,6,(ROW(Zeiterfassung!$D$6:$D$3665)-ROW(Zeiterfassung!$D$6)+1)/(Zeiterfassung!$D$6:$D$3665<>""),43),"")
A49: =IF($K49="","",WEEKNUM(INDEX(Zeiterfassung!$K$6:$K$3665,$K49),21)) | B49: =IF($K49="","",INDEX(Zeiterfassung!$K$6:$K$3665,$K49)) | C49: =IF($K49="","",INDEX(Zeiterfassung!$K$6:$K$3665,$K49)) | D49: =IF($K49="","",INDEX(Zeiterfassung!$D$6:$D$3665,$K49)) | E49: =IF($K49="","",INDEX(Zeiterfassung!$E$6:$E$3665,$K49)) | F49: =IF($K49="","",INDEX(Zeiterfassung!$F$6:$F$3665,$K49)) | G49: =IF($K49="","",INDEX(Zeiterfassung!$G$6:$G$3665,$K49)) | H49: =IF($K49="","",INDEX(Zeiterfassung!$H$6:$H$3665,$K49)) | I49: =IF(B49=B48,"",IF($K49="","",INDEX(Zeiterfassung!$I$6:$I$3665,MATCH(INDEX(Zeiterfassung!$K$6:$K$3665,$K49),Zeiterfassung!$K$6:$K$3665,0)))) | J49: =IF(B49=B48,"",IF($K49="","",INDEX(Zeiterfassung!$J$6:$J$3665,MATCH(INDEX(Zeiterfassung!$K$6:$K$3665,$K49),Zeiterfassung!$K$6:$K$3665,0)))) | K49: =IFERROR(AGGREGATE(15,6,(ROW(Zeiterfassung!$D$6:$D$3665)-ROW(Zeiterfassung!$D$6)+1)/(Zeiterfassung!$D$6:$D$3665<>""),44),"")
A50: =IF($K50="","",WEEKNUM(INDEX(Zeiterfassung!$K$6:$K$3665,$K50),21)) | B50: =IF($K50="","",INDEX(Zeiterfassung!$K$6:$K$3665,$K50)) | C50: =IF($K50="","",INDEX(Zeiterfassung!$K$6:$K$3665,$K50)) | D50: =IF($K50="","",INDEX(Zeiterfassung!$D$6:$D$3665,$K50)) | E50: =IF($K50="","",INDEX(Zeiterfassung!$E$6:$E$3665,$K50)) | F50: =IF($K50="","",INDEX(Zeiterfassung!$F$6:$F$3665,$K50)) | G50: =IF($K50="","",INDEX(Zeiterfassung!$G$6:$G$3665,$K50)) | H50: =IF($K50="","",INDEX(Zeiterfassung!$H$6:$H$3665,$K50)) | I50: =IF(B50=B49,"",IF($K50="","",INDEX(Zeiterfassung!$I$6:$I$3665,MATCH(INDEX(Zeiterfassung!$K$6:$K$3665,$K50),Zeiterfassung!$K$6:$K$3665,0)))) | J50: =IF(B50=B49,"",IF($K50="","",INDEX(Zeiterfassung!$J$6:$J$3665,MATCH(INDEX(Zeiterfassung!$K$6:$K$3665,$K50),Zeiterfassung!$K$6:$K$3665,0)))) | K50: =IFERROR(AGGREGATE(15,6,(ROW(Zeiterfassung!$D$6:$D$3665)-ROW(Zeiterfassung!$D$6)+1)/(Zeiterfassung!$D$6:$D$3665<>""),45),"")
A51: =IF($K51="","",WEEKNUM(INDEX(Zeiterfassung!$K$6:$K$3665,$K51),21)) | B51: =IF($K51="","",INDEX(Zeiterfassung!$K$6:$K$3665,$K51)) | C51: =IF($K51="","",INDEX(Zeiterfassung!$K$6:$K$3665,$K51)) | D51: =IF($K51="","",INDEX(Zeiterfassung!$D$6:$D$3665,$K51)) | E51: =IF($K51="","",INDEX(Zeiterfassung!$E$6:$E$3665,$K51)) | F51: =IF($K51="","",INDEX(Zeiterfassung!$F$6:$F$3665,$K51)) | G51: =IF($K51="","",INDEX(Zeiterfassung!$G$6:$G$3665,$K51)) | H51: =IF($K51="","",INDEX(Zeiterfassung!$H$6:$H$3665,$K51)) | I51: =IF(B51=B50,"",IF($K51="","",INDEX(Zeiterfassung!$I$6:$I$3665,MATCH(INDEX(Zeiterfassung!$K$6:$K$3665,$K51),Zeiterfassung!$K$6:$K$3665,0)))) | J51: =IF(B51=B50,"",IF($K51="","",INDEX(Zeiterfassung!$J$6:$J$3665,MATCH(INDEX(Zeiterfassung!$K$6:$K$3665,$K51),Zeiterfassung!$K$6:$K$3665,0)))) | K51: =IFERROR(AGGREGATE(15,6,(ROW(Zeiterfassung!$D$6:$D$3665)-ROW(Zeiterfassung!$D$6)+1)/(Zeiterfassung!$D$6:$D$3665<>""),46),"")
A52: =IF($K52="","",WEEKNUM(INDEX(Zeiterfassung!$K$6:$K$3665,$K52),21)) | B52: =IF($K52="","",INDEX(Zeiterfassung!$K$6:$K$3665,$K52)) | C52: =IF($K52="","",INDEX(Zeiterfassung!$K$6:$K$3665,$K52)) | D52: =IF($K52="","",INDEX(Zeiterfassung!$D$6:$D$3665,$K52)) | E52: =IF($K52="","",INDEX(Zeiterfassung!$E$6:$E$3665,$K52)) | F52: =IF($K52="","",INDEX(Zeiterfassung!$F$6:$F$3665,$K52)) | G52: =IF($K52="","",INDEX(Zeiterfassung!$G$6:$G$3665,$K52)) | H52: =IF($K52="","",INDEX(Zeiterfassung!$H$6:$H$3665,$K52)) | I52: =IF(B52=B51,"",IF($K52="","",INDEX(Zeiterfassung!$I$6:$I$3665,MATCH(INDEX(Zeiterfassung!$K$6:$K$3665,$K52),Zeiterfassung!$K$6:$K$3665,0)))) | J52: =IF(B52=B51,"",IF($K52="","",INDEX(Zeiterfassung!$J$6:$J$3665,MATCH(INDEX(Zeiterfassung!$K$6:$K$3665,$K52),Zeiterfassung!$K$6:$K$3665,0)))) | K52: =IFERROR(AGGREGATE(15,6,(ROW(Zeiterfassung!$D$6:$D$3665)-ROW(Zeiterfassung!$D$6)+1)/(Zeiterfassung!$D$6:$D$3665<>""),47),"")
A53: =IF($K53="","",WEEKNUM(INDEX(Zeiterfassung!$K$6:$K$3665,$K53),21)) | B53: =IF($K53="","",INDEX(Zeiterfassung!$K$6:$K$3665,$K53)) | C53: =IF($K53="","",INDEX(Zeiterfassung!$K$6:$K$3665,$K53)) | D53: =IF($K53="","",INDEX(Zeiterfassung!$D$6:$D$3665,$K53)) | E53: =IF($K53="","",INDEX(Zeiterfassung!$E$6:$E$3665,$K53)) | F53: =IF($K53="","",INDEX(Zeiterfassung!$F$6:$F$3665,$K53)) | G53: =IF($K53="","",INDEX(Zeiterfassung!$G$6:$G$3665,$K53)) | H53: =IF($K53="","",INDEX(Zeiterfassung!$H$6:$H$3665,$K53)) | I53: =IF(B53=B52,"",IF($K53="","",INDEX(Zeiterfassung!$I$6:$I$3665,MATCH(INDEX(Zeiterfassung!$K$6:$K$3665,$K53),Zeiterfassung!$K$6:$K$3665,0)))) | J53: =IF(B53=B52,"",IF($K53="","",INDEX(Zeiterfassung!$J$6:$J$3665,MATCH(INDEX(Zeiterfassung!$K$6:$K$3665,$K53),Zeiterfassung!$K$6:$K$3665,0)))) | K53: =IFERROR(AGGREGATE(15,6,(ROW(Zeiterfassung!$D$6:$D$3665)-ROW(Zeiterfassung!$D$6)+1)/(Zeiterfassung!$D$6:$D$3665<>""),48),"")
A54: =IF($K54="","",WEEKNUM(INDEX(Zeiterfassung!$K$6:$K$3665,$K54),21)) | B54: =IF($K54="","",INDEX(Zeiterfassung!$K$6:$K$3665,$K54)) | C54: =IF($K54="","",INDEX(Zeiterfassung!$K$6:$K$3665,$K54)) | D54: =IF($K54="","",INDEX(Zeiterfassung!$D$6:$D$3665,$K54)) | E54: =IF($K54="","",INDEX(Zeiterfassung!$E$6:$E$3665,$K54)) | F54: =IF($K54="","",INDEX(Zeiterfassung!$F$6:$F$3665,$K54)) | G54: =IF($K54="","",INDEX(Zeiterfassung!$G$6:$G$3665,$K54)) | H54: =IF($K54="","",INDEX(Zeiterfassung!$H$6:$H$3665,$K54)) | I54: =IF(B54=B53,"",IF($K54="","",INDEX(Zeiterfassung!$I$6:$I$3665,MATCH(INDEX(Zeiterfassung!$K$6:$K$3665,$K54),Zeiterfassung!$K$6:$K$3665,0)))) | J54: =IF(B54=B53,"",IF($K54="","",INDEX(Zeiterfassung!$J$6:$J$3665,MATCH(INDEX(Zeiterfassung!$K$6:$K$3665,$K54),Zeiterfassung!$K$6:$K$3665,0)))) | K54: =IFERROR(AGGREGATE(15,6,(ROW(Zeiterfassung!$D$6:$D$3665)-ROW(Zeiterfassung!$D$6)+1)/(Zeiterfassung!$D$6:$D$3665<>""),49),"")
A55: =IF($K55="","",WEEKNUM(INDEX(Zeiterfassung!$K$6:$K$3665,$K55),21)) | B55: =IF($K55="","",INDEX(Zeiterfassung!$K$6:$K$3665,$K55)) | C55: =IF($K55="","",INDEX(Zeiterfassung!$K$6:$K$3665,$K55)) | D55: =IF($K55="","",INDEX(Zeiterfassung!$D$6:$D$3665,$K55)) | E55: =IF($K55="","",INDEX(Zeiterfassung!$E$6:$E$3665,$K55)) | F55: =IF($K55="","",INDEX(Zeiterfassung!$F$6:$F$3665,$K55)) | G55: =IF($K55="","",INDEX(Zeiterfassung!$G$6:$G$3665,$K55)) | H55: =IF($K55="","",INDEX(Zeiterfassung!$H$6:$H$3665,$K55)) | I55: =IF(B55=B54,"",IF($K55="","",INDEX(Zeiterfassung!$I$6:$I$3665,MATCH(INDEX(Zeiterfassung!$K$6:$K$3665,$K55),Zeiterfassung!$K$6:$K$3665,0)))) | J55: =IF(B55=B54,"",IF($K55="","",INDEX(Zeiterfassung!$J$6:$J$3665,MATCH(INDEX(Zeiterfassung!$K$6:$K$3665,$K55),Zeiterfassung!$K$6:$K$3665,0)))) | K55: =IFERROR(AGGREGATE(15,6,(ROW(Zeiterfassung!$D$6:$D$3665)-ROW(Zeiterfassung!$D$6)+1)/(Zeiterfassung!$D$6:$D$3665<>""),50),"")
A56: =IF($K56="","",WEEKNUM(INDEX(Zeiterfassung!$K$6:$K$3665,$K56),21)) | B56: =IF($K56="","",INDEX(Zeiterfassung!$K$6:$K$3665,$K56)) | C56: =IF($K56="","",INDEX(Zeiterfassung!$K$6:$K$3665,$K56)) | D56: =IF($K56="","",INDEX(Zeiterfassung!$D$6:$D$3665,$K56)) | E56: =IF($K56="","",INDEX(Zeiterfassung!$E$6:$E$3665,$K56)) | F56: =IF($K56="","",INDEX(Zeiterfassung!$F$6:$F$3665,$K56)) | G56: =IF($K56="","",INDEX(Zeiterfassung!$G$6:$G$3665,$K56)) | H56: =IF($K56="","",INDEX(Zeiterfassung!$H$6:$H$3665,$K56)) | I56: =IF(B56=B55,"",IF($K56="","",INDEX(Zeiterfassung!$I$6:$I$3665,MATCH(INDEX(Zeiterfassung!$K$6:$K$3665,$K56),Zeiterfassung!$K$6:$K$3665,0)))) | J56: =IF(B56=B55,"",IF($K56="","",INDEX(Zeiterfassung!$J$6:$J$3665,MATCH(INDEX(Zeiterfassung!$K$6:$K$3665,$K56),Zeiterfassung!$K$6:$K$3665,0)))) | K56: =IFERROR(AGGREGATE(15,6,(ROW(Zeiterfassung!$D$6:$D$3665)-ROW(Zeiterfassung!$D$6)+1)/(Zeiterfassung!$D$6:$D$3665<>""),51),"")
A57: =IF($K57="","",WEEKNUM(INDEX(Zeiterfassung!$K$6:$K$3665,$K57),21)) | B57: =IF($K57="","",INDEX(Zeiterfassung!$K$6:$K$3665,$K57)) | C57: =IF($K57="","",INDEX(Zeiterfassung!$K$6:$K$3665,$K57)) | D57: =IF($K57="","",INDEX(Zeiterfassung!$D$6:$D$3665,$K57)) | E57: =IF($K57="","",INDEX(Zeiterfassung!$E$6:$E$3665,$K57)) | F57: =IF($K57="","",INDEX(Zeiterfassung!$F$6:$F$3665,$K57)) | G57: =IF($K57="","",INDEX(Zeiterfassung!$G$6:$G$3665,$K57)) | H57: =IF($K57="","",INDEX(Zeiterfassung!$H$6:$H$3665,$K57)) | I57: =IF(B57=B56,"",IF($K57="","",INDEX(Zeiterfassung!$I$6:$I$3665,MATCH(INDEX(Zeiterfassung!$K$6:$K$3665,$K57),Zeiterfassung!$K$6:$K$3665,0)))) | J57: =IF(B57=B56,"",IF($K57="","",INDEX(Zeiterfassung!$J$6:$J$3665,MATCH(INDEX(Zeiterfassung!$K$6:$K$3665,$K57),Zeiterfassung!$K$6:$K$3665,0)))) | K57: =IFERROR(AGGREGATE(15,6,(ROW(Zeiterfassung!$D$6:$D$3665)-ROW(Zeiterfassung!$D$6)+1)/(Zeiterfassung!$D$6:$D$3665<>""),52),"")
A58: =IF($K58="","",WEEKNUM(INDEX(Zeiterfassung!$K$6:$K$3665,$K58),21)) | B58: =IF($K58="","",INDEX(Zeiterfassung!$K$6:$K$3665,$K58)) | C58: =IF($K58="","",INDEX(Zeiterfassung!$K$6:$K$3665,$K58)) | D58: =IF($K58="","",INDEX(Zeiterfassung!$D$6:$D$3665,$K58)) | E58: =IF($K58="","",INDEX(Zeiterfassung!$E$6:$E$3665,$K58)) | F58: =IF($K58="","",INDEX(Zeiterfassung!$F$6:$F$3665,$K58)) | G58: =IF($K58="","",INDEX(Zeiterfassung!$G$6:$G$3665,$K58)) | H58: =IF($K58="","",INDEX(Zeiterfassung!$H$6:$H$3665,$K58)) | I58: =IF(B58=B57,"",IF($K58="","",INDEX(Zeiterfassung!$I$6:$I$3665,MATCH(INDEX(Zeiterfassung!$K$6:$K$3665,$K58),Zeiterfassung!$K$6:$K$3665,0)))) | J58: =IF(B58=B57,"",IF($K58="","",INDEX(Zeiterfassung!$J$6:$J$3665,MATCH(INDEX(Zeiterfassung!$K$6:$K$3665,$K58),Zeiterfassung!$K$6:$K$3665,0)))) | K58: =IFERROR(AGGREGATE(15,6,(ROW(Zeiterfassung!$D$6:$D$3665)-ROW(Zeiterfassung!$D$6)+1)/(Zeiterfassung!$D$6:$D$3665<>""),53),"")
A59: =IF($K59="","",WEEKNUM(INDEX(Zeiterfassung!$K$6:$K$3665,$K59),21)) | B59: =IF($K59="","",INDEX(Zeiterfassung!$K$6:$K$3665,$K59)) | C59: =IF($K59="","",INDEX(Zeiterfassung!$K$6:$K$3665,$K59)) | D59: =IF($K59="","",INDEX(Zeiterfassung!$D$6:$D$3665,$K59)) | E59: =IF($K59="","",INDEX(Zeiterfassung!$E$6:$E$3665,$K59)) | F59: =IF($K59="","",INDEX(Zeiterfassung!$F$6:$F$3665,$K59)) | G59: =IF($K59="","",INDEX(Zeiterfassung!$G$6:$G$3665,$K59)) | H59: =IF($K59="","",INDEX(Zeiterfassung!$H$6:$H$3665,$K59)) | I59: =IF(B59=B58,"",IF($K59="","",INDEX(Zeiterfassung!$I$6:$I$3665,MATCH(INDEX(Zeiterfassung!$K$6:$K$3665,$K59),Zeiterfassung!$K$6:$K$3665,0)))) | J59: =IF(B59=B58,"",IF($K59="","",INDEX(Zeiterfassung!$J$6:$J$3665,MATCH(INDEX(Zeiterfassung!$K$6:$K$3665,$K59),Zeiterfassung!$K$6:$K$3665,0)))) | K59: =IFERROR(AGGREGATE(15,6,(ROW(Zeiterfassung!$D$6:$D$3665)-ROW(Zeiterfassung!$D$6)+1)/(Zeiterfassung!$D$6:$D$3665<>""),54),"")
A60: =IF($K60="","",WEEKNUM(INDEX(Zeiterfassung!$K$6:$K$3665,$K60),21)) | B60: =IF($K60="","",INDEX(Zeiterfassung!$K$6:$K$3665,$K60)) | C60: =IF($K60="","",INDEX(Zeiterfassung!$K$6:$K$3665,$K60)) | D60: =IF($K60="","",INDEX(Zeiterfassung!$D$6:$D$3665,$K60)) | E60: =IF($K60="","",INDEX(Zeiterfassung!$E$6:$E$3665,$K60)) | F60: =IF($K60="","",INDEX(Zeiterfassung!$F$6:$F$3665,$K60)) | G60: =IF($K60="","",INDEX(Zeiterfassung!$G$6:$G$3665,$K60)) | H60: =IF($K60="","",INDEX(Zeiterfassung!$H$6:$H$3665,$K60)) | I60: =IF(B60=B59,"",IF($K60="","",INDEX(Zeiterfassung!$I$6:$I$3665,MATCH(INDEX(Zeiterfassung!$K$6:$K$3665,$K60),Zeiterfassung!$K$6:$K$3665,0)))) | J60: =IF(B60=B59,"",IF($K60="","",INDEX(Zeiterfassung!$J$6:$J$3665,MATCH(INDEX(Zeiterfassung!$K$6:$K$3665,$K60),Zeiterfassung!$K$6:$K$3665,0)))) | K60: =IFERROR(AGGREGATE(15,6,(ROW(Zeiterfassung!$D$6:$D$3665)-ROW(Zeiterfassung!$D$6)+1)/(Zeiterfassung!$D$6:$D$3665<>""),55),"")
A61: =IF($K61="","",WEEKNUM(INDEX(Zeiterfassung!$K$6:$K$3665,$K61),21)) | B61: =IF($K61="","",INDEX(Zeiterfassung!$K$6:$K$3665,$K61)) | C61: =IF($K61="","",INDEX(Zeiterfassung!$K$6:$K$3665,$K61)) | D61: =IF($K61="","",INDEX(Zeiterfassung!$D$6:$D$3665,$K61)) | E61: =IF($K61="","",INDEX(Zeiterfassung!$E$6:$E$3665,$K61)) | F61: =IF($K61="","",INDEX(Zeiterfassung!$F$6:$F$3665,$K61)) | G61: =IF($K61="","",INDEX(Zeiterfassung!$G$6:$G$3665,$K61)) | H61: =IF($K61="","",INDEX(Zeiterfassung!$H$6:$H$3665,$K61)) | I61: =IF(B61=B60,"",IF($K61="","",INDEX(Zeiterfassung!$I$6:$I$3665,MATCH(INDEX(Zeiterfassung!$K$6:$K$3665,$K61),Zeiterfassung!$K$6:$K$3665,0)))) | J61: =IF(B61=B60,"",IF($K61="","",INDEX(Zeiterfassung!$J$6:$J$3665,MATCH(INDEX(Zeiterfassung!$K$6:$K$3665,$K61),Zeiterfassung!$K$6:$K$3665,0)))) | K61: =IFERROR(AGGREGATE(15,6,(ROW(Zeiterfassung!$D$6:$D$3665)-ROW(Zeiterfassung!$D$6)+1)/(Zeiterfassung!$D$6:$D$3665<>""),56),"")
A62: =IF($K62="","",WEEKNUM(INDEX(Zeiterfassung!$K$6:$K$3665,$K62),21)) | B62: =IF($K62="","",INDEX(Zeiterfassung!$K$6:$K$3665,$K62)) | C62: =IF($K62="","",INDEX(Zeiterfassung!$K$6:$K$3665,$K62)) | D62: =IF($K62="","",INDEX(Zeiterfassung!$D$6:$D$3665,$K62)) | E62: =IF($K62="","",INDEX(Zeiterfassung!$E$6:$E$3665,$K62)) | F62: =IF($K62="","",INDEX(Zeiterfassung!$F$6:$F$3665,$K62)) | G62: =IF($K62="","",INDEX(Zeiterfassung!$G$6:$G$3665,$K62)) | H62: =IF($K62="","",INDEX(Zeiterfassung!$H$6:$H$3665,$K62)) | I62: =IF(B62=B61,"",IF($K62="","",INDEX(Zeiterfassung!$I$6:$I$3665,MATCH(INDEX(Zeiterfassung!$K$6:$K$3665,$K62),Zeiterfassung!$K$6:$K$3665,0)))) | J62: =IF(B62=B61,"",IF($K62="","",INDEX(Zeiterfassung!$J$6:$J$3665,MATCH(INDEX(Zeiterfassung!$K$6:$K$3665,$K62),Zeiterfassung!$K$6:$K$3665,0)))) | K62: =IFERROR(AGGREGATE(15,6,(ROW(Zeiterfassung!$D$6:$D$3665)-ROW(Zeiterfassung!$D$6)+1)/(Zeiterfassung!$D$6:$D$3665<>""),57),"")
A63: =IF($K63="","",WEEKNUM(INDEX(Zeiterfassung!$K$6:$K$3665,$K63),21)) | B63: =IF($K63="","",INDEX(Zeiterfassung!$K$6:$K$3665,$K63)) | C63: =IF($K63="","",INDEX(Zeiterfassung!$K$6:$K$3665,$K63)) | D63: =IF($K63="","",INDEX(Zeiterfassung!$D$6:$D$3665,$K63)) | E63: =IF($K63="","",INDEX(Zeiterfassung!$E$6:$E$3665,$K63)) | F63: =IF($K63="","",INDEX(Zeiterfassung!$F$6:$F$3665,$K63)) | G63: =IF($K63="","",INDEX(Zeiterfassung!$G$6:$G$3665,$K63)) | H63: =IF($K63="","",INDEX(Zeiterfassung!$H$6:$H$3665,$K63)) | I63: =IF(B63=B62,"",IF($K63="","",INDEX(Zeiterfassung!$I$6:$I$3665,MATCH(INDEX(Zeiterfassung!$K$6:$K$3665,$K63),Zeiterfassung!$K$6:$K$3665,0)))) | J63: =IF(B63=B62,"",IF($K63="","",INDEX(Zeiterfassung!$J$6:$J$3665,MATCH(INDEX(Zeiterfassung!$K$6:$K$3665,$K63),Zeiterfassung!$K$6:$K$3665,0)))) | K63: =IFERROR(AGGREGATE(15,6,(ROW(Zeiterfassung!$D$6:$D$3665)-ROW(Zeiterfassung!$D$6)+1)/(Zeiterfassung!$D$6:$D$3665<>""),58),"")
A64: =IF($K64="","",WEEKNUM(INDEX(Zeiterfassung!$K$6:$K$3665,$K64),21)) | B64: =IF($K64="","",INDEX(Zeiterfassung!$K$6:$K$3665,$K64)) | C64: =IF($K64="","",INDEX(Zeiterfassung!$K$6:$K$3665,$K64)) | D64: =IF($K64="","",INDEX(Zeiterfassung!$D$6:$D$3665,$K64)) | E64: =IF($K64="","",INDEX(Zeiterfassung!$E$6:$E$3665,$K64)) | F64: =IF($K64="","",INDEX(Zeiterfassung!$F$6:$F$3665,$K64)) | G64: =IF($K64="","",INDEX(Zeiterfassung!$G$6:$G$3665,$K64)) | H64: =IF($K64="","",INDEX(Zeiterfassung!$H$6:$H$3665,$K64)) | I64: =IF(B64=B63,"",IF($K64="","",INDEX(Zeiterfassung!$I$6:$I$3665,MATCH(INDEX(Zeiterfassung!$K$6:$K$3665,$K64),Zeiterfassung!$K$6:$K$3665,0)))) | J64: =IF(B64=B63,"",IF($K64="","",INDEX(Zeiterfassung!$J$6:$J$3665,MATCH(INDEX(Zeiterfassung!$K$6:$K$3665,$K64),Zeiterfassung!$K$6:$K$3665,0)))) | K64: =IFERROR(AGGREGATE(15,6,(ROW(Zeiterfassung!$D$6:$D$3665)-ROW(Zeiterfassung!$D$6)+1)/(Zeiterfassung!$D$6:$D$3665<>""),59),"")
A65: =IF($K65="","",WEEKNUM(INDEX(Zeiterfassung!$K$6:$K$3665,$K65),21)) | B65: =IF($K65="","",INDEX(Zeiterfassung!$K$6:$K$3665,$K65)) | C65: =IF($K65="","",INDEX(Zeiterfassung!$K$6:$K$3665,$K65)) | D65: =IF($K65="","",INDEX(Zeiterfassung!$D$6:$D$3665,$K65)) | E65: =IF($K65="","",INDEX(Zeiterfassung!$E$6:$E$3665,$K65)) | F65: =IF($K65="","",INDEX(Zeiterfassung!$F$6:$F$3665,$K65)) | G65: =IF($K65="","",INDEX(Zeiterfassung!$G$6:$G$3665,$K65)) | H65: =IF($K65="","",INDEX(Zeiterfassung!$H$6:$H$3665,$K65)) | I65: =IF(B65=B64,"",IF($K65="","",INDEX(Zeiterfassung!$I$6:$I$3665,MATCH(INDEX(Zeiterfassung!$K$6:$K$3665,$K65),Zeiterfassung!$K$6:$K$3665,0)))) | J65: =IF(B65=B64,"",IF($K65="","",INDEX(Zeiterfassung!$J$6:$J$3665,MATCH(INDEX(Zeiterfassung!$K$6:$K$3665,$K65),Zeiterfassung!$K$6:$K$3665,0)))) | K65: =IFERROR(AGGREGATE(15,6,(ROW(Zeiterfassung!$D$6:$D$3665)-ROW(Zeiterfassung!$D$6)+1)/(Zeiterfassung!$D$6:$D$3665<>""),60),"")
A66: =IF($K66="","",WEEKNUM(INDEX(Zeiterfassung!$K$6:$K$3665,$K66),21)) | B66: =IF($K66="","",INDEX(Zeiterfassung!$K$6:$K$3665,$K66)) | C66: =IF($K66="","",INDEX(Zeiterfassung!$K$6:$K$3665,$K66)) | D66: =IF($K66="","",INDEX(Zeiterfassung!$D$6:$D$3665,$K66)) | E66: =IF($K66="","",INDEX(Zeiterfassung!$E$6:$E$3665,$K66)) | F66: =IF($K66="","",INDEX(Zeiterfassung!$F$6:$F$3665,$K66)) | G66: =IF($K66="","",INDEX(Zeiterfassung!$G$6:$G$3665,$K66)) | H66: =IF($K66="","",INDEX(Zeiterfassung!$H$6:$H$3665,$K66)) | I66: =IF(B66=B65,"",IF($K66="","",INDEX(Zeiterfassung!$I$6:$I$3665,MATCH(INDEX(Zeiterfassung!$K$6:$K$3665,$K66),Zeiterfassung!$K$6:$K$3665,0)))) | J66: =IF(B66=B65,"",IF($K66="","",INDEX(Zeiterfassung!$J$6:$J$3665,MATCH(INDEX(Zeiterfassung!$K$6:$K$3665,$K66),Zeiterfassung!$K$6:$K$3665,0)))) | K66: =IFERROR(AGGREGATE(15,6,(ROW(Zeiterfassung!$D$6:$D$3665)-ROW(Zeiterfassung!$D$6)+1)/(Zeiterfassung!$D$6:$D$3665<>""),61),"")
A67: =IF($K67="","",WEEKNUM(INDEX(Zeiterfassung!$K$6:$K$3665,$K67),21)) | B67: =IF($K67="","",INDEX(Zeiterfassung!$K$6:$K$3665,$K67)) | C67: =IF($K67="","",INDEX(Zeiterfassung!$K$6:$K$3665,$K67)) | D67: =IF($K67="","",INDEX(Zeiterfassung!$D$6:$D$3665,$K67)) | E67: =IF($K67="","",INDEX(Zeiterfassung!$E$6:$E$3665,$K67)) | F67: =IF($K67="","",INDEX(Zeiterfassung!$F$6:$F$3665,$K67)) | G67: =IF($K67="","",INDEX(Zeiterfassung!$G$6:$G$3665,$K67)) | H67: =IF($K67="","",INDEX(Zeiterfassung!$H$6:$H$3665,$K67)) | I67: =IF(B67=B66,"",IF($K67="","",INDEX(Zeiterfassung!$I$6:$I$3665,MATCH(INDEX(Zeiterfassung!$K$6:$K$3665,$K67),Zeiterfassung!$K$6:$K$3665,0)))) | J67: =IF(B67=B66,"",IF($K67="","",INDEX(Zeiterfassung!$J$6:$J$3665,MATCH(INDEX(Zeiterfassung!$K$6:$K$3665,$K67),Zeiterfassung!$K$6:$K$3665,0)))) | K67: =IFERROR(AGGREGATE(15,6,(ROW(Zeiterfassung!$D$6:$D$3665)-ROW(Zeiterfassung!$D$6)+1)/(Zeiterfassung!$D$6:$D$3665<>""),62),"")
A68: =IF($K68="","",WEEKNUM(INDEX(Zeiterfassung!$K$6:$K$3665,$K68),21)) | B68: =IF($K68="","",INDEX(Zeiterfassung!$K$6:$K$3665,$K68)) | C68: =IF($K68="","",INDEX(Zeiterfassung!$K$6:$K$3665,$K68)) | D68: =IF($K68="","",INDEX(Zeiterfassung!$D$6:$D$3665,$K68)) | E68: =IF($K68="","",INDEX(Zeiterfassung!$E$6:$E$3665,$K68)) | F68: =IF($K68="","",INDEX(Zeiterfassung!$F$6:$F$3665,$K68)) | G68: =IF($K68="","",INDEX(Zeiterfassung!$G$6:$G$3665,$K68)) | H68: =IF($K68="","",INDEX(Zeiterfassung!$H$6:$H$3665,$K68)) | I68: =IF(B68=B67,"",IF($K68="","",INDEX(Zeiterfassung!$I$6:$I$3665,MATCH(INDEX(Zeiterfassung!$K$6:$K$3665,$K68),Zeiterfassung!$K$6:$K$3665,0)))) | J68: =IF(B68=B67,"",IF($K68="","",INDEX(Zeiterfassung!$J$6:$J$3665,MATCH(INDEX(Zeiterfassung!$K$6:$K$3665,$K68),Zeiterfassung!$K$6:$K$3665,0)))) | K68: =IFERROR(AGGREGATE(15,6,(ROW(Zeiterfassung!$D$6:$D$3665)-ROW(Zeiterfassung!$D$6)+1)/(Zeiterfassung!$D$6:$D$3665<>""),63),"")
A69: =IF($K69="","",WEEKNUM(INDEX(Zeiterfassung!$K$6:$K$3665,$K69),21)) | B69: =IF($K69="","",INDEX(Zeiterfassung!$K$6:$K$3665,$K69)) | C69: =IF($K69="","",INDEX(Zeiterfassung!$K$6:$K$3665,$K69)) | D69: =IF($K69="","",INDEX(Zeiterfassung!$D$6:$D$3665,$K69)) | E69: =IF($K69="","",INDEX(Zeiterfassung!$E$6:$E$3665,$K69)) | F69: =IF($K69="","",INDEX(Zeiterfassung!$F$6:$F$3665,$K69)) | G69: =IF($K69="","",INDEX(Zeiterfassung!$G$6:$G$3665,$K69)) | H69: =IF($K69="","",INDEX(Zeiterfassung!$H$6:$H$3665,$K69)) | I69: =IF(B69=B68,"",IF($K69="","",INDEX(Zeiterfassung!$I$6:$I$3665,MATCH(INDEX(Zeiterfassung!$K$6:$K$3665,$K69),Zeiterfassung!$K$6:$K$3665,0)))) | J69: =IF(B69=B68,"",IF($K69="","",INDEX(Zeiterfassung!$J$6:$J$3665,MATCH(INDEX(Zeiterfassung!$K$6:$K$3665,$K69),Zeiterfassung!$K$6:$K$3665,0)))) | K69: =IFERROR(AGGREGATE(15,6,(ROW(Zeiterfassung!$D$6:$D$3665)-ROW(Zeiterfassung!$D$6)+1)/(Zeiterfassung!$D$6:$D$3665<>""),64),"")
A70: =IF($K70="","",WEEKNUM(INDEX(Zeiterfassung!$K$6:$K$3665,$K70),21)) | B70: =IF($K70="","",INDEX(Zeiterfassung!$K$6:$K$3665,$K70)) | C70: =IF($K70="","",INDEX(Zeiterfassung!$K$6:$K$3665,$K70)) | D70: =IF($K70="","",INDEX(Zeiterfassung!$D$6:$D$3665,$K70)) | E70: =IF($K70="","",INDEX(Zeiterfassung!$E$6:$E$3665,$K70)) | F70: =IF($K70="","",INDEX(Zeiterfassung!$F$6:$F$3665,$K70)) | G70: =IF($K70="","",INDEX(Zeiterfassung!$G$6:$G$3665,$K70)) | H70: =IF($K70="","",INDEX(Zeiterfassung!$H$6:$H$3665,$K70)) | I70: =IF(B70=B69,"",IF($K70="","",INDEX(Zeiterfassung!$I$6:$I$3665,MATCH(INDEX(Zeiterfassung!$K$6:$K$3665,$K70),Zeiterfassung!$K$6:$K$3665,0)))) | J70: =IF(B70=B69,"",IF($K70="","",INDEX(Zeiterfassung!$J$6:$J$3665,MATCH(INDEX(Zeiterfassung!$K$6:$K$3665,$K70),Zeiterfassung!$K$6:$K$3665,0)))) | K70: =IFERROR(AGGREGATE(15,6,(ROW(Zeiterfassung!$D$6:$D$3665)-ROW(Zeiterfassung!$D$6)+1)/(Zeiterfassung!$D$6:$D$3665<>""),65),"")
A71: =IF($K71="","",WEEKNUM(INDEX(Zeiterfassung!$K$6:$K$3665,$K71),21)) | B71: =IF($K71="","",INDEX(Zeiterfassung!$K$6:$K$3665,$K71)) | C71: =IF($K71="","",INDEX(Zeiterfassung!$K$6:$K$3665,$K71)) | D71: =IF($K71="","",INDEX(Zeiterfassung!$D$6:$D$3665,$K71)) | E71: =IF($K71="","",INDEX(Zeiterfassung!$E$6:$E$3665,$K71)) | F71: =IF($K71="","",INDEX(Zeiterfassung!$F$6:$F$3665,$K71)) | G71: =IF($K71="","",INDEX(Zeiterfassung!$G$6:$G$3665,$K71)) | H71: =IF($K71="","",INDEX(Zeiterfassung!$H$6:$H$3665,$K71)) | I71: =IF(B71=B70,"",IF($K71="","",INDEX(Zeiterfassung!$I$6:$I$3665,MATCH(INDEX(Zeiterfassung!$K$6:$K$3665,$K71),Zeiterfassung!$K$6:$K$3665,0)))) | J71: =IF(B71=B70,"",IF($K71="","",INDEX(Zeiterfassung!$J$6:$J$3665,MATCH(INDEX(Zeiterfassung!$K$6:$K$3665,$K71),Zeiterfassung!$K$6:$K$3665,0)))) | K71: =IFERROR(AGGREGATE(15,6,(ROW(Zeiterfassung!$D$6:$D$3665)-ROW(Zeiterfassung!$D$6)+1)/(Zeiterfassung!$D$6:$D$3665<>""),66),"")
A72: =IF($K72="","",WEEKNUM(INDEX(Zeiterfassung!$K$6:$K$3665,$K72),21)) | B72: =IF($K72="","",INDEX(Zeiterfassung!$K$6:$K$3665,$K72)) | C72: =IF($K72="","",INDEX(Zeiterfassung!$K$6:$K$3665,$K72)) | D72: =IF($K72="","",INDEX(Zeiterfassung!$D$6:$D$3665,$K72)) | E72: =IF($K72="","",INDEX(Zeiterfassung!$E$6:$E$3665,$K72)) | F72: =IF($K72="","",INDEX(Zeiterfassung!$F$6:$F$3665,$K72)) | G72: =IF($K72="","",INDEX(Zeiterfassung!$G$6:$G$3665,$K72)) | H72: =IF($K72="","",INDEX(Zeiterfassung!$H$6:$H$3665,$K72)) | I72: =IF(B72=B71,"",IF($K72="","",INDEX(Zeiterfassung!$I$6:$I$3665,MATCH(INDEX(Zeiterfassung!$K$6:$K$3665,$K72),Zeiterfassung!$K$6:$K$3665,0)))) | J72: =IF(B72=B71,"",IF($K72="","",INDEX(Zeiterfassung!$J$6:$J$3665,MATCH(INDEX(Zeiterfassung!$K$6:$K$3665,$K72),Zeiterfassung!$K$6:$K$3665,0)))) | K72: =IFERROR(AGGREGATE(15,6,(ROW(Zeiterfassung!$D$6:$D$3665)-ROW(Zeiterfassung!$D$6)+1)/(Zeiterfassung!$D$6:$D$3665<>""),67),"")
A73: =IF($K73="","",WEEKNUM(INDEX(Zeiterfassung!$K$6:$K$3665,$K73),21)) | B73: =IF($K73="","",INDEX(Zeiterfassung!$K$6:$K$3665,$K73)) | C73: =IF($K73="","",INDEX(Zeiterfassung!$K$6:$K$3665,$K73)) | D73: =IF($K73="","",INDEX(Zeiterfassung!$D$6:$D$3665,$K73)) | E73: =IF($K73="","",INDEX(Zeiterfassung!$E$6:$E$3665,$K73)) | F73: =IF($K73="","",INDEX(Zeiterfassung!$F$6:$F$3665,$K73)) | G73: =IF($K73="","",INDEX(Zeiterfassung!$G$6:$G$3665,$K73)) | H73: =IF($K73="","",INDEX(Zeiterfassung!$H$6:$H$3665,$K73)) | I73: =IF(B73=B72,"",IF($K73="","",INDEX(Zeiterfassung!$I$6:$I$3665,MATCH(INDEX(Zeiterfassung!$K$6:$K$3665,$K73),Zeiterfassung!$K$6:$K$3665,0)))) | J73: =IF(B73=B72,"",IF($K73="","",INDEX(Zeiterfassung!$J$6:$J$3665,MATCH(INDEX(Zeiterfassung!$K$6:$K$3665,$K73),Zeiterfassung!$K$6:$K$3665,0)))) | K73: =IFERROR(AGGREGATE(15,6,(ROW(Zeiterfassung!$D$6:$D$3665)-ROW(Zeiterfassung!$D$6)+1)/(Zeiterfassung!$D$6:$D$3665<>""),68),"")
A74: =IF($K74="","",WEEKNUM(INDEX(Zeiterfassung!$K$6:$K$3665,$K74),21)) | B74: =IF($K74="","",INDEX(Zeiterfassung!$K$6:$K$3665,$K74)) | C74: =IF($K74="","",INDEX(Zeiterfassung!$K$6:$K$3665,$K74)) | D74: =IF($K74="","",INDEX(Zeiterfassung!$D$6:$D$3665,$K74)) | E74: =IF($K74="","",INDEX(Zeiterfassung!$E$6:$E$3665,$K74)) | F74: =IF($K74="","",INDEX(Zeiterfassung!$F$6:$F$3665,$K74)) | G74: =IF($K74="","",INDEX(Zeiterfassung!$G$6:$G$3665,$K74)) | H74: =IF($K74="","",INDEX(Zeiterfassung!$H$6:$H$3665,$K74)) | I74: =IF(B74=B73,"",IF($K74="","",INDEX(Zeiterfassung!$I$6:$I$3665,MATCH(INDEX(Zeiterfassung!$K$6:$K$3665,$K74),Zeiterfassung!$K$6:$K$3665,0)))) | J74: =IF(B74=B73,"",IF($K74="","",INDEX(Zeiterfassung!$J$6:$J$3665,MATCH(INDEX(Zeiterfassung!$K$6:$K$3665,$K74),Zeiterfassung!$K$6:$K$3665,0)))) | K74: =IFERROR(AGGREGATE(15,6,(ROW(Zeiterfassung!$D$6:$D$3665)-ROW(Zeiterfassung!$D$6)+1)/(Zeiterfassung!$D$6:$D$3665<>""),69),"")
A75: =IF($K75="","",WEEKNUM(INDEX(Zeiterfassung!$K$6:$K$3665,$K75),21)) | B75: =IF($K75="","",INDEX(Zeiterfassung!$K$6:$K$3665,$K75)) | C75: =IF($K75="","",INDEX(Zeiterfassung!$K$6:$K$3665,$K75)) | D75: =IF($K75="","",INDEX(Zeiterfassung!$D$6:$D$3665,$K75)) | E75: =IF($K75="","",INDEX(Zeiterfassung!$E$6:$E$3665,$K75)) | F75: =IF($K75="","",INDEX(Zeiterfassung!$F$6:$F$3665,$K75)) | G75: =IF($K75="","",INDEX(Zeiterfassung!$G$6:$G$3665,$K75)) | H75: =IF($K75="","",INDEX(Zeiterfassung!$H$6:$H$3665,$K75)) | I75: =IF(B75=B74,"",IF($K75="","",INDEX(Zeiterfassung!$I$6:$I$3665,MATCH(INDEX(Zeiterfassung!$K$6:$K$3665,$K75),Zeiterfassung!$K$6:$K$3665,0)))) | J75: =IF(B75=B74,"",IF($K75="","",INDEX(Zeiterfassung!$J$6:$J$3665,MATCH(INDEX(Zeiterfassung!$K$6:$K$3665,$K75),Zeiterfassung!$K$6:$K$3665,0)))) | K75: =IFERROR(AGGREGATE(15,6,(ROW(Zeiterfassung!$D$6:$D$3665)-ROW(Zeiterfassung!$D$6)+1)/(Zeiterfassung!$D$6:$D$3665<>""),70),"")
A76: =IF($K76="","",WEEKNUM(INDEX(Zeiterfassung!$K$6:$K$3665,$K76),21)) | B76: =IF($K76="","",INDEX(Zeiterfassung!$K$6:$K$3665,$K76)) | C76: =IF($K76="","",INDEX(Zeiterfassung!$K$6:$K$3665,$K76)) | D76: =IF($K76="","",INDEX(Zeiterfassung!$D$6:$D$3665,$K76)) | E76: =IF($K76="","",INDEX(Zeiterfassung!$E$6:$E$3665,$K76)) | F76: =IF($K76="","",INDEX(Zeiterfassung!$F$6:$F$3665,$K76)) | G76: =IF($K76="","",INDEX(Zeiterfassung!$G$6:$G$3665,$K76)) | H76: =IF($K76="","",INDEX(Zeiterfassung!$H$6:$H$3665,$K76)) | I76: =IF(B76=B75,"",IF($K76="","",INDEX(Zeiterfassung!$I$6:$I$3665,MATCH(INDEX(Zeiterfassung!$K$6:$K$3665,$K76),Zeiterfassung!$K$6:$K$3665,0)))) | J76: =IF(B76=B75,"",IF($K76="","",INDEX(Zeiterfassung!$J$6:$J$3665,MATCH(INDEX(Zeiterfassung!$K$6:$K$3665,$K76),Zeiterfassung!$K$6:$K$3665,0)))) | K76: =IFERROR(AGGREGATE(15,6,(ROW(Zeiterfassung!$D$6:$D$3665)-ROW(Zeiterfassung!$D$6)+1)/(Zeiterfassung!$D$6:$D$3665<>""),71),"")
A77: =IF($K77="","",WEEKNUM(INDEX(Zeiterfassung!$K$6:$K$3665,$K77),21)) | B77: =IF($K77="","",INDEX(Zeiterfassung!$K$6:$K$3665,$K77)) | C77: =IF($K77="","",INDEX(Zeiterfassung!$K$6:$K$3665,$K77)) | D77: =IF($K77="","",INDEX(Zeiterfassung!$D$6:$D$3665,$K77)) | E77: =IF($K77="","",INDEX(Zeiterfassung!$E$6:$E$3665,$K77)) | F77: =IF($K77="","",INDEX(Zeiterfassung!$F$6:$F$3665,$K77)) | G77: =IF($K77="","",INDEX(Zeiterfassung!$G$6:$G$3665,$K77)) | H77: =IF($K77="","",INDEX(Zeiterfassung!$H$6:$H$3665,$K77)) | I77: =IF(B77=B76,"",IF($K77="","",INDEX(Zeiterfassung!$I$6:$I$3665,MATCH(INDEX(Zeiterfassung!$K$6:$K$3665,$K77),Zeiterfassung!$K$6:$K$3665,0)))) | J77: =IF(B77=B76,"",IF($K77="","",INDEX(Zeiterfassung!$J$6:$J$3665,MATCH(INDEX(Zeiterfassung!$K$6:$K$3665,$K77),Zeiterfassung!$K$6:$K$3665,0)))) | K77: =IFERROR(AGGREGATE(15,6,(ROW(Zeiterfassung!$D$6:$D$3665)-ROW(Zeiterfassung!$D$6)+1)/(Zeiterfassung!$D$6:$D$3665<>""),72),"")
A78: =IF($K78="","",WEEKNUM(INDEX(Zeiterfassung!$K$6:$K$3665,$K78),21)) | B78: =IF($K78="","",INDEX(Zeiterfassung!$K$6:$K$3665,$K78)) | C78: =IF($K78="","",INDEX(Zeiterfassung!$K$6:$K$3665,$K78)) | D78: =IF($K78="","",INDEX(Zeiterfassung!$D$6:$D$3665,$K78)) | E78: =IF($K78="","",INDEX(Zeiterfassung!$E$6:$E$3665,$K78)) | F78: =IF($K78="","",INDEX(Zeiterfassung!$F$6:$F$3665,$K78)) | G78: =IF($K78="","",INDEX(Zeiterfassung!$G$6:$G$3665,$K78)) | H78: =IF($K78="","",INDEX(Zeiterfassung!$H$6:$H$3665,$K78)) | I78: =IF(B78=B77,"",IF($K78="","",INDEX(Zeiterfassung!$I$6:$I$3665,MATCH(INDEX(Zeiterfassung!$K$6:$K$3665,$K78),Zeiterfassung!$K$6:$K$3665,0)))) | J78: =IF(B78=B77,"",IF($K78="","",INDEX(Zeiterfassung!$J$6:$J$3665,MATCH(INDEX(Zeiterfassung!$K$6:$K$3665,$K78),Zeiterfassung!$K$6:$K$3665,0)))) | K78: =IFERROR(AGGREGATE(15,6,(ROW(Zeiterfassung!$D$6:$D$3665)-ROW(Zeiterfassung!$D$6)+1)/(Zeiterfassung!$D$6:$D$3665<>""),73),"")
A79: =IF($K79="","",WEEKNUM(INDEX(Zeiterfassung!$K$6:$K$3665,$K79),21)) | B79: =IF($K79="","",INDEX(Zeiterfassung!$K$6:$K$3665,$K79)) | C79: =IF($K79="","",INDEX(Zeiterfassung!$K$6:$K$3665,$K79)) | D79: =IF($K79="","",INDEX(Zeiterfassung!$D$6:$D$3665,$K79)) | E79: =IF($K79="","",INDEX(Zeiterfassung!$E$6:$E$3665,$K79)) | F79: =IF($K79="","",INDEX(Zeiterfassung!$F$6:$F$3665,$K79)) | G79: =IF($K79="","",INDEX(Zeiterfassung!$G$6:$G$3665,$K79)) | H79: =IF($K79="","",INDEX(Zeiterfassung!$H$6:$H$3665,$K79)) | I79: =IF(B79=B78,"",IF($K79="","",INDEX(Zeiterfassung!$I$6:$I$3665,MATCH(INDEX(Zeiterfassung!$K$6:$K$3665,$K79),Zeiterfassung!$K$6:$K$3665,0)))) | J79: =IF(B79=B78,"",IF($K79="","",INDEX(Zeiterfassung!$J$6:$J$3665,MATCH(INDEX(Zeiterfassung!$K$6:$K$3665,$K79),Zeiterfassung!$K$6:$K$3665,0)))) | K79: =IFERROR(AGGREGATE(15,6,(ROW(Zeiterfassung!$D$6:$D$3665)-ROW(Zeiterfassung!$D$6)+1)/(Zeiterfassung!$D$6:$D$3665<>""),74),"")
A80: =IF($K80="","",WEEKNUM(INDEX(Zeiterfassung!$K$6:$K$3665,$K80),21)) | B80: =IF($K80="","",INDEX(Zeiterfassung!$K$6:$K$3665,$K80)) | C80: =IF($K80="","",INDEX(Zeiterfassung!$K$6:$K$3665,$K80)) | D80: =IF($K80="","",INDEX(Zeiterfassung!$D$6:$D$3665,$K80)) | E80: =IF($K80="","",INDEX(Zeiterfassung!$E$6:$E$3665,$K80)) | F80: =IF($K80="","",INDEX(Zeiterfassung!$F$6:$F$3665,$K80)) | G80: =IF($K80="","",INDEX(Zeiterfassung!$G$6:$G$3665,$K80)) | H80: =IF($K80="","",INDEX(Zeiterfassung!$H$6:$H$3665,$K80)) | I80: =IF(B80=B79,"",IF($K80="","",INDEX(Zeiterfassung!$I$6:$I$3665,MATCH(INDEX(Zeiterfassung!$K$6:$K$3665,$K80),Zeiterfassung!$K$6:$K$3665,0)))) | J80: =IF(B80=B79,"",IF($K80="","",INDEX(Zeiterfassung!$J$6:$J$3665,MATCH(INDEX(Zeiterfassung!$K$6:$K$3665,$K80),Zeiterfassung!$K$6:$K$3665,0)))) | K80: =IFERROR(AGGREGATE(15,6,(ROW(Zeiterfassung!$D$6:$D$3665)-ROW(Zeiterfassung!$D$6)+1)/(Zeiterfassung!$D$6:$D$3665<>""),75),"")
A81: =IF($K81="","",WEEKNUM(INDEX(Zeiterfassung!$K$6:$K$3665,$K81),21)) | B81: =IF($K81="","",INDEX(Zeiterfassung!$K$6:$K$3665,$K81)) | C81: =IF($K81="","",INDEX(Zeiterfassung!$K$6:$K$3665,$K81)) | D81: =IF($K81="","",INDEX(Zeiterfassung!$D$6:$D$3665,$K81)) | E81: =IF($K81="","",INDEX(Zeiterfassung!$E$6:$E$3665,$K81)) | F81: =IF($K81="","",INDEX(Zeiterfassung!$F$6:$F$3665,$K81)) | G81: =IF($K81="","",INDEX(Zeiterfassung!$G$6:$G$3665,$K81)) | H81: =IF($K81="","",INDEX(Zeiterfassung!$H$6:$H$3665,$K81)) | I81: =IF(B81=B80,"",IF($K81="","",INDEX(Zeiterfassung!$I$6:$I$3665,MATCH(INDEX(Zeiterfassung!$K$6:$K$3665,$K81),Zeiterfassung!$K$6:$K$3665,0)))) | J81: =IF(B81=B80,"",IF($K81="","",INDEX(Zeiterfassung!$J$6:$J$3665,MATCH(INDEX(Zeiterfassung!$K$6:$K$3665,$K81),Zeiterfassung!$K$6:$K$3665,0)))) | K81: =IFERROR(AGGREGATE(15,6,(ROW(Zeiterfassung!$D$6:$D$3665)-ROW(Zeiterfassung!$D$6)+1)/(Zeiterfassung!$D$6:$D$3665<>""),76),"")
A82: =IF($K82="","",WEEKNUM(INDEX(Zeiterfassung!$K$6:$K$3665,$K82),21)) | B82: =IF($K82="","",INDEX(Zeiterfassung!$K$6:$K$3665,$K82)) | C82: =IF($K82="","",INDEX(Zeiterfassung!$K$6:$K$3665,$K82)) | D82: =IF($K82="","",INDEX(Zeiterfassung!$D$6:$D$3665,$K82)) | E82: =IF($K82="","",INDEX(Zeiterfassung!$E$6:$E$3665,$K82)) | F82: =IF($K82="","",INDEX(Zeiterfassung!$F$6:$F$3665,$K82)) | G82: =IF($K82="","",INDEX(Zeiterfassung!$G$6:$G$3665,$K82)) | H82: =IF($K82="","",INDEX(Zeiterfassung!$H$6:$H$3665,$K82)) | I82: =IF(B82=B81,"",IF($K82="","",INDEX(Zeiterfassung!$I$6:$I$3665,MATCH(INDEX(Zeiterfassung!$K$6:$K$3665,$K82),Zeiterfassung!$K$6:$K$3665,0)))) | J82: =IF(B82=B81,"",IF($K82="","",INDEX(Zeiterfassung!$J$6:$J$3665,MATCH(INDEX(Zeiterfassung!$K$6:$K$3665,$K82),Zeiterfassung!$K$6:$K$3665,0)))) | K82: =IFERROR(AGGREGATE(15,6,(ROW(Zeiterfassung!$D$6:$D$3665)-ROW(Zeiterfassung!$D$6)+1)/(Zeiterfassung!$D$6:$D$3665<>""),77),"")
A83: =IF($K83="","",WEEKNUM(INDEX(Zeiterfassung!$K$6:$K$3665,$K83),21)) | B83: =IF($K83="","",INDEX(Zeiterfassung!$K$6:$K$3665,$K83)) | C83: =IF($K83="","",INDEX(Zeiterfassung!$K$6:$K$3665,$K83)) | D83: =IF($K83="","",INDEX(Zeiterfassung!$D$6:$D$3665,$K83)) | E83: =IF($K83="","",INDEX(Zeiterfassung!$E$6:$E$3665,$K83)) | F83: =IF($K83="","",INDEX(Zeiterfassung!$F$6:$F$3665,$K83)) | G83: =IF($K83="","",INDEX(Zeiterfassung!$G$6:$G$3665,$K83)) | H83: =IF($K83="","",INDEX(Zeiterfassung!$H$6:$H$3665,$K83)) | I83: =IF(B83=B82,"",IF($K83="","",INDEX(Zeiterfassung!$I$6:$I$3665,MATCH(INDEX(Zeiterfassung!$K$6:$K$3665,$K83),Zeiterfassung!$K$6:$K$3665,0)))) | J83: =IF(B83=B82,"",IF($K83="","",INDEX(Zeiterfassung!$J$6:$J$3665,MATCH(INDEX(Zeiterfassung!$K$6:$K$3665,$K83),Zeiterfassung!$K$6:$K$3665,0)))) | K83: =IFERROR(AGGREGATE(15,6,(ROW(Zeiterfassung!$D$6:$D$3665)-ROW(Zeiterfassung!$D$6)+1)/(Zeiterfassung!$D$6:$D$3665<>""),78),"")
A84: =IF($K84="","",WEEKNUM(INDEX(Zeiterfassung!$K$6:$K$3665,$K84),21)) | B84: =IF($K84="","",INDEX(Zeiterfassung!$K$6:$K$3665,$K84)) | C84: =IF($K84="","",INDEX(Zeiterfassung!$K$6:$K$3665,$K84)) | D84: =IF($K84="","",INDEX(Zeiterfassung!$D$6:$D$3665,$K84)) | E84: =IF($K84="","",INDEX(Zeiterfassung!$E$6:$E$3665,$K84)) | F84: =IF($K84="","",INDEX(Zeiterfassung!$F$6:$F$3665,$K84)) | G84: =IF($K84="","",INDEX(Zeiterfassung!$G$6:$G$3665,$K84)) | H84: =IF($K84="","",INDEX(Zeiterfassung!$H$6:$H$3665,$K84)) | I84: =IF(B84=B83,"",IF($K84="","",INDEX(Zeiterfassung!$I$6:$I$3665,MATCH(INDEX(Zeiterfassung!$K$6:$K$3665,$K84),Zeiterfassung!$K$6:$K$3665,0)))) | J84: =IF(B84=B83,"",IF($K84="","",INDEX(Zeiterfassung!$J$6:$J$3665,MATCH(INDEX(Zeiterfassung!$K$6:$K$3665,$K84),Zeiterfassung!$K$6:$K$3665,0)))) | K84: =IFERROR(AGGREGATE(15,6,(ROW(Zeiterfassung!$D$6:$D$3665)-ROW(Zeiterfassung!$D$6)+1)/(Zeiterfassung!$D$6:$D$3665<>""),79),"")
A85: =IF($K85="","",WEEKNUM(INDEX(Zeiterfassung!$K$6:$K$3665,$K85),21)) | B85: =IF($K85="","",INDEX(Zeiterfassung!$K$6:$K$3665,$K85)) | C85: =IF($K85="","",INDEX(Zeiterfassung!$K$6:$K$3665,$K85)) | D85: =IF($K85="","",INDEX(Zeiterfassung!$D$6:$D$3665,$K85)) | E85: =IF($K85="","",INDEX(Zeiterfassung!$E$6:$E$3665,$K85)) | F85: =IF($K85="","",INDEX(Zeiterfassung!$F$6:$F$3665,$K85)) | G85: =IF($K85="","",INDEX(Zeiterfassung!$G$6:$G$3665,$K85)) | H85: =IF($K85="","",INDEX(Zeiterfassung!$H$6:$H$3665,$K85)) | I85: =IF(B85=B84,"",IF($K85="","",INDEX(Zeiterfassung!$I$6:$I$3665,MATCH(INDEX(Zeiterfassung!$K$6:$K$3665,$K85),Zeiterfassung!$K$6:$K$3665,0)))) | J85: =IF(B85=B84,"",IF($K85="","",INDEX(Zeiterfassung!$J$6:$J$3665,MATCH(INDEX(Zeiterfassung!$K$6:$K$3665,$K85),Zeiterfassung!$K$6:$K$3665,0)))) | K85: =IFERROR(AGGREGATE(15,6,(ROW(Zeiterfassung!$D$6:$D$3665)-ROW(Zeiterfassung!$D$6)+1)/(Zeiterfassung!$D$6:$D$3665<>""),80),"")
A86: =IF($K86="","",WEEKNUM(INDEX(Zeiterfassung!$K$6:$K$3665,$K86),21)) | B86: =IF($K86="","",INDEX(Zeiterfassung!$K$6:$K$3665,$K86)) | C86: =IF($K86="","",INDEX(Zeiterfassung!$K$6:$K$3665,$K86)) | D86: =IF($K86="","",INDEX(Zeiterfassung!$D$6:$D$3665,$K86)) | E86: =IF($K86="","",INDEX(Zeiterfassung!$E$6:$E$3665,$K86)) | F86: =IF($K86="","",INDEX(Zeiterfassung!$F$6:$F$3665,$K86)) | G86: =IF($K86="","",INDEX(Zeiterfassung!$G$6:$G$3665,$K86)) | H86: =IF($K86="","",INDEX(Zeiterfassung!$H$6:$H$3665,$K86)) | I86: =IF(B86=B85,"",IF($K86="","",INDEX(Zeiterfassung!$I$6:$I$3665,MATCH(INDEX(Zeiterfassung!$K$6:$K$3665,$K86),Zeiterfassung!$K$6:$K$3665,0)))) | J86: =IF(B86=B85,"",IF($K86="","",INDEX(Zeiterfassung!$J$6:$J$3665,MATCH(INDEX(Zeiterfassung!$K$6:$K$3665,$K86),Zeiterfassung!$K$6:$K$3665,0)))) | K86: =IFERROR(AGGREGATE(15,6,(ROW(Zeiterfassung!$D$6:$D$3665)-ROW(Zeiterfassung!$D$6)+1)/(Zeiterfassung!$D$6:$D$3665<>""),81),"")
A87: =IF($K87="","",WEEKNUM(INDEX(Zeiterfassung!$K$6:$K$3665,$K87),21)) | B87: =IF($K87="","",INDEX(Zeiterfassung!$K$6:$K$3665,$K87)) | C87: =IF($K87="","",INDEX(Zeiterfassung!$K$6:$K$3665,$K87)) | D87: =IF($K87="","",INDEX(Zeiterfassung!$D$6:$D$3665,$K87)) | E87: =IF($K87="","",INDEX(Zeiterfassung!$E$6:$E$3665,$K87)) | F87: =IF($K87="","",INDEX(Zeiterfassung!$F$6:$F$3665,$K87)) | G87: =IF($K87="","",INDEX(Zeiterfassung!$G$6:$G$3665,$K87)) | H87: =IF($K87="","",INDEX(Zeiterfassung!$H$6:$H$3665,$K87)) | I87: =IF(B87=B86,"",IF($K87="","",INDEX(Zeiterfassung!$I$6:$I$3665,MATCH(INDEX(Zeiterfassung!$K$6:$K$3665,$K87),Zeiterfassung!$K$6:$K$3665,0)))) | J87: =IF(B87=B86,"",IF($K87="","",INDEX(Zeiterfassung!$J$6:$J$3665,MATCH(INDEX(Zeiterfassung!$K$6:$K$3665,$K87),Zeiterfassung!$K$6:$K$3665,0)))) | K87: =IFERROR(AGGREGATE(15,6,(ROW(Zeiterfassung!$D$6:$D$3665)-ROW(Zeiterfassung!$D$6)+1)/(Zeiterfassung!$D$6:$D$3665<>""),82),"")
A88: =IF($K88="","",WEEKNUM(INDEX(Zeiterfassung!$K$6:$K$3665,$K88),21)) | B88: =IF($K88="","",INDEX(Zeiterfassung!$K$6:$K$3665,$K88)) | C88: =IF($K88="","",INDEX(Zeiterfassung!$K$6:$K$3665,$K88)) | D88: =IF($K88="","",INDEX(Zeiterfassung!$D$6:$D$3665,$K88)) | E88: =IF($K88="","",INDEX(Zeiterfassung!$E$6:$E$3665,$K88)) | F88: =IF($K88="","",INDEX(Zeiterfassung!$F$6:$F$3665,$K88)) | G88: =IF($K88="","",INDEX(Zeiterfassung!$G$6:$G$3665,$K88)) | H88: =IF($K88="","",INDEX(Zeiterfassung!$H$6:$H$3665,$K88)) | I88: =IF(B88=B87,"",IF($K88="","",INDEX(Zeiterfassung!$I$6:$I$3665,MATCH(INDEX(Zeiterfassung!$K$6:$K$3665,$K88),Zeiterfassung!$K$6:$K$3665,0)))) | J88: =IF(B88=B87,"",IF($K88="","",INDEX(Zeiterfassung!$J$6:$J$3665,MATCH(INDEX(Zeiterfassung!$K$6:$K$3665,$K88),Zeiterfassung!$K$6:$K$3665,0)))) | K88: =IFERROR(AGGREGATE(15,6,(ROW(Zeiterfassung!$D$6:$D$3665)-ROW(Zeiterfassung!$D$6)+1)/(Zeiterfassung!$D$6:$D$3665<>""),83),"")
A89: =IF($K89="","",WEEKNUM(INDEX(Zeiterfassung!$K$6:$K$3665,$K89),21)) | B89: =IF($K89="","",INDEX(Zeiterfassung!$K$6:$K$3665,$K89)) | C89: =IF($K89="","",INDEX(Zeiterfassung!$K$6:$K$3665,$K89)) | D89: =IF($K89="","",INDEX(Zeiterfassung!$D$6:$D$3665,$K89)) | E89: =IF($K89="","",INDEX(Zeiterfassung!$E$6:$E$3665,$K89)) | F89: =IF($K89="","",INDEX(Zeiterfassung!$F$6:$F$3665,$K89)) | G89: =IF($K89="","",INDEX(Zeiterfassung!$G$6:$G$3665,$K89)) | H89: =IF($K89="","",INDEX(Zeiterfassung!$H$6:$H$3665,$K89)) | I89: =IF(B89=B88,"",IF($K89="","",INDEX(Zeiterfassung!$I$6:$I$3665,MATCH(INDEX(Zeiterfassung!$K$6:$K$3665,$K89),Zeiterfassung!$K$6:$K$3665,0)))) | J89: =IF(B89=B88,"",IF($K89="","",INDEX(Zeiterfassung!$J$6:$J$3665,MATCH(INDEX(Zeiterfassung!$K$6:$K$3665,$K89),Zeiterfassung!$K$6:$K$3665,0)))) | K89: =IFERROR(AGGREGATE(15,6,(ROW(Zeiterfassung!$D$6:$D$3665)-ROW(Zeiterfassung!$D$6)+1)/(Zeiterfassung!$D$6:$D$3665<>""),84),"")
A90: =IF($K90="","",WEEKNUM(INDEX(Zeiterfassung!$K$6:$K$3665,$K90),21)) | B90: =IF($K90="","",INDEX(Zeiterfassung!$K$6:$K$3665,$K90)) | C90: =IF($K90="","",INDEX(Zeiterfassung!$K$6:$K$3665,$K90)) | D90: =IF($K90="","",INDEX(Zeiterfassung!$D$6:$D$3665,$K90)) | E90: =IF($K90="","",INDEX(Zeiterfassung!$E$6:$E$3665,$K90)) | F90: =IF($K90="","",INDEX(Zeiterfassung!$F$6:$F$3665,$K90)) | G90: =IF($K90="","",INDEX(Zeiterfassung!$G$6:$G$3665,$K90)) | H90: =IF($K90="","",INDEX(Zeiterfassung!$H$6:$H$3665,$K90)) | I90: =IF(B90=B89,"",IF($K90="","",INDEX(Zeiterfassung!$I$6:$I$3665,MATCH(INDEX(Zeiterfassung!$K$6:$K$3665,$K90),Zeiterfassung!$K$6:$K$3665,0)))) | J90: =IF(B90=B89,"",IF($K90="","",INDEX(Zeiterfassung!$J$6:$J$3665,MATCH(INDEX(Zeiterfassung!$K$6:$K$3665,$K90),Zeiterfassung!$K$6:$K$3665,0)))) | K90: =IFERROR(AGGREGATE(15,6,(ROW(Zeiterfassung!$D$6:$D$3665)-ROW(Zeiterfassung!$D$6)+1)/(Zeiterfassung!$D$6:$D$3665<>""),85),"")
A91: =IF($K91="","",WEEKNUM(INDEX(Zeiterfassung!$K$6:$K$3665,$K91),21)) | B91: =IF($K91="","",INDEX(Zeiterfassung!$K$6:$K$3665,$K91)) | C91: =IF($K91="","",INDEX(Zeiterfassung!$K$6:$K$3665,$K91)) | D91: =IF($K91="","",INDEX(Zeiterfassung!$D$6:$D$3665,$K91)) | E91: =IF($K91="","",INDEX(Zeiterfassung!$E$6:$E$3665,$K91)) | F91: =IF($K91="","",INDEX(Zeiterfassung!$F$6:$F$3665,$K91)) | G91: =IF($K91="","",INDEX(Zeiterfassung!$G$6:$G$3665,$K91)) | H91: =IF($K91="","",INDEX(Zeiterfassung!$H$6:$H$3665,$K91)) | I91: =IF(B91=B90,"",IF($K91="","",INDEX(Zeiterfassung!$I$6:$I$3665,MATCH(INDEX(Zeiterfassung!$K$6:$K$3665,$K91),Zeiterfassung!$K$6:$K$3665,0)))) | J91: =IF(B91=B90,"",IF($K91="","",INDEX(Zeiterfassung!$J$6:$J$3665,MATCH(INDEX(Zeiterfassung!$K$6:$K$3665,$K91),Zeiterfassung!$K$6:$K$3665,0)))) | K91: =IFERROR(AGGREGATE(15,6,(ROW(Zeiterfassung!$D$6:$D$3665)-ROW(Zeiterfassung!$D$6)+1)/(Zeiterfassung!$D$6:$D$3665<>""),86),"")
A92: =IF($K92="","",WEEKNUM(INDEX(Zeiterfassung!$K$6:$K$3665,$K92),21)) | B92: =IF($K92="","",INDEX(Zeiterfassung!$K$6:$K$3665,$K92)) | C92: =IF($K92="","",INDEX(Zeiterfassung!$K$6:$K$3665,$K92)) | D92: =IF($K92="","",INDEX(Zeiterfassung!$D$6:$D$3665,$K92)) | E92: =IF($K92="","",INDEX(Zeiterfassung!$E$6:$E$3665,$K92)) | F92: =IF($K92="","",INDEX(Zeiterfassung!$F$6:$F$3665,$K92)) | G92: =IF($K92="","",INDEX(Zeiterfassung!$G$6:$G$3665,$K92)) | H92: =IF($K92="","",INDEX(Zeiterfassung!$H$6:$H$3665,$K92)) | I92: =IF(B92=B91,"",IF($K92="","",INDEX(Zeiterfassung!$I$6:$I$3665,MATCH(INDEX(Zeiterfassung!$K$6:$K$3665,$K92),Zeiterfassung!$K$6:$K$3665,0)))) | J92: =IF(B92=B91,"",IF($K92="","",INDEX(Zeiterfassung!$J$6:$J$3665,MATCH(INDEX(Zeiterfassung!$K$6:$K$3665,$K92),Zeiterfassung!$K$6:$K$3665,0)))) | K92: =IFERROR(AGGREGATE(15,6,(ROW(Zeiterfassung!$D$6:$D$3665)-ROW(Zeiterfassung!$D$6)+1)/(Zeiterfassung!$D$6:$D$3665<>""),87),"")
A93: =IF($K93="","",WEEKNUM(INDEX(Zeiterfassung!$K$6:$K$3665,$K93),21)) | B93: =IF($K93="","",INDEX(Zeiterfassung!$K$6:$K$3665,$K93)) | C93: =IF($K93="","",INDEX(Zeiterfassung!$K$6:$K$3665,$K93)) | D93: =IF($K93="","",INDEX(Zeiterfassung!$D$6:$D$3665,$K93)) | E93: =IF($K93="","",INDEX(Zeiterfassung!$E$6:$E$3665,$K93)) | F93: =IF($K93="","",INDEX(Zeiterfassung!$F$6:$F$3665,$K93)) | G93: =IF($K93="","",INDEX(Zeiterfassung!$G$6:$G$3665,$K93)) | H93: =IF($K93="","",INDEX(Zeiterfassung!$H$6:$H$3665,$K93)) | I93: =IF(B93=B92,"",IF($K93="","",INDEX(Zeiterfassung!$I$6:$I$3665,MATCH(INDEX(Zeiterfassung!$K$6:$K$3665,$K93),Zeiterfassung!$K$6:$K$3665,0)))) | J93: =IF(B93=B92,"",IF($K93="","",INDEX(Zeiterfassung!$J$6:$J$3665,MATCH(INDEX(Zeiterfassung!$K$6:$K$3665,$K93),Zeiterfassung!$K$6:$K$3665,0)))) | K93: =IFERROR(AGGREGATE(15,6,(ROW(Zeiterfassung!$D$6:$D$3665)-ROW(Zeiterfassung!$D$6)+1)/(Zeiterfassung!$D$6:$D$3665<>""),88),"")
A94: =IF($K94="","",WEEKNUM(INDEX(Zeiterfassung!$K$6:$K$3665,$K94),21)) | B94: =IF($K94="","",INDEX(Zeiterfassung!$K$6:$K$3665,$K94)) | C94: =IF($K94="","",INDEX(Zeiterfassung!$K$6:$K$3665,$K94)) | D94: =IF($K94="","",INDEX(Zeiterfassung!$D$6:$D$3665,$K94)) | E94: =IF($K94="","",INDEX(Zeiterfassung!$E$6:$E$3665,$K94)) | F94: =IF($K94="","",INDEX(Zeiterfassung!$F$6:$F$3665,$K94)) | G94: =IF($K94="","",INDEX(Zeiterfassung!$G$6:$G$3665,$K94)) | H94: =IF($K94="","",INDEX(Zeiterfassung!$H$6:$H$3665,$K94)) | I94: =IF(B94=B93,"",IF($K94="","",INDEX(Zeiterfassung!$I$6:$I$3665,MATCH(INDEX(Zeiterfassung!$K$6:$K$3665,$K94),Zeiterfassung!$K$6:$K$3665,0)))) | J94: =IF(B94=B93,"",IF($K94="","",INDEX(Zeiterfassung!$J$6:$J$3665,MATCH(INDEX(Zeiterfassung!$K$6:$K$3665,$K94),Zeiterfassung!$K$6:$K$3665,0)))) | K94: =IFERROR(AGGREGATE(15,6,(ROW(Zeiterfassung!$D$6:$D$3665)-ROW(Zeiterfassung!$D$6)+1)/(Zeiterfassung!$D$6:$D$3665<>""),89),"")
A95: =IF($K95="","",WEEKNUM(INDEX(Zeiterfassung!$K$6:$K$3665,$K95),21)) | B95: =IF($K95="","",INDEX(Zeiterfassung!$K$6:$K$3665,$K95)) | C95: =IF($K95="","",INDEX(Zeiterfassung!$K$6:$K$3665,$K95)) | D95: =IF($K95="","",INDEX(Zeiterfassung!$D$6:$D$3665,$K95)) | E95: =IF($K95="","",INDEX(Zeiterfassung!$E$6:$E$3665,$K95)) | F95: =IF($K95="","",INDEX(Zeiterfassung!$F$6:$F$3665,$K95)) | G95: =IF($K95="","",INDEX(Zeiterfassung!$G$6:$G$3665,$K95)) | H95: =IF($K95="","",INDEX(Zeiterfassung!$H$6:$H$3665,$K95)) | I95: =IF(B95=B94,"",IF($K95="","",INDEX(Zeiterfassung!$I$6:$I$3665,MATCH(INDEX(Zeiterfassung!$K$6:$K$3665,$K95),Zeiterfassung!$K$6:$K$3665,0)))) | J95: =IF(B95=B94,"",IF($K95="","",INDEX(Zeiterfassung!$J$6:$J$3665,MATCH(INDEX(Zeiterfassung!$K$6:$K$3665,$K95),Zeiterfassung!$K$6:$K$3665,0)))) | K95: =IFERROR(AGGREGATE(15,6,(ROW(Zeiterfassung!$D$6:$D$3665)-ROW(Zeiterfassung!$D$6)+1)/(Zeiterfassung!$D$6:$D$3665<>""),90),"")
A96: =IF($K96="","",WEEKNUM(INDEX(Zeiterfassung!$K$6:$K$3665,$K96),21)) | B96: =IF($K96="","",INDEX(Zeiterfassung!$K$6:$K$3665,$K96)) | C96: =IF($K96="","",INDEX(Zeiterfassung!$K$6:$K$3665,$K96)) | D96: =IF($K96="","",INDEX(Zeiterfassung!$D$6:$D$3665,$K96)) | E96: =IF($K96="","",INDEX(Zeiterfassung!$E$6:$E$3665,$K96)) | F96: =IF($K96="","",INDEX(Zeiterfassung!$F$6:$F$3665,$K96)) | G96: =IF($K96="","",INDEX(Zeiterfassung!$G$6:$G$3665,$K96)) | H96: =IF($K96="","",INDEX(Zeiterfassung!$H$6:$H$3665,$K96)) | I96: =IF(B96=B95,"",IF($K96="","",INDEX(Zeiterfassung!$I$6:$I$3665,MATCH(INDEX(Zeiterfassung!$K$6:$K$3665,$K96),Zeiterfassung!$K$6:$K$3665,0)))) | J96: =IF(B96=B95,"",IF($K96="","",INDEX(Zeiterfassung!$J$6:$J$3665,MATCH(INDEX(Zeiterfassung!$K$6:$K$3665,$K96),Zeiterfassung!$K$6:$K$3665,0)))) | K96: =IFERROR(AGGREGATE(15,6,(ROW(Zeiterfassung!$D$6:$D$3665)-ROW(Zeiterfassung!$D$6)+1)/(Zeiterfassung!$D$6:$D$3665<>""),91),"")
A97: =IF($K97="","",WEEKNUM(INDEX(Zeiterfassung!$K$6:$K$3665,$K97),21)) | B97: =IF($K97="","",INDEX(Zeiterfassung!$K$6:$K$3665,$K97)) | C97: =IF($K97="","",INDEX(Zeiterfassung!$K$6:$K$3665,$K97)) | D97: =IF($K97="","",INDEX(Zeiterfassung!$D$6:$D$3665,$K97)) | E97: =IF($K97="","",INDEX(Zeiterfassung!$E$6:$E$3665,$K97)) | F97: =IF($K97="","",INDEX(Zeiterfassung!$F$6:$F$3665,$K97)) | G97: =IF($K97="","",INDEX(Zeiterfassung!$G$6:$G$3665,$K97)) | H97: =IF($K97="","",INDEX(Zeiterfassung!$H$6:$H$3665,$K97)) | I97: =IF(B97=B96,"",IF($K97="","",INDEX(Zeiterfassung!$I$6:$I$3665,MATCH(INDEX(Zeiterfassung!$K$6:$K$3665,$K97),Zeiterfassung!$K$6:$K$3665,0)))) | J97: =IF(B97=B96,"",IF($K97="","",INDEX(Zeiterfassung!$J$6:$J$3665,MATCH(INDEX(Zeiterfassung!$K$6:$K$3665,$K97),Zeiterfassung!$K$6:$K$3665,0)))) | K97: =IFERROR(AGGREGATE(15,6,(ROW(Zeiterfassung!$D$6:$D$3665)-ROW(Zeiterfassung!$D$6)+1)/(Zeiterfassung!$D$6:$D$3665<>""),92),"")
A98: =IF($K98="","",WEEKNUM(INDEX(Zeiterfassung!$K$6:$K$3665,$K98),21)) | B98: =IF($K98="","",INDEX(Zeiterfassung!$K$6:$K$3665,$K98)) | C98: =IF($K98="","",INDEX(Zeiterfassung!$K$6:$K$3665,$K98)) | D98: =IF($K98="","",INDEX(Zeiterfassung!$D$6:$D$3665,$K98)) | E98: =IF($K98="","",INDEX(Zeiterfassung!$E$6:$E$3665,$K98)) | F98: =IF($K98="","",INDEX(Zeiterfassung!$F$6:$F$3665,$K98)) | G98: =IF($K98="","",INDEX(Zeiterfassung!$G$6:$G$3665,$K98)) | H98: =IF($K98="","",INDEX(Zeiterfassung!$H$6:$H$3665,$K98)) | I98: =IF(B98=B97,"",IF($K98="","",INDEX(Zeiterfassung!$I$6:$I$3665,MATCH(INDEX(Zeiterfassung!$K$6:$K$3665,$K98),Zeiterfassung!$K$6:$K$3665,0)))) | J98: =IF(B98=B97,"",IF($K98="","",INDEX(Zeiterfassung!$J$6:$J$3665,MATCH(INDEX(Zeiterfassung!$K$6:$K$3665,$K98),Zeiterfassung!$K$6:$K$3665,0)))) | K98: =IFERROR(AGGREGATE(15,6,(ROW(Zeiterfassung!$D$6:$D$3665)-ROW(Zeiterfassung!$D$6)+1)/(Zeiterfassung!$D$6:$D$3665<>""),93),"")
A99: =IF($K99="","",WEEKNUM(INDEX(Zeiterfassung!$K$6:$K$3665,$K99),21)) | B99: =IF($K99="","",INDEX(Zeiterfassung!$K$6:$K$3665,$K99)) | C99: =IF($K99="","",INDEX(Zeiterfassung!$K$6:$K$3665,$K99)) | D99: =IF($K99="","",INDEX(Zeiterfassung!$D$6:$D$3665,$K99)) | E99: =IF($K99="","",INDEX(Zeiterfassung!$E$6:$E$3665,$K99)) | F99: =IF($K99="","",INDEX(Zeiterfassung!$F$6:$F$3665,$K99)) | G99: =IF($K99="","",INDEX(Zeiterfassung!$G$6:$G$3665,$K99)) | H99: =IF($K99="","",INDEX(Zeiterfassung!$H$6:$H$3665,$K99)) | I99: =IF(B99=B98,"",IF($K99="","",INDEX(Zeiterfassung!$I$6:$I$3665,MATCH(INDEX(Zeiterfassung!$K$6:$K$3665,$K99),Zeiterfassung!$K$6:$K$3665,0)))) | J99: =IF(B99=B98,"",IF($K99="","",INDEX(Zeiterfassung!$J$6:$J$3665,MATCH(INDEX(Zeiterfassung!$K$6:$K$3665,$K99),Zeiterfassung!$K$6:$K$3665,0)))) | K99: =IFERROR(AGGREGATE(15,6,(ROW(Zeiterfassung!$D$6:$D$3665)-ROW(Zeiterfassung!$D$6)+1)/(Zeiterfassung!$D$6:$D$3665<>""),94),"")
A100: =IF($K100="","",WEEKNUM(INDEX(Zeiterfassung!$K$6:$K$3665,$K100),21)) | B100: =IF($K100="","",INDEX(Zeiterfassung!$K$6:$K$3665,$K100)) | C100: =IF($K100="","",INDEX(Zeiterfassung!$K$6:$K$3665,$K100)) | D100: =IF($K100="","",INDEX(Zeiterfassung!$D$6:$D$3665,$K100)) | E100: =IF($K100="","",INDEX(Zeiterfassung!$E$6:$E$3665,$K100)) | F100: =IF($K100="","",INDEX(Zeiterfassung!$F$6:$F$3665,$K100)) | G100: =IF($K100="","",INDEX(Zeiterfassung!$G$6:$G$3665,$K100)) | H100: =IF($K100="","",INDEX(Zeiterfassung!$H$6:$H$3665,$K100)) | I100: =IF(B100=B99,"",IF($K100="","",INDEX(Zeiterfassung!$I$6:$I$3665,MATCH(INDEX(Zeiterfassung!$K$6:$K$3665,$K100),Zeiterfassung!$K$6:$K$3665,0)))) | J100: =IF(B100=B99,"",IF($K100="","",INDEX(Zeiterfassung!$J$6:$J$3665,MATCH(INDEX(Zeiterfassung!$K$6:$K$3665,$K100),Zeiterfassung!$K$6:$K$3665,0)))) | K100: =IFERROR(AGGREGATE(15,6,(ROW(Zeiterfassung!$D$6:$D$3665)-ROW(Zeiterfassung!$D$6)+1)/(Zeiterfassung!$D$6:$D$3665<>""),95),"")
A101: =IF($K101="","",WEEKNUM(INDEX(Zeiterfassung!$K$6:$K$3665,$K101),21)) | B101: =IF($K101="","",INDEX(Zeiterfassung!$K$6:$K$3665,$K101)) | C101: =IF($K101="","",INDEX(Zeiterfassung!$K$6:$K$3665,$K101)) | D101: =IF($K101="","",INDEX(Zeiterfassung!$D$6:$D$3665,$K101)) | E101: =IF($K101="","",INDEX(Zeiterfassung!$E$6:$E$3665,$K101)) | F101: =IF($K101="","",INDEX(Zeiterfassung!$F$6:$F$3665,$K101)) | G101: =IF($K101="","",INDEX(Zeiterfassung!$G$6:$G$3665,$K101)) | H101: =IF($K101="","",INDEX(Zeiterfassung!$H$6:$H$3665,$K101)) | I101: =IF(B101=B100,"",IF($K101="","",INDEX(Zeiterfassung!$I$6:$I$3665,MATCH(INDEX(Zeiterfassung!$K$6:$K$3665,$K101),Zeiterfassung!$K$6:$K$3665,0)))) | J101: =IF(B101=B100,"",IF($K101="","",INDEX(Zeiterfassung!$J$6:$J$3665,MATCH(INDEX(Zeiterfassung!$K$6:$K$3665,$K101),Zeiterfassung!$K$6:$K$3665,0)))) | K101: =IFERROR(AGGREGATE(15,6,(ROW(Zeiterfassung!$D$6:$D$3665)-ROW(Zeiterfassung!$D$6)+1)/(Zeiterfassung!$D$6:$D$3665<>""),96),"")
...

Sheet Materialkosten
A1: MATERIALKOSTEN | H1: ← ZUM COCKPIT
A3: Fortlaufende Erfassung der projektbezogenen Material- und Sachkosten · Nachunternehmer separat erfassen
A5: Datum | B5: Lieferant | C5: Rechnung / Beleg-Nr. | D5: Beschreibung | E5: Nettobetrag | F5: Bemerkung

Sheet Rechnungsstand
A1: RECHNUNGSSTAND | O1: ← ZUM COCKPIT
K2: PROJEKTFORTSCHRITT
A3: Fortlaufende Erfassung von Abschlags-, Teilschluss- und Schlussrechnungen | K3: Auftragssumme netto | M3: ='Projektübersicht'!$B$28
K4: In Rechnung gestellt netto | M4: =SUM($F$6:$F$305)
A5: Rechnungsdatum | B5: Rechnungsnummer | C5: Rechnungsart | D5: Leistungszeitraum | E5: Leistungsstand / Bezeichnung | F5: Rechnungsbetrag netto (diese Rechnung) | G5: Zahlungseingang | H5: Offener Betrag | I5: Bemerkung | K5: Unfertige Leistungen netto
H6: =IF(F6="","",F6-IF(G6="",0,G6)) | K6: Leistungsstand gesamt | M6: =SUM(M4:M5)
H7: =IF(F7="","",F7-IF(G7="",0,G7)) | K7: Restleistung | M7: =MAX(0,M3-M6)
H8: =IF(F8="","",F8-IF(G8="",0,G8)) | K8: Projektfortschritt | M8: =IF(M3>0,M6/M3,"")
H9: =IF(F9="","",F9-IF(G9="",0,G9)) | K9: Hinweis: Unfertige Leistungen werden manuell zum jeweiligen Stichtag bewertet.
H10: =IF(F10="","",F10-IF(G10="",0,G10))
H11: =IF(F11="","",F11-IF(G11="",0,G11)) | K11: RECHNUNGSPRÜFUNG
H12: =IF(F12="","",F12-IF(G12="",0,G12)) | K12: → PRÜFBLATT ÖFFNEN
H13: =IF(F13="","",F13-IF(G13="",0,G13))
H14: =IF(F14="","",F14-IF(G14="",0,G14))
H15: =IF(F15="","",F15-IF(G15="",0,G15))
H16: =IF(F16="","",F16-IF(G16="",0,G16))
H17: =IF(F17="","",F17-IF(G17="",0,G17))
H18: =IF(F18="","",F18-IF(G18="",0,G18))
H19: =IF(F19="","",F19-IF(G19="",0,G19))
H20: =IF(F20="","",F20-IF(G20="",0,G20))
H21: =IF(F21="","",F21-IF(G21="",0,G21))
H22: =IF(F22="","",F22-IF(G22="",0,G22))
H23: =IF(F23="","",F23-IF(G23="",0,G23))
H24: =IF(F24="","",F24-IF(G24="",0,G24))
... H305: =IF(F305="","",F305-IF(G305="",0,G305))

Sheet Rechnungsprüfung
A1: RECHNUNGSPRÜFUNG · VOB/B-ORIENTIERTE ABSTIMMUNG
A3: Fortlaufender Soll-/Ist-Abgleich zwischen eigener Rechnungsstellung und den Prüfblättern des Auftraggebers | U3: ← ZUM COCKPIT
A5: VERTRAGLICHE PRÜFPARAMETER | G5: KUMULIERTER ABRECHNUNGSSTAND
A6: Auftragssumme netto | B6: ='Projektübersicht'!$B$28 | G6: AN Rechnungen netto | J6: =SUM($D$12:$D$311) | L6: Vertragliche Einbehalte Soll | O6: =SUM($J$12:$J$311) | Q6: Erwartet zahlbar | T6: =SUM($K$12:$K$311)
A7: Baustrom | B7: 0 | D7: Vertragserfüllung · Einbehalt je Abschlag | E7: 0.1 | G7: AG anerkannt netto | J7: =SUM($N$12:$N$311) | L7: AG Einbehalte / Kürzungen | O7: =SUM($S$12:$S$311) | Q7: AG geprüft zahlbar | T7: =SUM($T$12:$T$311)
A8: Versicherung | B8: 0 | D8: Vertragserfüllung · Sicherungsziel | E8: 0 | G8: Differenz Leistungsstand | J8: =J6-J7 | L8: Differenz Einbehalte | O8: =O7-O6 | Q8: Differenz zahlbar | T8: =T7-T6
A9: Infrastruktur | B9: 0 | D9: Mängelanspruchssicherheit (optional) | E9: 0 | L9: Blau = Werte aus dem Prüfblatt des Auftraggebers manuell übernehmen
A10: EIGENE RECHNUNG / ERWARTETE PRÜFUNG | L10: PRÜFBLATT AUFTRAGGEBER · MANUELLE ÜBERNAHME | U10: ABWEICHUNG / KLÄRUNG
A11: Rechnungsdatum | B11: Rechnungsnummer | C11: Rechnungsart | D11: AN Rechnung netto | E11: Kumuliert AN netto | F11: Baustrom Soll | G11: Versicherung Soll | H11: Infrastruktur Soll | I11: VE-Sicherheit Soll | J11: Einbehalte Soll gesamt | K11: Erwartet zahlbar | L11: AG Prüfblatt-Nr. | M11: AG Prüfdatum | N11: AG anerkannt netto | O11: AG Baustrom | P11: AG Versicherung | Q11: AG Infrastruktur | R11: AG VE-Sicherheit | S11: AG Einbehalte gesamt | T11: AG geprüft zahlbar | U11: Diff. Leistung | V11: Diff. zahlbar | W11: Bemerkung / Klärung
A12: =IF(Rechnungsstand!B6="","",Rechnungsstand!A6) | B12: =IF(Rechnungsstand!B6="","",Rechnungsstand!B6) | C12: =IF(Rechnungsstand!B6="","",Rechnungsstand!C6) | D12: =IF(Rechnungsstand!B6="","",Rechnungsstand!F6) | E12: =IF(D12="","",SUM($D$12:D12)) | F12: =IF(D12="","",D12*$B$7) | G12: =IF(D12="","",D12*$B$8) | H12: =IF(D12="","",D12*$B$9) | I12: =IF(D12="","",IF(C12="Abschlagsrechnung",MAX(0,MIN(D12*$E$7,IF($E$8>0,$B$6*$E$8-0,D12*$E$7))),0)) | J12: =IF(D12="","",SUM(F12:I12)) | K12: =IF(D12="","",D12-J12) | S12: =IF(COUNTA(O12:R12)=0,"",SUM(O12:R12)) | T12: =IF(N12="","",N12-IF(S12="",0,S12)) | U12: =IF(OR(D12="",N12=""),"",N12-D12) | V12: =IF(OR(K12="",T12=""),"",T12-K12)
A13: =IF(Rechnungsstand!B7="","",Rechnungsstand!A7) | B13: =IF(Rechnungsstand!B7="","",Rechnungsstand!B7) | C13: =IF(Rechnungsstand!B7="","",Rechnungsstand!C7) | D13: =IF(Rechnungsstand!B7="","",Rechnungsstand!F7) | E13: =IF(D13="","",SUM($D$12:D13)) | F13: =IF(D13="","",D13*$B$7) | G13: =IF(D13="","",D13*$B$8) | H13: =IF(D13="","",D13*$B$9) | I13: =IF(D13="","",IF(C13="Abschlagsrechnung",MAX(0,MIN(D13*$E$7,IF($E$8>0,$B$6*$E$8-SUM($I$12:I12),D13*$E$7))),0)) | J13: =IF(D13="","",SUM(F13:I13)) | K13: =IF(D13="","",D13-J13) | S13: =IF(COUNTA(O13:R13)=0,"",SUM(O13:R13)) | T13: =IF(N13="","",N13-IF(S13="",0,S13)) | U13: =IF(OR(D13="",N13=""),"",N13-D13) | V13: =IF(OR(K13="",T13=""),"",T13-K13)
A14: =IF(Rechnungsstand!B8="","",Rechnungsstand!A8) | B14: =IF(Rechnungsstand!B8="","",Rechnungsstand!B8) | C14: =IF(Rechnungsstand!B8="","",Rechnungsstand!C8) | D14: =IF(Rechnungsstand!B8="","",Rechnungsstand!F8) | E14: =IF(D14="","",SUM($D$12:D14)) | F14: =IF(D14="","",D14*$B$7) | G14: =IF(D14="","",D14*$B$8) | H14: =IF(D14="","",D14*$B$9) | I14: =IF(D14="","",IF(C14="Abschlagsrechnung",MAX(0,MIN(D14*$E$7,IF($E$8>0,$B$6*$E$8-SUM($I$12:I13),D14*$E$7))),0)) | J14: =IF(D14="","",SUM(F14:I14)) | K14: =IF(D14="","",D14-J14) | S14: =IF(COUNTA(O14:R14)=0,"",SUM(O14:R14)) | T14: =IF(N14="","",N14-IF(S14="",0,S14)) | U14: =IF(OR(D14="",N14=""),"",N14-D14) | V14: =IF(OR(K14="",T14=""),"",T14-K14)
A15: =IF(Rechnungsstand!B9="","",Rechnungsstand!A9) | B15: =IF(Rechnungsstand!B9="","",Rechnungsstand!B9) | C15: =IF(Rechnungsstand!B9="","",Rechnungsstand!C9) | D15: =IF(Rechnungsstand!B9="","",Rechnungsstand!F9) | E15: =IF(D15="","",SUM($D$12:D15)) | F15: =IF(D15="","",D15*$B$7) | G15: =IF(D15="","",D15*$B$8) | H15: =IF(D15="","",D15*$B$9) | I15: =IF(D15="","",IF(C15="Abschlagsrechnung",MAX(0,MIN(D15*$E$7,IF($E$8>0,$B$6*$E$8-SUM($I$12:I14),D15*$E$7))),0)) | J15: =IF(D15="","",SUM(F15:I15)) | K15: =IF(D15="","",D15-J15) | S15: =IF(COUNTA(O15:R15)=0,"",SUM(O15:R15)) | T15: =IF(N15="","",N15-IF(S15="",0,S15)) | U15: =IF(OR(D15="",N15=""),"",N15-D15) | V15: =IF(OR(K15="",T15=""),"",T15-K15)
A16: =IF(Rechnungsstand!B10="","",Rechnungsstand!A10) | B16: =IF(Rechnungsstand!B10="","",Rechnungsstand!B10) | C16: =IF(Rechnungsstand!B10="","",Rechnungsstand!C10) | D16: =IF(Rechnungsstand!B10="","",Rechnungsstand!F10) | E16: =IF(D16="","",SUM($D$12:D16)) | F16: =IF(D16="","",D16*$B$7) | G16: =IF(D16="","",D16*$B$8) | H16: =IF(D16="","",D16*$B$9) | I16: =IF(D16="","",IF(C16="Abschlagsrechnung",MAX(0,MIN(D16*$E$7,IF($E$8>0,$B$6*$E$8-SUM($I$12:I15),D16*$E$7))),0)) | J16: =IF(D16="","",SUM(F16:I16)) | K16: =IF(D16="","",D16-J16) | S16: =IF(COUNTA(O16:R16)=0,"",SUM(O16:R16)) | T16: =IF(N16="","",N16-IF(S16="",0,S16)) | U16: =IF(OR(D16="",N16=""),"",N16-D16) | V16: =IF(OR(K16="",T16=""),"",T16-K16)
A17: =IF(Rechnungsstand!B11="","",Rechnungsstand!A11) | B17: =IF(Rechnungsstand!B11="","",Rechnungsstand!B11) | C17: =IF(Rechnungsstand!B11="","",Rechnungsstand!C11) | D17: =IF(Rechnungsstand!B11="","",Rechnungsstand!F11) | E17: =IF(D17="","",SUM($D$12:D17)) | F17: =IF(D17="","",D17*$B$7) | G17: =IF(D17="","",D17*$B$8) | H17: =IF(D17="","",D17*$B$9) | I17: =IF(D17="","",IF(C17="Abschlagsrechnung",MAX(0,MIN(D17*$E$7,IF($E$8>0,$B$6*$E$8-SUM($I$12:I16),D17*$E$7))),0)) | J17: =IF(D17="","",SUM(F17:I17)) | K17: =IF(D17="","",D17-J17) | S17: =IF(COUNTA(O17:R17)=0,"",SUM(O17:R17)) | T17: =IF(N17="","",N17-IF(S17="",0,S17)) | U17: =IF(OR(D17="",N17=""),"",N17-D17) | V17: =IF(OR(K17="",T17=""),"",T17-K17)
A18: =IF(Rechnungsstand!B12="","",Rechnungsstand!A12) | B18: =IF(Rechnungsstand!B12="","",Rechnungsstand!B12) | C18: =IF(Rechnungsstand!B12="","",Rechnungsstand!C12) | D18: =IF(Rechnungsstand!B12="","",Rechnungsstand!F12) | E18: =IF(D18="","",SUM($D$12:D18)) | F18: =IF(D18="","",D18*$B$7) | G18: =IF(D18="","",D18*$B$8) | H18: =IF(D18="","",D18*$B$9) | I18: =IF(D18="","",IF(C18="Abschlagsrechnung",MAX(0,MIN(D18*$E$7,IF($E$8>0,$B$6*$E$8-SUM($I$12:I17),D18*$E$7))),0)) | J18: =IF(D18="","",SUM(F18:I18)) | K18: =IF(D18="","",D18-J18) | S18: =IF(COUNTA(O18:R18)=0,"",SUM(O18:R18)) | T18: =IF(N18="","",N18-IF(S18="",0,S18)) | U18: =IF(OR(D18="",N18=""),"",N18-D18) | V18: =IF(OR(K18="",T18=""),"",T18-K18)
A19: =IF(Rechnungsstand!B13="","",Rechnungsstand!A13) | B19: =IF(Rechnungsstand!B13="","",Rechnungsstand!B13) | C19: =IF(Rechnungsstand!B13="","",Rechnungsstand!C13) | D19: =IF(Rechnungsstand!B13="","",Rechnungsstand!F13) | E19: =IF(D19="","",SUM($D$12:D19)) | F19: =IF(D19="","",D19*$B$7) | G19: =IF(D19="","",D19*$B$8) | H19: =IF(D19="","",D19*$B$9) | I19: =IF(D19="","",IF(C19="Abschlagsrechnung",MAX(0,MIN(D19*$E$7,IF($E$8>0,$B$6*$E$8-SUM($I$12:I18),D19*$E$7))),0)) | J19: =IF(D19="","",SUM(F19:I19)) | K19: =IF(D19="","",D19-J19) | S19: =IF(COUNTA(O19:R19)=0,"",SUM(O19:R19)) | T19: =IF(N19="","",N19-IF(S19="",0,S19)) | U19: =IF(OR(D19="",N19=""),"",N19-D19) | V19: =IF(OR(K19="",T19=""),"",T19-K19)
A20: =IF(Rechnungsstand!B14="","",Rechnungsstand!A14) | B20: =IF(Rechnungsstand!B14="","",Rechnungsstand!B14) | C20: =IF(Rechnungsstand!B14="","",Rechnungsstand!C14) | D20: =IF(Rechnungsstand!B14="","",Rechnungsstand!F14) | E20: =IF(D20="","",SUM($D$12:D20)) | F20: =IF(D20="","",D20*$B$7) | G20: =IF(D20="","",D20*$B$8) | H20: =IF(D20="","",D20*$B$9) | I20: =IF(D20="","",IF(C20="Abschlagsrechnung",MAX(0,MIN(D20*$E$7,IF($E$8>0,$B$6*$E$8-SUM($I$12:I19),D20*$E$7))),0)) | J20: =IF(D20="","",SUM(F20:I20)) | K20: =IF(D20="","",D20-J20) | S20: =IF(COUNTA(O20:R20)=0,"",SUM(O20:R20)) | T20: =IF(N20="","",N20-IF(S20="",0,S20)) | U20: =IF(OR(D20="",N20=""),"",N20-D20) | V20: =IF(OR(K20="",T20=""),"",T20-K20)
A21: =IF(Rechnungsstand!B15="","",Rechnungsstand!A15) | B21: =IF(Rechnungsstand!B15="","",Rechnungsstand!B15) | C21: =IF(Rechnungsstand!B15="","",Rechnungsstand!C15) | D21: =IF(Rechnungsstand!B15="","",Rechnungsstand!F15) | E21: =IF(D21="","",SUM($D$12:D21)) | F21: =IF(D21="","",D21*$B$7) | G21: =IF(D21="","",D21*$B$8) | H21: =IF(D21="","",D21*$B$9) | I21: =IF(D21="","",IF(C21="Abschlagsrechnung",MAX(0,MIN(D21*$E$7,IF($E$8>0,$B$6*$E$8-SUM($I$12:I20),D21*$E$7))),0)) | J21: =IF(D21="","",SUM(F21:I21)) | K21: =IF(D21="","",D21-J21) | S21: =IF(COUNTA(O21:R21)=0,"",SUM(O21:R21)) | T21: =IF(N21="","",N21-IF(S21="",0,S21)) | U21: =IF(OR(D21="",N21=""),"",N21-D21) | V21: =IF(OR(K21="",T21=""),"",T21-K21)
A22: =IF(Rechnungsstand!B16="","",Rechnungsstand!A16) | B22: =IF(Rechnungsstand!B16="","",Rechnungsstand!B16) | C22: =IF(Rechnungsstand!B16="","",Rechnungsstand!C16) | D22: =IF(Rechnungsstand!B16="","",Rechnungsstand!F16) | E22: =IF(D22="","",SUM($D$12:D22)) | F22: =IF(D22="","",D22*$B$7) | G22: =IF(D22="","",D22*$B$8) | H22: =IF(D22="","",D22*$B$9) | I22: =IF(D22="","",IF(C22="Abschlagsrechnung",MAX(0,MIN(D22*$E$7,IF($E$8>0,$B$6*$E$8-SUM($I$12:I21),D22*$E$7))),0)) | J22: =IF(D22="","",SUM(F22:I22)) | K22: =IF(D22="","",D22-J22) | S22: =IF(COUNTA(O22:R22)=0,"",SUM(O22:R22)) | T22: =IF(N22="","",N22-IF(S22="",0,S22)) | U22: =IF(OR(D22="",N22=""),"",N22-D22) | V22: =IF(OR(K22="",T22=""),"",T22-K22)
A23: =IF(Rechnungsstand!B17="","",Rechnungsstand!A17) | B23: =IF(Rechnungsstand!B17="","",Rechnungsstand!B17) | C23: =IF(Rechnungsstand!B17="","",Rechnungsstand!C17) | D23: =IF(Rechnungsstand!B17="","",Rechnungsstand!F17) | E23: =IF(D23="","",SUM($D$12:D23)) | F23: =IF(D23="","",D23*$B$7) | G23: =IF(D23="","",D23*$B$8) | H23: =IF(D23="","",D23*$B$9) | I23: =IF(D23="","",IF(C23="Abschlagsrechnung",MAX(0,MIN(D23*$E$7,IF($E$8>0,$B$6*$E$8-SUM($I$12:I22),D23*$E$7))),0)) | J23: =IF(D23="","",SUM(F23:I23)) | K23: =IF(D23="","",D23-J23) | S23: =IF(COUNTA(O23:R23)=0,"",SUM(O23:R23)) | T23: =IF(N23="","",N23-IF(S23="",0,S23)) | U23: =IF(OR(D23="",N23=""),"",N23-D23) | V23: =IF(OR(K23="",T23=""),"",T23-K23)
A24: =IF(Rechnungsstand!B18="","",Rechnungsstand!A18) | B24: =IF(Rechnungsstand!B18="","",Rechnungsstand!B18) | C24: =IF(Rechnungsstand!B18="","",Rechnungsstand!C18) | D24: =IF(Rechnungsstand!B18="","",Rechnungsstand!F18) | E24: =IF(D24="","",SUM($D$12:D24)) | F24: =IF(D24="","",D24*$B$7) | G24: =IF(D24="","",D24*$B$8) | H24: =IF(D24="","",D24*$B$9) | I24: =IF(D24="","",IF(C24="Abschlagsrechnung",MAX(0,MIN(D24*$E$7,IF($E$8>0,$B$6*$E$8-SUM($I$12:I23),D24*$E$7))),0)) | J24: =IF(D24="","",SUM(F24:I24)) | K24: =IF(D24="","",D24-J24) | S24: =IF(COUNTA(O24:R24)=0,"",SUM(O24:R24)) | T24: =IF(N24="","",N24-IF(S24="",0,S24)) | U24: =IF(OR(D24="",N24=""),"",N24-D24) | V24: =IF(OR(K24="",T24=""),"",T24-K24)
... A311: =IF(Rechnungsstand!B305="","",Rechnungsstand!A305) | B311: =IF(Rechnungsstand!B305="","",Rechnungsstand!B305) | C311: =IF(Rechnungsstand!B305="","",Rechnungsstand!C305) | D311: =IF(Rechnungsstand!B305="","",Rechnungsstand!F305) | E311: =IF(D311="","",SUM($D$12:D311)) | F311: =IF(D311="","",D311*$B$7) | G311: =IF(D311="","",D311*$B$8) | H311: =IF(D311="","",D311*$B$9) | I311: =IF(D311="","",IF(C311="Abschlagsrechnung",MAX(0,MIN(D311*$E$7,IF($E$8>0,$B$6*$E$8-SUM($I$12:I310),D311*$E$7))),0)) | J311: =IF(D311="","",SUM(F311:I311)) | K311: =IF(D311="","",D311-J311) | S311: =IF(COUNTA(O311:R311)=0,"",SUM(O311:R311)) | T311: =IF(N311="","",N311-IF(S311="",0,S311)) | U311: =IF(OR(D311="",N311=""),"",N311-D311) | V311: =IF(OR(K311="",T311=""),"",T311-K311)
A314: Hinweis zur VOB/B-Logik
A315: Abschlagszahlungen werden nach § 16 VOB/B auf Grundlage nachgewiesener vertragsgemäßer Leistungen geprüft. Sicherheitsabzüge setzen eine vertragliche Vereinbarung voraus. § 17 Abs. 6 VOB/B begrenzt den Einbehalt je Zahlung auf höchstens 10 %, bis die vereinbarte Sicherheitssumme erreicht ist. Baustrom, Versicherung und Infrastruktur sind keine pauschalen VOB/B-Sätze und müssen aus dem jeweiligen Vertrag/Prüfblatt übernommen werden. Bei Teil-/Schlussrechnungen ist die Behandlung bestehender Sicherheiten nach Vertrag und Abnahmestand zu prüfen. Quellen: https://dejure.org/gesetze/VOB-B/16.html ; https://dejure.org/gesetze/VOB-B/17.html ; https://www.vob-online.de/de/vob-2016-202072

Sheet Nachunternehmer
A1: NACHUNTERNEHMER · EINKAUF UND WEITERVERRECHNUNG | K1: ← ZUM COCKPIT
A2: Eine Zeile je zugeordneter Leistung: NU-Einkauf, Kundenrechnung und Kundenposition unmittelbar miteinander verknüpfen.
A3: NU-KOSTEN NETTO | C3: KUNDENWERT NETTO | E3: GEWINN / DECKUNGSBEITRAG | H3: MARGE NACHUNTERNEHMER
A4: =IF(COUNT($D$7:$D$106)=0,"",SUM($D$7:$D$106)) | C4: =IF(COUNT($G$7:$G$106)=0,"",SUM($G$7:$G$106)) | E4: =IF(COUNT($D$7:$D$106,$G$7:$G$106)=0,"",N(C4)-N(A4)) | H4: =IF(COUNT(C4)=0,"",IF(C4=0,"",E4/C4))
A6: GEWERK | B6: NACHUNTERNEHMER | C6: NU-RECHNUNG / BELEG | D6: EINKAUF NU NETTO | E6: KUNDENRECHNUNG | F6: RECHNUNGSPOSITION(EN) | G6: KUNDENWERT NETTO | H6: GEWINN / DB | I6: MARGE | J6: KURZBESCHREIBUNG / ZUORDNUNG
H7: =IF(COUNT(D7,G7)<2,"",G7-D7) | I7: =IF(COUNT(G7)=0,"",IF(G7=0,"",H7/G7))
H8: =IF(COUNT(D8,G8)<2,"",G8-D8) | I8: =IF(COUNT(G8)=0,"",IF(G8=0,"",H8/G8))
H9: =IF(COUNT(D9,G9)<2,"",G9-D9) | I9: =IF(COUNT(G9)=0,"",IF(G9=0,"",H9/G9))
H10: =IF(COUNT(D10,G10)<2,"",G10-D10) | I10: =IF(COUNT(G10)=0,"",IF(G10=0,"",H10/G10))
H11: =IF(COUNT(D11,G11)<2,"",G11-D11) | I11: =IF(COUNT(G11)=0,"",IF(G11=0,"",H11/G11))
H12: =IF(COUNT(D12,G12)<2,"",G12-D12) | I12: =IF(COUNT(G12)=0,"",IF(G12=0,"",H12/G12))
H13: =IF(COUNT(D13,G13)<2,"",G13-D13) | I13: =IF(COUNT(G13)=0,"",IF(G13=0,"",H13/G13))
H14: =IF(COUNT(D14,G14)<2,"",G14-D14) | I14: =IF(COUNT(G14)=0,"",IF(G14=0,"",H14/G14))
H15: =IF(COUNT(D15,G15)<2,"",G15-D15) | I15: =IF(COUNT(G15)=0,"",IF(G15=0,"",H15/G15))
H16: =IF(COUNT(D16,G16)<2,"",G16-D16) | I16: =IF(COUNT(G16)=0,"",IF(G16=0,"",H16/G16))
H17: =IF(COUNT(D17,G17)<2,"",G17-D17) | I17: =IF(COUNT(G17)=0,"",IF(G17=0,"",H17/G17))
H18: =IF(COUNT(D18,G18)<2,"",G18-D18) | I18: =IF(COUNT(G18)=0,"",IF(G18=0,"",H18/G18))
... H106: =IF(COUNT(D106,G106)<2,"",G106-D106) | I106: =IF(COUNT(G106)=0,"",IF(G106=0,"",H106/G106))

Sheet Eigenleistung
A1: EIGENLEISTUNGS-KALKULATION | L1: ← ZUM COCKPIT
A2: Je Gewerk eine Zeile verwenden. Kundenwert und interner Kostensatz werden manuell erfasst; Ist-Stunden kommen automatisch aus der Zeiterfassung.
A3: Leistungswert netto | B3: =IF(COUNTA($A$6:$E$105)=0,"",SUM($D$6:$D$105)) | C3: Stunden Ist | D3: =IF(COUNTA($A$6:$E$105)=0,"",SUM($F$6:$F$105)) | E3: Eigenkosten | F3: =IF(B3="","",SUM($G$6:$G$105)) | G3: Eigenleistungsmarge | H3: =IF(COUNT(B3,F3)<2,"",IF(B3=0,"",(B3-F3)/B3)) | I3: Je Gewerk nur 1 Zeile
A5: Gewerk | B5: Rechnungsposition(en) | C5: Leistung / Beschreibung | D5: Kundenpreis netto | E5: Interner Kostensatz €/Std. | F5: Stunden Ist | G5: Eigenkosten Ist | H5: Deckungsbeitrag | I5: Eigenleistungsmarge | J5: Bemerkung
F6: =IF(A6="","",SUMIF(Zeiterfassung!$E$6:$E$3665,A6,Zeiterfassung!$H$6:$H$3665)) | G6: =IF(OR(E6="",F6=""),"",E6*F6) | H6: =IF(D6="","",D6-IF(G6="",0,G6)) | I6: =IF(D6>0,H6/D6,"")
F7: =IF(A7="","",SUMIF(Zeiterfassung!$E$6:$E$3665,A7,Zeiterfassung!$H$6:$H$3665)) | G7: =IF(OR(E7="",F7=""),"",E7*F7) | H7: =IF(D7="","",D7-IF(G7="",0,G7)) | I7: =IF(D7>0,H7/D7,"")
F8: =IF(A8="","",SUMIF(Zeiterfassung!$E$6:$E$3665,A8,Zeiterfassung!$H$6:$H$3665)) | G8: =IF(OR(E8="",F8=""),"",E8*F8) | H8: =IF(D8="","",D8-IF(G8="",0,G8)) | I8: =IF(D8>0,H8/D8,"")
F9: =IF(A9="","",SUMIF(Zeiterfassung!$E$6:$E$3665,A9,Zeiterfassung!$H$6:$H$3665)) | G9: =IF(OR(E9="",F9=""),"",E9*F9) | H9: =IF(D9="","",D9-IF(G9="",0,G9)) | I9: =IF(D9>0,H9/D9,"")
F10: =IF(A10="","",SUMIF(Zeiterfassung!$E$6:$E$3665,A10,Zeiterfassung!$H$6:$H$3665)) | G10: =IF(OR(E10="",F10=""),"",E10*F10) | H10: =IF(D10="","",D10-IF(G10="",0,G10)) | I10: =IF(D10>0,H10/D10,"")
F11: =IF(A11="","",SUMIF(Zeiterfassung!$E$6:$E$3665,A11,Zeiterfassung!$H$6:$H$3665)) | G11: =IF(OR(E11="",F11=""),"",E11*F11) | H11: =IF(D11="","",D11-IF(G11="",0,G11)) | I11: =IF(D11>0,H11/D11,"")
F12: =IF(A12="","",SUMIF(Zeiterfassung!$E$6:$E$3665,A12,Zeiterfassung!$H$6:$H$3665)) | G12: =IF(OR(E12="",F12=""),"",E12*F12) | H12: =IF(D12="","",D12-IF(G12="",0,G12)) | I12: =IF(D12>0,H12/D12,"")
F13: =IF(A13="","",SUMIF(Zeiterfassung!$E$6:$E$3665,A13,Zeiterfassung!$H$6:$H$3665)) | G13: =IF(OR(E13="",F13=""),"",E13*F13) | H13: =IF(D13="","",D13-IF(G13="",0,G13)) | I13: =IF(D13>0,H13/D13,"")
F14: =IF(A14="","",SUMIF(Zeiterfassung!$E$6:$E$3665,A14,Zeiterfassung!$H$6:$H$3665)) | G14: =IF(OR(E14="",F14=""),"",E14*F14) | H14: =IF(D14="","",D14-IF(G14="",0,G14)) | I14: =IF(D14>0,H14/D14,"")
F15: =IF(A15="","",SUMIF(Zeiterfassung!$E$6:$E$3665,A15,Zeiterfassung!$H$6:$H$3665)) | G15: =IF(OR(E15="",F15=""),"",E15*F15) | H15: =IF(D15="","",D15-IF(G15="",0,G15)) | I15: =IF(D15>0,H15/D15,"")
F16: =IF(A16="","",SUMIF(Zeiterfassung!$E$6:$E$3665,A16,Zeiterfassung!$H$6:$H$3665)) | G16: =IF(OR(E16="",F16=""),"",E16*F16) | H16: =IF(D16="","",D16-IF(G16="",0,G16)) | I16: =IF(D16>0,H16/D16,"")
F17: =IF(A17="","",SUMIF(Zeiterfassung!$E$6:$E$3665,A17,Zeiterfassung!$H$6:$H$3665)) | G17: =IF(OR(E17="",F17=""),"",E17*F17) | H17: =IF(D17="","",D17-IF(G17="",0,G17)) | I17: =IF(D17>0,H17/D17,"")
... F105: =IF(A105="","",SUMIF(Zeiterfassung!$E$6:$E$3665,A105,Zeiterfassung!$H$6:$H$3665)) | G105: =IF(OR(E105="",F105=""),"",E105*F105) | H105: =IF(D105="","",D105-IF(G105="",0,G105)) | I105: =IF(D105>0,H105/D105,"")

Sheet KPI-Basis
B2: KPI-BERECHNUNGSBASIS | G2: ← ZUM COCKPIT
B3: Eingaben in Blau. Verknüpfte bzw. berechnete Werte werden automatisch aktualisiert.
B5: NACHUNTERNEHMER
B6: Auftragssumme netto | C6: ='Projektübersicht'!$B$28 | E6: Gesamter Netto-Auftragswert des Projekts.
B7: Leistungswert Nachunternehmer netto | C7: ='Nachunternehmer'!$C$4 | E7: Automatische Übernahme des Netto-Kundenwerts der den NU-Leistungen zugeordneten Kundenpositionen.
B8: Nachunternehmerkosten Ist | C8: ='Nachunternehmer'!$A$4 | E8: Automatische Übernahme der Netto-Einkaufssumme der erfassten Nachunternehmerrechnungen.
B9: Marge Nachunternehmer | C9: ='Nachunternehmer'!$H$4 | E9: Gewichtete NU-Marge: (Kundenwert − NU-Kosten) ÷ Kundenwert.
B10: EIGENE PRODUKTIVITÄT
B11: Leistungswert eigene Produktion netto | C11: ='Eigenleistung'!$B$3 | E11: Automatische Übernahme des Kundenwerts der Eigenleistungen.
B12: Eigene produktive Stunden Ist | C12: ='Eigenleistung'!$D$3 | E12: Summe der Ist-Stunden aus der Eigenleistungs-Kalkulation / Zeiterfassung.
B13: Ø Produktivkostensatz eigene MA €/Std. | C13: =IF(COUNT(C12,C14)<2,"",IF(C12=0,"",C14/C12)) | E13: Gewichteter durchschnittlicher interner Produktivkostensatz.
B14: Eigene Produktivkosten Ist | C14: ='Eigenleistung'!$F$3 | E14: Ist-Stunden × interner Kostensatz je Gewerk.
B15: Eigenleistungsmarge | C15: ='Eigenleistung'!$H$3 | E15: Gewichtete Marge aller mit eigenen Mitarbeitern erbrachten Leistungen.
B16: GESAMTPROJEKT
B17: Materialkosten Ist | C17: =SUM(Materialkosten!$E$6:$E$305) | E17: Automatische Übernahme aus Materialkosten. Nachunternehmerkosten hier nicht nochmals erfassen.
B18: Sonstige projektbezogene Kosten Ist | C18: 0 | E18: Weitere direkte Projektkosten, die weder Material, Nachunternehmer noch produktive Eigenleistung sind.
B19: Gesamtprojektkosten Ist | C19: =IF(SUM(N(C8),N(C14),N(C17),N(C18))=0,"",SUM(N(C8),N(C14),N(C17),N(C18))) | E19: Summe der direkt zurechenbaren Projektkosten.
B20: Projektmarge | C20: =IF(OR(COUNT(C6)=0,COUNT(C19)=0,C6=0),"",(C6-C19)/C6) | E20: Marge des Gesamtprojekts nach Abzug aller erfassten direkten Projektkosten.
B22: STUNDENCONTROLLING
B23: Stunden Soll | C23: ='Projektübersicht'!$B$22
B24: Stunden Ist | C24: ='Projektübersicht'!$F$22
B25: Restbudget Stunden | C25: ='Projektübersicht'!$J$22

Sheet Listen
A1: Gewerke | B1: Mitarbeiter | C1: Status | E1: Feiertage Berlin | F1: Bezeichnung | G1: Quelle | I1: ← ZUM COCKPIT | N1: NU-Gewerke | P1: Lieferanten | X1: Rechnungsarten | Z1: VOB/B Quellen Rechnungsprüfung | AA1: KW-Navigation | AB1: Datumsnavigation ohne Sonntage | AC1: KW-Navigation
A2: Bauleitung | B2: Ahrens | C2: Offen | E2: 45658 | F2: Neujahr | G2: https://gesetze.berlin.de/perma?j=FeiertG_BE | N2: Rüster | P2: Ohlwein | X2: Abschlagsrechnung | Z2: https://dejure.org/gesetze/VOB-B/16.html | AA2: 1 | AB2: =IF(OR('Projektübersicht'!$F$11="",'Projektübersicht'!$F$13="",'Projektübersicht'!$F$11>'Projektübersicht'!$F$13),"",IF(WORKDAY.INTL('Projektübersicht'!$F$11-1,1,"0000001")<='Projektübersicht'!$F$13,WORKDAY.INTL('Projektübersicht'!$F$11-1,1,"0000001"),"")) | AC2: 1
A3: Rückbau | B3: Berkhoff | C3: In Arbeit | E3: 45724 | F3: Internationaler Frauentag | G3: https://gesetze.berlin.de/perma?j=FeiertG_BE | N3: Elektriker | P3: Prosol | X3: Teilschlussrechnung | Z3: https://dejure.org/gesetze/VOB-B/17.html | AA3: 2 | AB3: =IF(OR('Projektübersicht'!$F$11="",'Projektübersicht'!$F$13="",'Projektübersicht'!$F$11>'Projektübersicht'!$F$13),"",IF(WORKDAY.INTL('Projektübersicht'!$F$11-1,2,"0000001")<='Projektübersicht'!$F$13,WORKDAY.INTL('Projektübersicht'!$F$11-1,2,"0000001"),"")) | AC3: 2
A4: Maurer | B4: Böttger | C4: Erledigt | E4: 45765 | F4: Karfreitag | G4: https://gesetze.berlin.de/perma?j=FeiertG_BE | N4: Reinigung | P4: Raab | X4: Schlussrechnung | Z4: https://www.vob-online.de/de/vob-2016-202072 | AA4: 3 | AB4: =IF(OR('Projektübersicht'!$F$11="",'Projektübersicht'!$F$13="",'Projektübersicht'!$F$11>'Projektübersicht'!$F$13),"",IF(WORKDAY.INTL('Projektübersicht'!$F$11-1,3,"0000001")<='Projektübersicht'!$F$13,WORKDAY.INTL('Projektübersicht'!$F$11-1,3,"0000001"),"")) | AC4: 3
A5: Trockenbau | B5: Cordes | C5: Wartet | E5: 45768 | F5: Ostermontag | G5: https://gesetze.berlin.de/perma?j=FeiertG_BE | N5: Tischler | P5: Fliesenparadies | Z5: =IF(OR('Projektübersicht'!$F$11="",'Projektübersicht'!$F$13="",'Projektübersicht'!$F$11>'Projektübersicht'!$F$13),"",IF('Projektübersicht'!$F$11+3<='Projektübersicht'!$F$13,'Projektübersicht'!$F$11+3,"")) | AA5: 4 | AB5: =IF(OR('Projektübersicht'!$F$11="",'Projektübersicht'!$F$13="",'Projektübersicht'!$F$11>'Projektübersicht'!$F$13),"",IF(WORKDAY.INTL('Projektübersicht'!$F$11-1,4,"0000001")<='Projektübersicht'!$F$13,WORKDAY.INTL('Projektübersicht'!$F$11-1,4,"0000001"),"")) | AC5: 4
A6: Elektro | B6: S.Dallmann | C6: Abgerechnet | E6: 45778 | F6: Tag der Arbeit | G6: https://gesetze.berlin.de/perma?j=FeiertG_BE | N6: Betonbauer | P6: Wego | Z6: =IF(OR('Projektübersicht'!$F$11="",'Projektübersicht'!$F$13="",'Projektübersicht'!$F$11>'Projektübersicht'!$F$13),"",IF('Projektübersicht'!$F$11+4<='Projektübersicht'!$F$13,'Projektübersicht'!$F$11+4,"")) | AA6: 5 | AB6: =IF(OR('Projektübersicht'!$F$11="",'Projektübersicht'!$F$13="",'Projektübersicht'!$F$11>'Projektübersicht'!$F$13),"",IF(WORKDAY.INTL('Projektübersicht'!$F$11-1,5,"0000001")<='Projektübersicht'!$F$13,WORKDAY.INTL('Projektübersicht'!$F$11-1,5,"0000001"),"")) | AC6: 5
A7: Sanitär/Heizung | B7: D. Dallmann | E7: 45806 | F7: Christi Himmelfahrt | G7: https://gesetze.berlin.de/perma?j=FeiertG_BE | N7: Galabauer | P7: MB Moog | Z7: =IF(OR('Projektübersicht'!$F$11="",'Projektübersicht'!$F$13="",'Projektübersicht'!$F$11>'Projektübersicht'!$F$13),"",IF('Projektübersicht'!$F$11+5<='Projektübersicht'!$F$13,'Projektübersicht'!$F$11+5,"")) | AA7: 6 | AB7: =IF(OR('Projektübersicht'!$F$11="",'Projektübersicht'!$F$13="",'Projektübersicht'!$F$11>'Projektübersicht'!$F$13),"",IF(WORKDAY.INTL('Projektübersicht'!$F$11-1,6,"0000001")<='Projektübersicht'!$F$13,WORKDAY.INTL('Projektübersicht'!$F$11-1,6,"0000001"),"")) | AC7: 6
A8: Fliesen | B8: Emmrich | E8: 45817 | F8: Pfingstmontag | G8: https://gesetze.berlin.de/perma?j=FeiertG_BE | N8: Sanitär | P8: reuter | Z8: =IF(OR('Projektübersicht'!$F$11="",'Projektübersicht'!$F$13="",'Projektübersicht'!$F$11>'Projektübersicht'!$F$13),"",IF('Projektübersicht'!$F$11+6<='Projektübersicht'!$F$13,'Projektübersicht'!$F$11+6,"")) | AA8: 7 | AB8: =IF(OR('Projektübersicht'!$F$11="",'Projektübersicht'!$F$13="",'Projektübersicht'!$F$11>'Projektübersicht'!$F$13),"",IF(WORKDAY.INTL('Projektübersicht'!$F$11-1,7,"0000001")<='Projektübersicht'!$F$13,WORKDAY.INTL('Projektübersicht'!$F$11-1,7,"0000001"),"")) | AC8: 7
A9: Maler | B9: Fahnert | E9: 45933 | F9: Tag der Deutschen Einheit | G9: https://gesetze.berlin.de/perma?j=FeiertG_BE | P9: Wiedemann | Z9: =IF(OR('Projektübersicht'!$F$11="",'Projektübersicht'!$F$13="",'Projektübersicht'!$F$11>'Projektübersicht'!$F$13),"",IF('Projektübersicht'!$F$11+7<='Projektübersicht'!$F$13,'Projektübersicht'!$F$11+7,"")) | AA9: 8 | AB9: =IF(OR('Projektübersicht'!$F$11="",'Projektübersicht'!$F$13="",'Projektübersicht'!$F$11>'Projektübersicht'!$F$13),"",IF(WORKDAY.INTL('Projektübersicht'!$F$11-1,8,"0000001")<='Projektübersicht'!$F$13,WORKDAY.INTL('Projektübersicht'!$F$11-1,8,"0000001"),"")) | AC9: 8
A10: Bodenleger | B10: Gollnick | E10: 46016 | F10: 1. Weihnachtsfeiertag | G10: https://gesetze.berlin.de/perma?j=FeiertG_BE | P10: Bauking | Z10: =IF(OR('Projektübersicht'!$F$11="",'Projektübersicht'!$F$13="",'Projektübersicht'!$F$11>'Projektübersicht'!$F$13),"",IF('Projektübersicht'!$F$11+8<='Projektübersicht'!$F$13,'Projektübersicht'!$F$11+8,"")) | AA10: 9 | AB10: =IF(OR('Projektübersicht'!$F$11="",'Projektübersicht'!$F$13="",'Projektübersicht'!$F$11>'Projektübersicht'!$F$13),"",IF(WORKDAY.INTL('Projektübersicht'!$F$11-1,9,"0000001")<='Projektübersicht'!$F$13,WORKDAY.INTL('Projektübersicht'!$F$11-1,9,"0000001"),"")) | AC10: 9
A11: Tischler | B11: Grewe | E11: 46017 | F11: 2. Weihnachtsfeiertag | G11: https://gesetze.berlin.de/perma?j=FeiertG_BE | P11: Knittel | Z11: =IF(OR('Projektübersicht'!$F$11="",'Projektübersicht'!$F$13="",'Projektübersicht'!$F$11>'Projektübersicht'!$F$13),"",IF('Projektübersicht'!$F$11+9<='Projektübersicht'!$F$13,'Projektübersicht'!$F$11+9,"")) | AA11: 10 | AB11: =IF(OR('Projektübersicht'!$F$11="",'Projektübersicht'!$F$13="",'Projektübersicht'!$F$11>'Projektübersicht'!$F$13),"",IF(WORKDAY.INTL('Projektübersicht'!$F$11-1,10,"0000001")<='Projektübersicht'!$F$13,WORKDAY.INTL('Projektübersicht'!$F$11-1,10,"0000001"),"")) | AC11: 10
A12: Reinigung | B12: Hasselbach | E12: 46023 | F12: Neujahr | G12: https://gesetze.berlin.de/perma?j=FeiertG_BE | P12: Brillux | Z12: =IF(OR('Projektübersicht'!$F$11="",'Projektübersicht'!$F$13="",'Projektübersicht'!$F$11>'Projektübersicht'!$F$13),"",IF('Projektübersicht'!$F$11+10<='Projektübersicht'!$F$13,'Projektübersicht'!$F$11+10,"")) | AA12: 11 | AB12: =IF(OR('Projektübersicht'!$F$11="",'Projektübersicht'!$F$13="",'Projektübersicht'!$F$11>'Projektübersicht'!$F$13),"",IF(WORKDAY.INTL('Projektübersicht'!$F$11-1,11,"0000001")<='Projektübersicht'!$F$13,WORKDAY.INTL('Projektübersicht'!$F$11-1,11,"0000001"),"")) | AC12: 11
A13: Sonstiges | B13: Hüttemann | E13: 46089 | F13: Internationaler Frauentag | G13: https://gesetze.berlin.de/perma?j=FeiertG_BE | Z13: =IF(OR('Projektübersicht'!$F$11="",'Projektübersicht'!$F$13="",'Projektübersicht'!$F$11>'Projektübersicht'!$F$13),"",IF('Projektübersicht'!$F$11+11<='Projektübersicht'!$F$13,'Projektübersicht'!$F$11+11,"")) | AA13: 12 | AB13: =IF(OR('Projektübersicht'!$F$11="",'Projektübersicht'!$F$13="",'Projektübersicht'!$F$11>'Projektübersicht'!$F$13),"",IF(WORKDAY.INTL('Projektübersicht'!$F$11-1,12,"0000001")<='Projektübersicht'!$F$13,WORKDAY.INTL('Projektübersicht'!$F$11-1,12,"0000001"),"")) | AC13: 12
B14: Immig | E14: 46115 | F14: Karfreitag | G14: https://gesetze.berlin.de/perma?j=FeiertG_BE | Z14: =IF(OR('Projektübersicht'!$F$11="",'Projektübersicht'!$F$13="",'Projektübersicht'!$F$11>'Projektübersicht'!$F$13),"",IF('Projektübersicht'!$F$11+12<='Projektübersicht'!$F$13,'Projektübersicht'!$F$11+12,"")) | AA14: 13 | AB14: =IF(OR('Projektübersicht'!$F$11="",'Projektübersicht'!$F$13="",'Projektübersicht'!$F$11>'Projektübersicht'!$F$13),"",IF(WORKDAY.INTL('Projektübersicht'!$F$11-1,13,"0000001")<='Projektübersicht'!$F$13,WORKDAY.INTL('Projektübersicht'!$F$11-1,13,"0000001"),"")) | AC14: 13
B15: Jarosch | E15: 46118 | F15: Ostermontag | G15: https://gesetze.berlin.de/perma?j=FeiertG_BE | Z15: =IF(OR('Projektübersicht'!$F$11="",'Projektübersicht'!$F$13="",'Projektübersicht'!$F$11>'Projektübersicht'!$F$13),"",IF('Projektübersicht'!$F$11+13<='Projektübersicht'!$F$13,'Projektübersicht'!$F$11+13,"")) | AA15: 14 | AB15: =IF(OR('Projektübersicht'!$F$11="",'Projektübersicht'!$F$13="",'Projektübersicht'!$F$11>'Projektübersicht'!$F$13),"",IF(WORKDAY.INTL('Projektübersicht'!$F$11-1,14,"0000001")<='Projektübersicht'!$F$13,WORKDAY.INTL('Projektübersicht'!$F$11-1,14,"0000001"),"")) | AC15: 14
B16: Kettler | E16: 46143 | F16: Tag der Arbeit | G16: https://gesetze.berlin.de/perma?j=FeiertG_BE | Z16: =IF(OR('Projektübersicht'!$F$11="",'Projektübersicht'!$F$13="",'Projektübersicht'!$F$11>'Projektübersicht'!$F$13),"",IF('Projektübersicht'!$F$11+14<='Projektübersicht'!$F$13,'Projektübersicht'!$F$11+14,"")) | AA16: 15 | AB16: =IF(OR('Projektübersicht'!$F$11="",'Projektübersicht'!$F$13="",'Projektübersicht'!$F$11>'Projektübersicht'!$F$13),"",IF(WORKDAY.INTL('Projektübersicht'!$F$11-1,15,"0000001")<='Projektübersicht'!$F$13,WORKDAY.INTL('Projektübersicht'!$F$11-1,15,"0000001"),"")) | AC16: 15
B17: Lohmeyer | E17: 46156 | F17: Christi Himmelfahrt | G17: https://gesetze.berlin.de/perma?j=FeiertG_BE | Z17: =IF(OR('Projektübersicht'!$F$11="",'Projektübersicht'!$F$13="",'Projektübersicht'!$F$11>'Projektübersicht'!$F$13),"",IF('Projektübersicht'!$F$11+15<='Projektübersicht'!$F$13,'Projektübersicht'!$F$11+15,"")) | AA17: 16 | AB17: =IF(OR('Projektübersicht'!$F$11="",'Projektübersicht'!$F$13="",'Projektübersicht'!$F$11>'Projektübersicht'!$F$13),"",IF(WORKDAY.INTL('Projektübersicht'!$F$11-1,16,"0000001")<='Projektübersicht'!$F$13,WORKDAY.INTL('Projektübersicht'!$F$11-1,16,"0000001"),"")) | AC17: 16
B18: Mertens | E18: 46167 | F18: Pfingstmontag | G18: https://gesetze.berlin.de/perma?j=FeiertG_BE | Z18: =IF(OR('Projektübersicht'!$F$11="",'Projektübersicht'!$F$13="",'Projektübersicht'!$F$11>'Projektübersicht'!$F$13),"",IF('Projektübersicht'!$F$11+16<='Projektübersicht'!$F$13,'Projektübersicht'!$F$11+16,"")) | AA18: 17 | AB18: =IF(OR('Projektübersicht'!$F$11="",'Projektübersicht'!$F$13="",'Projektübersicht'!$F$11>'Projektübersicht'!$F$13),"",IF(WORKDAY.INTL('Projektübersicht'!$F$11-1,17,"0000001")<='Projektübersicht'!$F$13,WORKDAY.INTL('Projektübersicht'!$F$11-1,17,"0000001"),"")) | AC18: 17
B19: Osterloh | E19: 46298 | F19: Tag der Deutschen Einheit | G19: https://gesetze.berlin.de/perma?j=FeiertG_BE | Z19: =IF(OR('Projektübersicht'!$F$11="",'Projektübersicht'!$F$13="",'Projektübersicht'!$F$11>'Projektübersicht'!$F$13),"",IF('Projektübersicht'!$F$11+17<='Projektübersicht'!$F$13,'Projektübersicht'!$F$11+17,"")) | AA19: 18 | AB19: =IF(OR('Projektübersicht'!$F$11="",'Projektübersicht'!$F$13="",'Projektübersicht'!$F$11>'Projektübersicht'!$F$13),"",IF(WORKDAY.INTL('Projektübersicht'!$F$11-1,18,"0000001")<='Projektübersicht'!$F$13,WORKDAY.INTL('Projektübersicht'!$F$11-1,18,"0000001"),"")) | AC19: 18
B20: Petzold | E20: 46381 | F20: 1. Weihnachtsfeiertag | G20: https://gesetze.berlin.de/perma?j=FeiertG_BE | Z20: =IF(OR('Projektübersicht'!$F$11="",'Projektübersicht'!$F$13="",'Projektübersicht'!$F$11>'Projektübersicht'!$F$13),"",IF('Projektübersicht'!$F$11+18<='Projektübersicht'!$F$13,'Projektübersicht'!$F$11+18,"")) | AA20: 19 | AB20: =IF(OR('Projektübersicht'!$F$11="",'Projektübersicht'!$F$13="",'Projektübersicht'!$F$11>'Projektübersicht'!$F$13),"",IF(WORKDAY.INTL('Projektübersicht'!$F$11-1,19,"0000001")<='Projektübersicht'!$F$13,WORKDAY.INTL('Projektübersicht'!$F$11-1,19,"0000001"),"")) | AC20: 19
B21: Reichardt | E21: 46382 | F21: 2. Weihnachtsfeiertag | G21: https://gesetze.berlin.de/perma?j=FeiertG_BE | Z21: =IF(OR('Projektübersicht'!$F$11="",'Projektübersicht'!$F$13="",'Projektübersicht'!$F$11>'Projektübersicht'!$F$13),"",IF('Projektübersicht'!$F$11+19<='Projektübersicht'!$F$13,'Projektübersicht'!$F$11+19,"")) | AA21: 20 | AB21: =IF(OR('Projektübersicht'!$F$11="",'Projektübersicht'!$F$13="",'Projektübersicht'!$F$11>'Projektübersicht'!$F$13),"",IF(WORKDAY.INTL('Projektübersicht'!$F$11-1,20,"0000001")<='Projektübersicht'!$F$13,WORKDAY.INTL('Projektübersicht'!$F$11-1,20,"0000001"),"")) | AC21: 20
B22: Sandbrink | E22: 46388 | F22: Neujahr | G22: https://gesetze.berlin.de/perma?j=FeiertG_BE | Z22: =IF(OR('Projektübersicht'!$F$11="",'Projektübersicht'!$F$13="",'Projektübersicht'!$F$11>'Projektübersicht'!$F$13),"",IF('Projektübersicht'!$F$11+20<='Projektübersicht'!$F$13,'Projektübersicht'!$F$11+20,"")) | AA22: 21 | AB22: =IF(OR('Projektübersicht'!$F$11="",'Projektübersicht'!$F$13="",'Projektübersicht'!$F$11>'Projektübersicht'!$F$13),"",IF(WORKDAY.INTL('Projektübersicht'!$F$11-1,21,"0000001")<='Projektübersicht'!$F$13,WORKDAY.INTL('Projektübersicht'!$F$11-1,21,"0000001"),"")) | AC22: 21
B23: Terhorst | E23: 46454 | F23: Internationaler Frauentag | G23: https://gesetze.berlin.de/perma?j=FeiertG_BE | Z23: =IF(OR('Projektübersicht'!$F$11="",'Projektübersicht'!$F$13="",'Projektübersicht'!$F$11>'Projektübersicht'!$F$13),"",IF('Projektübersicht'!$F$11+21<='Projektübersicht'!$F$13,'Projektübersicht'!$F$11+21,"")) | AA23: 22 | AB23: =IF(OR('Projektübersicht'!$F$11="",'Projektübersicht'!$F$13="",'Projektübersicht'!$F$11>'Projektübersicht'!$F$13),"",IF(WORKDAY.INTL('Projektübersicht'!$F$11-1,22,"0000001")<='Projektübersicht'!$F$13,WORKDAY.INTL('Projektübersicht'!$F$11-1,22,"0000001"),"")) | AC23: 22
B24: SO (extern) | E24: 46472 | F24: Karfreitag | G24: https://gesetze.berlin.de/perma?j=FeiertG_BE | Z24: =IF(OR('Projektübersicht'!$F$11="",'Projektübersicht'!$F$13="",'Projektübersicht'!$F$11>'Projektübersicht'!$F$13),"",IF('Projektübersicht'!$F$11+22<='Projektübersicht'!$F$13,'Projektübersicht'!$F$11+22,"")) | AA24: 23 | AB24: =IF(OR('Projektübersicht'!$F$11="",'Projektübersicht'!$F$13="",'Projektübersicht'!$F$11>'Projektübersicht'!$F$13),"",IF(WORKDAY.INTL('Projektübersicht'!$F$11-1,23,"0000001")<='Projektübersicht'!$F$13,WORKDAY.INTL('Projektübersicht'!$F$11-1,23,"0000001"),"")) | AC24: 23
B25: Uhlig | E25: 46475 | F25: Ostermontag | G25: https://gesetze.berlin.de/perma?j=FeiertG_BE | Z25: =IF(OR('Projektübersicht'!$F$11="",'Projektübersicht'!$F$13="",'Projektübersicht'!$F$11>'Projektübersicht'!$F$13),"",IF('Projektübersicht'!$F$11+23<='Projektübersicht'!$F$13,'Projektübersicht'!$F$11+23,"")) | AA25: 24 | AB25: =IF(OR('Projektübersicht'!$F$11="",'Projektübersicht'!$F$13="",'Projektübersicht'!$F$11>'Projektübersicht'!$F$13),"",IF(WORKDAY.INTL('Projektübersicht'!$F$11-1,24,"0000001")<='Projektübersicht'!$F$13,WORKDAY.INTL('Projektübersicht'!$F$11-1,24,"0000001"),"")) | AC25: 24
B26: Vollmert | E26: 46508 | F26: Tag der Arbeit | G26: https://gesetze.berlin.de/perma?j=FeiertG_BE | Z26: =IF(OR('Projektübersicht'!$F$11="",'Projektübersicht'!$F$13="",'Projektübersicht'!$F$11>'Projektübersicht'!$F$13),"",IF('Projektübersicht'!$F$11+24<='Projektübersicht'!$F$13,'Projektübersicht'!$F$11+24,"")) | AA26: 25 | AB26: =IF(OR('Projektübersicht'!$F$11="",'Projektübersicht'!$F$13="",'Projektübersicht'!$F$11>'Projektübersicht'!$F$13),"",IF(WORKDAY.INTL('Projektübersicht'!$F$11-1,25,"0000001")<='Projektübersicht'!$F$13,WORKDAY.INTL('Projektübersicht'!$F$11-1,25,"0000001"),"")) | AC26: 25
B27: Wesseling | E27: 46513 | F27: Christi Himmelfahrt | G27: https://gesetze.berlin.de/perma?j=FeiertG_BE | Z27: =IF(OR('Projektübersicht'!$F$11="",'Projektübersicht'!$F$13="",'Projektübersicht'!$F$11>'Projektübersicht'!$F$13),"",IF('Projektübersicht'!$F$11+25<='Projektübersicht'!$F$13,'Projektübersicht'!$F$11+25,"")) | AA27: 26 | AB27: =IF(OR('Projektübersicht'!$F$11="",'Projektübersicht'!$F$13="",'Projektübersicht'!$F$11>'Projektübersicht'!$F$13),"",IF(WORKDAY.INTL('Projektübersicht'!$F$11-1,26,"0000001")<='Projektübersicht'!$F$13,WORKDAY.INTL('Projektübersicht'!$F$11-1,26,"0000001"),"")) | AC27: 26
B28: Nowak | E28: 46524 | F28: Pfingstmontag | G28: https://gesetze.berlin.de/perma?j=FeiertG_BE | Z28: =IF(OR('Projektübersicht'!$F$11="",'Projektübersicht'!$F$13="",'Projektübersicht'!$F$11>'Projektübersicht'!$F$13),"",IF('Projektübersicht'!$F$11+26<='Projektübersicht'!$F$13,'Projektübersicht'!$F$11+26,"")) | AA28: 27 | AB28: =IF(OR('Projektübersicht'!$F$11="",'Projektübersicht'!$F$13="",'Projektübersicht'!$F$11>'Projektübersicht'!$F$13),"",IF(WORKDAY.INTL('Projektübersicht'!$F$11-1,27,"0000001")<='Projektübersicht'!$F$13,WORKDAY.INTL('Projektübersicht'!$F$11-1,27,"0000001"),"")) | AC28: 27
B29: Öztürk | E29: 46663 | F29: Tag der Deutschen Einheit | G29: https://gesetze.berlin.de/perma?j=FeiertG_BE | Z29: =IF(OR('Projektübersicht'!$F$11="",'Projektübersicht'!$F$13="",'Projektübersicht'!$F$11>'Projektübersicht'!$F$13),"",IF('Projektübersicht'!$F$11+27<='Projektübersicht'!$F$13,'Projektübersicht'!$F$11+27,"")) | AA29: 28 | AB29: =IF(OR('Projektübersicht'!$F$11="",'Projektübersicht'!$F$13="",'Projektübersicht'!$F$11>'Projektübersicht'!$F$13),"",IF(WORKDAY.INTL('Projektübersicht'!$F$11-1,28,"0000001")<='Projektübersicht'!$F$13,WORKDAY.INTL('Projektübersicht'!$F$11-1,28,"0000001"),"")) | AC29: 28
E30: 46746 | F30: 1. Weihnachtsfeiertag | G30: https://gesetze.berlin.de/perma?j=FeiertG_BE | Z30: =IF(OR('Projektübersicht'!$F$11="",'Projektübersicht'!$F$13="",'Projektübersicht'!$F$11>'Projektübersicht'!$F$13),"",IF('Projektübersicht'!$F$11+28<='Projektübersicht'!$F$13,'Projektübersicht'!$F$11+28,"")) | AA30: 29 | AB30: =IF(OR('Projektübersicht'!$F$11="",'Projektübersicht'!$F$13="",'Projektübersicht'!$F$11>'Projektübersicht'!$F$13),"",IF(WORKDAY.INTL('Projektübersicht'!$F$11-1,29,"0000001")<='Projektübersicht'!$F$13,WORKDAY.INTL('Projektübersicht'!$F$11-1,29,"0000001"),"")) | AC30: 29
E31: 46747 | F31: 2. Weihnachtsfeiertag | G31: https://gesetze.berlin.de/perma?j=FeiertG_BE | Z31: =IF(OR('Projektübersicht'!$F$11="",'Projektübersicht'!$F$13="",'Projektübersicht'!$F$11>'Projektübersicht'!$F$13),"",IF('Projektübersicht'!$F$11+29<='Projektübersicht'!$F$13,'Projektübersicht'!$F$11+29,"")) | AA31: 30 | AB31: =IF(OR('Projektübersicht'!$F$11="",'Projektübersicht'!$F$13="",'Projektübersicht'!$F$11>'Projektübersicht'!$F$13),"",IF(WORKDAY.INTL('Projektübersicht'!$F$11-1,30,"0000001")<='Projektübersicht'!$F$13,WORKDAY.INTL('Projektübersicht'!$F$11-1,30,"0000001"),"")) | AC31: 30
E32: 46753 | F32: Neujahr | G32: https://gesetze.berlin.de/perma?j=FeiertG_BE | Z32: =IF(OR('Projektübersicht'!$F$11="",'Projektübersicht'!$F$13="",'Projektübersicht'!$F$11>'Projektübersicht'!$F$13),"",IF('Projektübersicht'!$F$11+30<='Projektübersicht'!$F$13,'Projektübersicht'!$F$11+30,"")) | AA32: 31 | AB32: =IF(OR('Projektübersicht'!$F$11="",'Projektübersicht'!$F$13="",'Projektübersicht'!$F$11>'Projektübersicht'!$F$13),"",IF(WORKDAY.INTL('Projektübersicht'!$F$11-1,31,"0000001")<='Projektübersicht'!$F$13,WORKDAY.INTL('Projektübersicht'!$F$11-1,31,"0000001"),"")) | AC32: 31
E33: 46820 | F33: Internationaler Frauentag | G33: https://gesetze.berlin.de/perma?j=FeiertG_BE | Z33: =IF(OR('Projektübersicht'!$F$11="",'Projektübersicht'!$F$13="",'Projektübersicht'!$F$11>'Projektübersicht'!$F$13),"",IF('Projektübersicht'!$F$11+31<='Projektübersicht'!$F$13,'Projektübersicht'!$F$11+31,"")) | AA33: 32 | AB33: =IF(OR('Projektübersicht'!$F$11="",'Projektübersicht'!$F$13="",'Projektübersicht'!$F$11>'Projektübersicht'!$F$13),"",IF(WORKDAY.INTL('Projektübersicht'!$F$11-1,32,"0000001")<='Projektübersicht'!$F$13,WORKDAY.INTL('Projektübersicht'!$F$11-1,32,"0000001"),"")) | AC33: 32
E34: 46857 | F34: Karfreitag | G34: https://gesetze.berlin.de/perma?j=FeiertG_BE | Z34: =IF(OR('Projektübersicht'!$F$11="",'Projektübersicht'!$F$13="",'Projektübersicht'!$F$11>'Projektübersicht'!$F$13),"",IF('Projektübersicht'!$F$11+32<='Projektübersicht'!$F$13,'Projektübersicht'!$F$11+32,"")) | AA34: 33 | AB34: =IF(OR('Projektübersicht'!$F$11="",'Projektübersicht'!$F$13="",'Projektübersicht'!$F$11>'Projektübersicht'!$F$13),"",IF(WORKDAY.INTL('Projektübersicht'!$F$11-1,33,"0000001")<='Projektübersicht'!$F$13,WORKDAY.INTL('Projektübersicht'!$F$11-1,33,"0000001"),"")) | AC34: 33
E35: 46860 | F35: Ostermontag | G35: https://gesetze.berlin.de/perma?j=FeiertG_BE | Z35: =IF(OR('Projektübersicht'!$F$11="",'Projektübersicht'!$F$13="",'Projektübersicht'!$F$11>'Projektübersicht'!$F$13),"",IF('Projektübersicht'!$F$11+33<='Projektübersicht'!$F$13,'Projektübersicht'!$F$11+33,"")) | AA35: 34 | AB35: =IF(OR('Projektübersicht'!$F$11="",'Projektübersicht'!$F$13="",'Projektübersicht'!$F$11>'Projektübersicht'!$F$13),"",IF(WORKDAY.INTL('Projektübersicht'!$F$11-1,34,"0000001")<='Projektübersicht'!$F$13,WORKDAY.INTL('Projektübersicht'!$F$11-1,34,"0000001"),"")) | AC35: 34
E36: 46874 | F36: Tag der Arbeit | G36: https://gesetze.berlin.de/perma?j=FeiertG_BE | Z36: =IF(OR('Projektübersicht'!$F$11="",'Projektübersicht'!$F$13="",'Projektübersicht'!$F$11>'Projektübersicht'!$F$13),"",IF('Projektübersicht'!$F$11+34<='Projektübersicht'!$F$13,'Projektübersicht'!$F$11+34,"")) | AA36: 35 | AB36: =IF(OR('Projektübersicht'!$F$11="",'Projektübersicht'!$F$13="",'Projektübersicht'!$F$11>'Projektübersicht'!$F$13),"",IF(WORKDAY.INTL('Projektübersicht'!$F$11-1,35,"0000001")<='Projektübersicht'!$F$13,WORKDAY.INTL('Projektübersicht'!$F$11-1,35,"0000001"),"")) | AC36: 35
E37: 46898 | F37: Christi Himmelfahrt | G37: https://gesetze.berlin.de/perma?j=FeiertG_BE | Z37: =IF(OR('Projektübersicht'!$F$11="",'Projektübersicht'!$F$13="",'Projektübersicht'!$F$11>'Projektübersicht'!$F$13),"",IF('Projektübersicht'!$F$11+35<='Projektübersicht'!$F$13,'Projektübersicht'!$F$11+35,"")) | AA37: 36 | AB37: =IF(OR('Projektübersicht'!$F$11="",'Projektübersicht'!$F$13="",'Projektübersicht'!$F$11>'Projektübersicht'!$F$13),"",IF(WORKDAY.INTL('Projektübersicht'!$F$11-1,36,"0000001")<='Projektübersicht'!$F$13,WORKDAY.INTL('Projektübersicht'!$F$11-1,36,"0000001"),"")) | AC37: 36
E38: 46909 | F38: Pfingstmontag | G38: https://gesetze.berlin.de/perma?j=FeiertG_BE | Z38: =IF(OR('Projektübersicht'!$F$11="",'Projektübersicht'!$F$13="",'Projektübersicht'!$F$11>'Projektübersicht'!$F$13),"",IF('Projektübersicht'!$F$11+36<='Projektübersicht'!$F$13,'Projektübersicht'!$F$11+36,"")) | AA38: 37 | AB38: =IF(OR('Projektübersicht'!$F$11="",'Projektübersicht'!$F$13="",'Projektübersicht'!$F$11>'Projektübersicht'!$F$13),"",IF(WORKDAY.INTL('Projektübersicht'!$F$11-1,37,"0000001")<='Projektübersicht'!$F$13,WORKDAY.INTL('Projektübersicht'!$F$11-1,37,"0000001"),"")) | AC38: 37
E39: 46921 | F39: 75. Jahrestag des Volksaufstands vom 17. Juni 1953 | G39: https://gesetze.berlin.de/perma?j=FeiertG_BE | Z39: =IF(OR('Projektübersicht'!$F$11="",'Projektübersicht'!$F$13="",'Projektübersicht'!$F$11>'Projektübersicht'!$F$13),"",IF('Projektübersicht'!$F$11+37<='Projektübersicht'!$F$13,'Projektübersicht'!$F$11+37,"")) | AA39: 38 | AB39: =IF(OR('Projektübersicht'!$F$11="",'Projektübersicht'!$F$13="",'Projektübersicht'!$F$11>'Projektübersicht'!$F$13),"",IF(WORKDAY.INTL('Projektübersicht'!$F$11-1,38,"0000001")<='Projektübersicht'!$F$13,WORKDAY.INTL('Projektübersicht'!$F$11-1,38,"0000001"),"")) | AC39: 38
E40: 47029 | F40: Tag der Deutschen Einheit | G40: https://gesetze.berlin.de/perma?j=FeiertG_BE | Z40: =IF(OR('Projektübersicht'!$F$11="",'Projektübersicht'!$F$13="",'Projektübersicht'!$F$11>'Projektübersicht'!$F$13),"",IF('Projektübersicht'!$F$11+38<='Projektübersicht'!$F$13,'Projektübersicht'!$F$11+38,"")) | AA40: 39 | AB40: =IF(OR('Projektübersicht'!$F$11="",'Projektübersicht'!$F$13="",'Projektübersicht'!$F$11>'Projektübersicht'!$F$13),"",IF(WORKDAY.INTL('Projektübersicht'!$F$11-1,39,"0000001")<='Projektübersicht'!$F$13,WORKDAY.INTL('Projektübersicht'!$F$11-1,39,"0000001"),"")) | AC40: 39
E41: 47112 | F41: 1. Weihnachtsfeiertag | G41: https://gesetze.berlin.de/perma?j=FeiertG_BE | Z41: =IF(OR('Projektübersicht'!$F$11="",'Projektübersicht'!$F$13="",'Projektübersicht'!$F$11>'Projektübersicht'!$F$13),"",IF('Projektübersicht'!$F$11+39<='Projektübersicht'!$F$13,'Projektübersicht'!$F$11+39,"")) | AA41: 40 | AB41: =IF(OR('Projektübersicht'!$F$11="",'Projektübersicht'!$F$13="",'Projektübersicht'!$F$11>'Projektübersicht'!$F$13),"",IF(WORKDAY.INTL('Projektübersicht'!$F$11-1,40,"0000001")<='Projektübersicht'!$F$13,WORKDAY.INTL('Projektübersicht'!$F$11-1,40,"0000001"),"")) | AC41: 40
E42: 47113 | F42: 2. Weihnachtsfeiertag | G42: https://gesetze.berlin.de/perma?j=FeiertG_BE | Z42: =IF(OR('Projektübersicht'!$F$11="",'Projektübersicht'!$F$13="",'Projektübersicht'!$F$11>'Projektübersicht'!$F$13),"",IF('Projektübersicht'!$F$11+40<='Projektübersicht'!$F$13,'Projektübersicht'!$F$11+40,"")) | AA42: 41 | AB42: =IF(OR('Projektübersicht'!$F$11="",'Projektübersicht'!$F$13="",'Projektübersicht'!$F$11>'Projektübersicht'!$F$13),"",IF(WORKDAY.INTL('Projektübersicht'!$F$11-1,41,"0000001")<='Projektübersicht'!$F$13,WORKDAY.INTL('Projektübersicht'!$F$11-1,41,"0000001"),"")) | AC42: 41
E43: 47119 | F43: Neujahr | G43: https://gesetze.berlin.de/perma?j=FeiertG_BE | Z43: =IF(OR('Projektübersicht'!$F$11="",'Projektübersicht'!$F$13="",'Projektübersicht'!$F$11>'Projektübersicht'!$F$13),"",IF('Projektübersicht'!$F$11+41<='Projektübersicht'!$F$13,'Projektübersicht'!$F$11+41,"")) | AA43: 42 | AB43: =IF(OR('Projektübersicht'!$F$11="",'Projektübersicht'!$F$13="",'Projektübersicht'!$F$11>'Projektübersicht'!$F$13),"",IF(WORKDAY.INTL('Projektübersicht'!$F$11-1,42,"0000001")<='Projektübersicht'!$F$13,WORKDAY.INTL('Projektübersicht'!$F$11-1,42,"0000001"),"")) | AC43: 42
E44: 47185 | F44: Internationaler Frauentag | G44: https://gesetze.berlin.de/perma?j=FeiertG_BE | Z44: =IF(OR('Projektübersicht'!$F$11="",'Projektübersicht'!$F$13="",'Projektübersicht'!$F$11>'Projektübersicht'!$F$13),"",IF('Projektübersicht'!$F$11+42<='Projektübersicht'!$F$13,'Projektübersicht'!$F$11+42,"")) | AA44: 43 | AB44: =IF(OR('Projektübersicht'!$F$11="",'Projektübersicht'!$F$13="",'Projektübersicht'!$F$11>'Projektübersicht'!$F$13),"",IF(WORKDAY.INTL('Projektübersicht'!$F$11-1,43,"0000001")<='Projektübersicht'!$F$13,WORKDAY.INTL('Projektübersicht'!$F$11-1,43,"0000001"),"")) | AC44: 43
E45: 47207 | F45: Karfreitag | G45: https://gesetze.berlin.de/perma?j=FeiertG_BE | Z45: =IF(OR('Projektübersicht'!$F$11="",'Projektübersicht'!$F$13="",'Projektübersicht'!$F$11>'Projektübersicht'!$F$13),"",IF('Projektübersicht'!$F$11+43<='Projektübersicht'!$F$13,'Projektübersicht'!$F$11+43,"")) | AA45: 44 | AB45: =IF(OR('Projektübersicht'!$F$11="",'Projektübersicht'!$F$13="",'Projektübersicht'!$F$11>'Projektübersicht'!$F$13),"",IF(WORKDAY.INTL('Projektübersicht'!$F$11-1,44,"0000001")<='Projektübersicht'!$F$13,WORKDAY.INTL('Projektübersicht'!$F$11-1,44,"0000001"),"")) | AC45: 44
E46: 47210 | F46: Ostermontag | G46: https://gesetze.berlin.de/perma?j=FeiertG_BE | Z46: =IF(OR('Projektübersicht'!$F$11="",'Projektübersicht'!$F$13="",'Projektübersicht'!$F$11>'Projektübersicht'!$F$13),"",IF('Projektübersicht'!$F$11+44<='Projektübersicht'!$F$13,'Projektübersicht'!$F$11+44,"")) | AA46: 45 | AB46: =IF(OR('Projektübersicht'!$F$11="",'Projektübersicht'!$F$13="",'Projektübersicht'!$F$11>'Projektübersicht'!$F$13),"",IF(WORKDAY.INTL('Projektübersicht'!$F$11-1,45,"0000001")<='Projektübersicht'!$F$13,WORKDAY.INTL('Projektübersicht'!$F$11-1,45,"0000001"),"")) | AC46: 45
E47: 47239 | F47: Tag der Arbeit | G47: https://gesetze.berlin.de/perma?j=FeiertG_BE | Z47: =IF(OR('Projektübersicht'!$F$11="",'Projektübersicht'!$F$13="",'Projektübersicht'!$F$11>'Projektübersicht'!$F$13),"",IF('Projektübersicht'!$F$11+45<='Projektübersicht'!$F$13,'Projektübersicht'!$F$11+45,"")) | AA47: 46 | AB47: =IF(OR('Projektübersicht'!$F$11="",'Projektübersicht'!$F$13="",'Projektübersicht'!$F$11>'Projektübersicht'!$F$13),"",IF(WORKDAY.INTL('Projektübersicht'!$F$11-1,46,"0000001")<='Projektübersicht'!$F$13,WORKDAY.INTL('Projektübersicht'!$F$11-1,46,"0000001"),"")) | AC47: 46
E48: 47248 | F48: Christi Himmelfahrt | G48: https://gesetze.berlin.de/perma?j=FeiertG_BE | Z48: =IF(OR('Projektübersicht'!$F$11="",'Projektübersicht'!$F$13="",'Projektübersicht'!$F$11>'Projektübersicht'!$F$13),"",IF('Projektübersicht'!$F$11+46<='Projektübersicht'!$F$13,'Projektübersicht'!$F$11+46,"")) | AA48: 47 | AB48: =IF(OR('Projektübersicht'!$F$11="",'Projektübersicht'!$F$13="",'Projektübersicht'!$F$11>'Projektübersicht'!$F$13),"",IF(WORKDAY.INTL('Projektübersicht'!$F$11-1,47,"0000001")<='Projektübersicht'!$F$13,WORKDAY.INTL('Projektübersicht'!$F$11-1,47,"0000001"),"")) | AC48: 47
E49: 47259 | F49: Pfingstmontag | G49: https://gesetze.berlin.de/perma?j=FeiertG_BE | Z49: =IF(OR('Projektübersicht'!$F$11="",'Projektübersicht'!$F$13="",'Projektübersicht'!$F$11>'Projektübersicht'!$F$13),"",IF('Projektübersicht'!$F$11+47<='Projektübersicht'!$F$13,'Projektübersicht'!$F$11+47,"")) | AA49: 48 | AB49: =IF(OR('Projektübersicht'!$F$11="",'Projektübersicht'!$F$13="",'Projektübersicht'!$F$11>'Projektübersicht'!$F$13),"",IF(WORKDAY.INTL('Projektübersicht'!$F$11-1,48,"0000001")<='Projektübersicht'!$F$13,WORKDAY.INTL('Projektübersicht'!$F$11-1,48,"0000001"),"")) | AC49: 48
E50: 47394 | F50: Tag der Deutschen Einheit | G50: https://gesetze.berlin.de/perma?j=FeiertG_BE | Z50: =IF(OR('Projektübersicht'!$F$11="",'Projektübersicht'!$F$13="",'Projektübersicht'!$F$11>'Projektübersicht'!$F$13),"",IF('Projektübersicht'!$F$11+48<='Projektübersicht'!$F$13,'Projektübersicht'!$F$11+48,"")) | AA50: 49 | AB50: =IF(OR('Projektübersicht'!$F$11="",'Projektübersicht'!$F$13="",'Projektübersicht'!$F$11>'Projektübersicht'!$F$13),"",IF(WORKDAY.INTL('Projektübersicht'!$F$11-1,49,"0000001")<='Projektübersicht'!$F$13,WORKDAY.INTL('Projektübersicht'!$F$11-1,49,"0000001"),"")) | AC50: 49
E51: 47477 | F51: 1. Weihnachtsfeiertag | G51: https://gesetze.berlin.de/perma?j=FeiertG_BE | Z51: =IF(OR('Projektübersicht'!$F$11="",'Projektübersicht'!$F$13="",'Projektübersicht'!$F$11>'Projektübersicht'!$F$13),"",IF('Projektübersicht'!$F$11+49<='Projektübersicht'!$F$13,'Projektübersicht'!$F$11+49,"")) | AA51: 50 | AB51: =IF(OR('Projektübersicht'!$F$11="",'Projektübersicht'!$F$13="",'Projektübersicht'!$F$11>'Projektübersicht'!$F$13),"",IF(WORKDAY.INTL('Projektübersicht'!$F$11-1,50,"0000001")<='Projektübersicht'!$F$13,WORKDAY.INTL('Projektübersicht'!$F$11-1,50,"0000001"),"")) | AC51: 50
E52: 47478 | F52: 2. Weihnachtsfeiertag | G52: https://gesetze.berlin.de/perma?j=FeiertG_BE | Z52: =IF(OR('Projektübersicht'!$F$11="",'Projektübersicht'!$F$13="",'Projektübersicht'!$F$11>'Projektübersicht'!$F$13),"",IF('Projektübersicht'!$F$11+50<='Projektübersicht'!$F$13,'Projektübersicht'!$F$11+50,"")) | AA52: 51 | AB52: =IF(OR('Projektübersicht'!$F$11="",'Projektübersicht'!$F$13="",'Projektübersicht'!$F$11>'Projektübersicht'!$F$13),"",IF(WORKDAY.INTL('Projektübersicht'!$F$11-1,51,"0000001")<='Projektübersicht'!$F$13,WORKDAY.INTL('Projektübersicht'!$F$11-1,51,"0000001"),"")) | AC52: 51
E53: 47484 | F53: Neujahr | G53: https://gesetze.berlin.de/perma?j=FeiertG_BE | Z53: =IF(OR('Projektübersicht'!$F$11="",'Projektübersicht'!$F$13="",'Projektübersicht'!$F$11>'Projektübersicht'!$F$13),"",IF('Projektübersicht'!$F$11+51<='Projektübersicht'!$F$13,'Projektübersicht'!$F$11+51,"")) | AA53: 52 | AB53: =IF(OR('Projektübersicht'!$F$11="",'Projektübersicht'!$F$13="",'Projektübersicht'!$F$11>'Projektübersicht'!$F$13),"",IF(WORKDAY.INTL('Projektübersicht'!$F$11-1,52,"0000001")<='Projektübersicht'!$F$13,WORKDAY.INTL('Projektübersicht'!$F$11-1,52,"0000001"),"")) | AC53: 52
E54: 47550 | F54: Internationaler Frauentag | G54: https://gesetze.berlin.de/perma?j=FeiertG_BE | Z54: =IF(OR('Projektübersicht'!$F$11="",'Projektübersicht'!$F$13="",'Projektübersicht'!$F$11>'Projektübersicht'!$F$13),"",IF('Projektübersicht'!$F$11+52<='Projektübersicht'!$F$13,'Projektübersicht'!$F$11+52,"")) | AA54: 53 | AB54: =IF(OR('Projektübersicht'!$F$11="",'Projektübersicht'!$F$13="",'Projektübersicht'!$F$11>'Projektübersicht'!$F$13),"",IF(WORKDAY.INTL('Projektübersicht'!$F$11-1,53,"0000001")<='Projektübersicht'!$F$13,WORKDAY.INTL('Projektübersicht'!$F$11-1,53,"0000001"),"")) | AC54: 53
E55: 47592 | F55: Karfreitag | G55: https://gesetze.berlin.de/perma?j=FeiertG_BE | Z55: =IF(OR('Projektübersicht'!$F$11="",'Projektübersicht'!$F$13="",'Projektübersicht'!$F$11>'Projektübersicht'!$F$13),"",IF('Projektübersicht'!$F$11+53<='Projektübersicht'!$F$13,'Projektübersicht'!$F$11+53,"")) | AB55: =IF(OR('Projektübersicht'!$F$11="",'Projektübersicht'!$F$13="",'Projektübersicht'!$F$11>'Projektübersicht'!$F$13),"",IF(WORKDAY.INTL('Projektübersicht'!$F$11-1,54,"0000001")<='Projektübersicht'!$F$13,WORKDAY.INTL('Projektübersicht'!$F$11-1,54,"0000001"),""))
E56: 47595 | F56: Ostermontag | G56: https://gesetze.berlin.de/perma?j=FeiertG_BE | Z56: =IF(OR('Projektübersicht'!$F$11="",'Projektübersicht'!$F$13="",'Projektübersicht'!$F$11>'Projektübersicht'!$F$13),"",IF('Projektübersicht'!$F$11+54<='Projektübersicht'!$F$13,'Projektübersicht'!$F$11+54,"")) | AB56: =IF(OR('Projektübersicht'!$F$11="",'Projektübersicht'!$F$13="",'Projektübersicht'!$F$11>'Projektübersicht'!$F$13),"",IF(WORKDAY.INTL('Projektübersicht'!$F$11-1,55,"0000001")<='Projektübersicht'!$F$13,WORKDAY.INTL('Projektübersicht'!$F$11-1,55,"0000001"),""))
E57: 47604 | F57: Tag der Arbeit | G57: https://gesetze.berlin.de/perma?j=FeiertG_BE | Z57: =IF(OR('Projektübersicht'!$F$11="",'Projektübersicht'!$F$13="",'Projektübersicht'!$F$11>'Projektübersicht'!$F$13),"",IF('Projektübersicht'!$F$11+55<='Projektübersicht'!$F$13,'Projektübersicht'!$F$11+55,"")) | AB57: =IF(OR('Projektübersicht'!$F$11="",'Projektübersicht'!$F$13="",'Projektübersicht'!$F$11>'Projektübersicht'!$F$13),"",IF(WORKDAY.INTL('Projektübersicht'!$F$11-1,56,"0000001")<='Projektübersicht'!$F$13,WORKDAY.INTL('Projektübersicht'!$F$11-1,56,"0000001"),""))
E58: 47633 | F58: Christi Himmelfahrt | G58: https://gesetze.berlin.de/perma?j=FeiertG_BE | Z58: =IF(OR('Projektübersicht'!$F$11="",'Projektübersicht'!$F$13="",'Projektübersicht'!$F$11>'Projektübersicht'!$F$13),"",IF('Projektübersicht'!$F$11+56<='Projektübersicht'!$F$13,'Projektübersicht'!$F$11+56,"")) | AB58: =IF(OR('Projektübersicht'!$F$11="",'Projektübersicht'!$F$13="",'Projektübersicht'!$F$11>'Projektübersicht'!$F$13),"",IF(WORKDAY.INTL('Projektübersicht'!$F$11-1,57,"0000001")<='Projektübersicht'!$F$13,WORKDAY.INTL('Projektübersicht'!$F$11-1,57,"0000001"),""))
E59: 47644 | F59: Pfingstmontag | G59: https://gesetze.berlin.de/perma?j=FeiertG_BE | Z59: =IF(OR('Projektübersicht'!$F$11="",'Projektübersicht'!$F$13="",'Projektübersicht'!$F$11>'Projektübersicht'!$F$13),"",IF('Projektübersicht'!$F$11+57<='Projektübersicht'!$F$13,'Projektübersicht'!$F$11+57,"")) | AB59: =IF(OR('Projektübersicht'!$F$11="",'Projektübersicht'!$F$13="",'Projektübersicht'!$F$11>'Projektübersicht'!$F$13),"",IF(WORKDAY.INTL('Projektübersicht'!$F$11-1,58,"0000001")<='Projektübersicht'!$F$13,WORKDAY.INTL('Projektübersicht'!$F$11-1,58,"0000001"),""))
E60: 47759 | F60: Tag der Deutschen Einheit | G60: https://gesetze.berlin.de/perma?j=FeiertG_BE | Z60: =IF(OR('Projektübersicht'!$F$11="",'Projektübersicht'!$F$13="",'Projektübersicht'!$F$11>'Projektübersicht'!$F$13),"",IF('Projektübersicht'!$F$11+58<='Projektübersicht'!$F$13,'Projektübersicht'!$F$11+58,"")) | AB60: =IF(OR('Projektübersicht'!$F$11="",'Projektübersicht'!$F$13="",'Projektübersicht'!$F$11>'Projektübersicht'!$F$13),"",IF(WORKDAY.INTL('Projektübersicht'!$F$11-1,59,"0000001")<='Projektübersicht'!$F$13,WORKDAY.INTL('Projektübersicht'!$F$11-1,59,"0000001"),""))
E61: 47842 | F61: 1. Weihnachtsfeiertag | G61: https://gesetze.berlin.de/perma?j=FeiertG_BE | Z61: =IF(OR('Projektübersicht'!$F$11="",'Projektübersicht'!$F$13="",'Projektübersicht'!$F$11>'Projektübersicht'!$F$13),"",IF('Projektübersicht'!$F$11+59<='Projektübersicht'!$F$13,'Projektübersicht'!$F$11+59,"")) | AB61: =IF(OR('Projektübersicht'!$F$11="",'Projektübersicht'!$F$13="",'Projektübersicht'!$F$11>'Projektübersicht'!$F$13),"",IF(WORKDAY.INTL('Projektübersicht'!$F$11-1,60,"0000001")<='Projektübersicht'!$F$13,WORKDAY.INTL('Projektübersicht'!$F$11-1,60,"0000001"),""))
E62: 47843 | F62: 2. Weihnachtsfeiertag | G62: https://gesetze.berlin.de/perma?j=FeiertG_BE | Z62: =IF(OR('Projektübersicht'!$F$11="",'Projektübersicht'!$F$13="",'Projektübersicht'!$F$11>'Projektübersicht'!$F$13),"",IF('Projektübersicht'!$F$11+60<='Projektübersicht'!$F$13,'Projektübersicht'!$F$11+60,"")) | AB62: =IF(OR('Projektübersicht'!$F$11="",'Projektübersicht'!$F$13="",'Projektübersicht'!$F$11>'Projektübersicht'!$F$13),"",IF(WORKDAY.INTL('Projektübersicht'!$F$11-1,61,"0000001")<='Projektübersicht'!$F$13,WORKDAY.INTL('Projektübersicht'!$F$11-1,61,"0000001"),""))
E63: 47849 | F63: Neujahr | G63: https://gesetze.berlin.de/perma?j=FeiertG_BE | Z63: =IF(OR('Projektübersicht'!$F$11="",'Projektübersicht'!$F$13="",'Projektübersicht'!$F$11>'Projektübersicht'!$F$13),"",IF('Projektübersicht'!$F$11+61<='Projektübersicht'!$F$13,'Projektübersicht'!$F$11+61,"")) | AB63: =IF(OR('Projektübersicht'!$F$11="",'Projektübersicht'!$F$13="",'Projektübersicht'!$F$11>'Projektübersicht'!$F$13),"",IF(WORKDAY.INTL('Projektübersicht'!$F$11-1,62,"0000001")<='Projektübersicht'!$F$13,WORKDAY.INTL('Projektübersicht'!$F$11-1,62,"0000001"),""))
E64: 47915 | F64: Internationaler Frauentag | G64: https://gesetze.berlin.de/perma?j=FeiertG_BE | Z64: =IF(OR('Projektübersicht'!$F$11="",'Projektübersicht'!$F$13="",'Projektübersicht'!$F$11>'Projektübersicht'!$F$13),"",IF('Projektübersicht'!$F$11+62<='Projektübersicht'!$F$13,'Projektübersicht'!$F$11+62,"")) | AB64: =IF(OR('Projektübersicht'!$F$11="",'Projektübersicht'!$F$13="",'Projektübersicht'!$F$11>'Projektübersicht'!$F$13),"",IF(WORKDAY.INTL('Projektübersicht'!$F$11-1,63,"0000001")<='Projektübersicht'!$F$13,WORKDAY.INTL('Projektübersicht'!$F$11-1,63,"0000001"),""))
E65: 47949 | F65: Karfreitag | G65: https://gesetze.berlin.de/perma?j=FeiertG_BE | Z65: =IF(OR('Projektübersicht'!$F$11="",'Projektübersicht'!$F$13="",'Projektübersicht'!$F$11>'Projektübersicht'!$F$13),"",IF('Projektübersicht'!$F$11+63<='Projektübersicht'!$F$13,'Projektübersicht'!$F$11+63,"")) | AB65: =IF(OR('Projektübersicht'!$F$11="",'Projektübersicht'!$F$13="",'Projektübersicht'!$F$11>'Projektübersicht'!$F$13),"",IF(WORKDAY.INTL('Projektübersicht'!$F$11-1,64,"0000001")<='Projektübersicht'!$F$13,WORKDAY.INTL('Projektübersicht'!$F$11-1,64,"0000001"),""))
E66: 47952 | F66: Ostermontag | G66: https://gesetze.berlin.de/perma?j=FeiertG_BE | Z66: =IF(OR('Projektübersicht'!$F$11="",'Projektübersicht'!$F$13="",'Projektübersicht'!$F$11>'Projektübersicht'!$F$13),"",IF('Projektübersicht'!$F$11+64<='Projektübersicht'!$F$13,'Projektübersicht'!$F$11+64,"")) | AB66: =IF(OR('Projektübersicht'!$F$11="",'Projektübersicht'!$F$13="",'Projektübersicht'!$F$11>'Projektübersicht'!$F$13),"",IF(WORKDAY.INTL('Projektübersicht'!$F$11-1,65,"0000001")<='Projektübersicht'!$F$13,WORKDAY.INTL('Projektübersicht'!$F$11-1,65,"0000001"),""))
E67: 47969 | F67: Tag der Arbeit | G67: https://gesetze.berlin.de/perma?j=FeiertG_BE | Z67: =IF(OR('Projektübersicht'!$F$11="",'Projektübersicht'!$F$13="",'Projektübersicht'!$F$11>'Projektübersicht'!$F$13),"",IF('Projektübersicht'!$F$11+65<='Projektübersicht'!$F$13,'Projektübersicht'!$F$11+65,"")) | AB67: =IF(OR('Projektübersicht'!$F$11="",'Projektübersicht'!$F$13="",'Projektübersicht'!$F$11>'Projektübersicht'!$F$13),"",IF(WORKDAY.INTL('Projektübersicht'!$F$11-1,66,"0000001")<='Projektübersicht'!$F$13,WORKDAY.INTL('Projektübersicht'!$F$11-1,66,"0000001"),""))
E68: 47990 | F68: Christi Himmelfahrt | G68: https://gesetze.berlin.de/perma?j=FeiertG_BE | Z68: =IF(OR('Projektübersicht'!$F$11="",'Projektübersicht'!$F$13="",'Projektübersicht'!$F$11>'Projektübersicht'!$F$13),"",IF('Projektübersicht'!$F$11+66<='Projektübersicht'!$F$13,'Projektübersicht'!$F$11+66,"")) | AB68: =IF(OR('Projektübersicht'!$F$11="",'Projektübersicht'!$F$13="",'Projektübersicht'!$F$11>'Projektübersicht'!$F$13),"",IF(WORKDAY.INTL('Projektübersicht'!$F$11-1,67,"0000001")<='Projektübersicht'!$F$13,WORKDAY.INTL('Projektübersicht'!$F$11-1,67,"0000001"),""))
E69: 48001 | F69: Pfingstmontag | G69: https://gesetze.berlin.de/perma?j=FeiertG_BE | Z69: =IF(OR('Projektübersicht'!$F$11="",'Projektübersicht'!$F$13="",'Projektübersicht'!$F$11>'Projektübersicht'!$F$13),"",IF('Projektübersicht'!$F$11+67<='Projektübersicht'!$F$13,'Projektübersicht'!$F$11+67,"")) | AB69: =IF(OR('Projektübersicht'!$F$11="",'Projektübersicht'!$F$13="",'Projektübersicht'!$F$11>'Projektübersicht'!$F$13),"",IF(WORKDAY.INTL('Projektübersicht'!$F$11-1,68,"0000001")<='Projektübersicht'!$F$13,WORKDAY.INTL('Projektübersicht'!$F$11-1,68,"0000001"),""))
E70: 48124 | F70: Tag der Deutschen Einheit | G70: https://gesetze.berlin.de/perma?j=FeiertG_BE | Z70: =IF(OR('Projektübersicht'!$F$11="",'Projektübersicht'!$F$13="",'Projektübersicht'!$F$11>'Projektübersicht'!$F$13),"",IF('Projektübersicht'!$F$11+68<='Projektübersicht'!$F$13,'Projektübersicht'!$F$11+68,"")) | AB70: =IF(OR('Projektübersicht'!$F$11="",'Projektübersicht'!$F$13="",'Projektübersicht'!$F$11>'Projektübersicht'!$F$13),"",IF(WORKDAY.INTL('Projektübersicht'!$F$11-1,69,"0000001")<='Projektübersicht'!$F$13,WORKDAY.INTL('Projektübersicht'!$F$11-1,69,"0000001"),""))
E71: 48207 | F71: 1. Weihnachtsfeiertag | G71: https://gesetze.berlin.de/perma?j=FeiertG_BE | Z71: =IF(OR('Projektübersicht'!$F$11="",'Projektübersicht'!$F$13="",'Projektübersicht'!$F$11>'Projektübersicht'!$F$13),"",IF('Projektübersicht'!$F$11+69<='Projektübersicht'!$F$13,'Projektübersicht'!$F$11+69,"")) | AB71: =IF(OR('Projektübersicht'!$F$11="",'Projektübersicht'!$F$13="",'Projektübersicht'!$F$11>'Projektübersicht'!$F$13),"",IF(WORKDAY.INTL('Projektübersicht'!$F$11-1,70,"0000001")<='Projektübersicht'!$F$13,WORKDAY.INTL('Projektübersicht'!$F$11-1,70,"0000001"),""))
E72: 48208 | F72: 2. Weihnachtsfeiertag | G72: https://gesetze.berlin.de/perma?j=FeiertG_BE | Z72: =IF(OR('Projektübersicht'!$F$11="",'Projektübersicht'!$F$13="",'Projektübersicht'!$F$11>'Projektübersicht'!$F$13),"",IF('Projektübersicht'!$F$11+70<='Projektübersicht'!$F$13,'Projektübersicht'!$F$11+70,"")) | AB72: =IF(OR('Projektübersicht'!$F$11="",'Projektübersicht'!$F$13="",'Projektübersicht'!$F$11>'Projektübersicht'!$F$13),"",IF(WORKDAY.INTL('Projektübersicht'!$F$11-1,71,"0000001")<='Projektübersicht'!$F$13,WORKDAY.INTL('Projektübersicht'!$F$11-1,71,"0000001"),""))
E73: 48214 | F73: Neujahr | G73: https://gesetze.berlin.de/perma?j=FeiertG_BE | Z73: =IF(OR('Projektübersicht'!$F$11="",'Projektübersicht'!$F$13="",'Projektübersicht'!$F$11>'Projektübersicht'!$F$13),"",IF('Projektübersicht'!$F$11+71<='Projektübersicht'!$F$13,'Projektübersicht'!$F$11+71,"")) | AB73: =IF(OR('Projektübersicht'!$F$11="",'Projektübersicht'!$F$13="",'Projektübersicht'!$F$11>'Projektübersicht'!$F$13),"",IF(WORKDAY.INTL('Projektübersicht'!$F$11-1,72,"0000001")<='Projektübersicht'!$F$13,WORKDAY.INTL('Projektübersicht'!$F$11-1,72,"0000001"),""))
E74: 48281 | F74: Internationaler Frauentag | G74: https://gesetze.berlin.de/perma?j=FeiertG_BE | Z74: =IF(OR('Projektübersicht'!$F$11="",'Projektübersicht'!$F$13="",'Projektübersicht'!$F$11>'Projektübersicht'!$F$13),"",IF('Projektübersicht'!$F$11+72<='Projektübersicht'!$F$13,'Projektübersicht'!$F$11+72,"")) | AB74: =IF(OR('Projektübersicht'!$F$11="",'Projektübersicht'!$F$13="",'Projektübersicht'!$F$11>'Projektübersicht'!$F$13),"",IF(WORKDAY.INTL('Projektübersicht'!$F$11-1,73,"0000001")<='Projektübersicht'!$F$13,WORKDAY.INTL('Projektübersicht'!$F$11-1,73,"0000001"),""))
E75: 48299 | F75: Karfreitag | G75: https://gesetze.berlin.de/perma?j=FeiertG_BE | Z75: =IF(OR('Projektübersicht'!$F$11="",'Projektübersicht'!$F$13="",'Projektübersicht'!$F$11>'Projektübersicht'!$F$13),"",IF('Projektübersicht'!$F$11+73<='Projektübersicht'!$F$13,'Projektübersicht'!$F$11+73,"")) | AB75: =IF(OR('Projektübersicht'!$F$11="",'Projektübersicht'!$F$13="",'Projektübersicht'!$F$11>'Projektübersicht'!$F$13),"",IF(WORKDAY.INTL('Projektübersicht'!$F$11-1,74,"0000001")<='Projektübersicht'!$F$13,WORKDAY.INTL('Projektübersicht'!$F$11-1,74,"0000001"),""))
E76: 48302 | F76: Ostermontag | G76: https://gesetze.berlin.de/perma?j=FeiertG_BE | Z76: =IF(OR('Projektübersicht'!$F$11="",'Projektübersicht'!$F$13="",'Projektübersicht'!$F$11>'Projektübersicht'!$F$13),"",IF('Projektübersicht'!$F$11+74<='Projektübersicht'!$F$13,'Projektübersicht'!$F$11+74,"")) | AB76: =IF(OR('Projektübersicht'!$F$11="",'Projektübersicht'!$F$13="",'Projektübersicht'!$F$11>'Projektübersicht'!$F$13),"",IF(WORKDAY.INTL('Projektübersicht'!$F$11-1,75,"0000001")<='Projektübersicht'!$F$13,WORKDAY.INTL('Projektübersicht'!$F$11-1,75,"0000001"),""))
E77: 48335 | F77: Tag der Arbeit | G77: https://gesetze.berlin.de/perma?j=FeiertG_BE | Z77: =IF(OR('Projektübersicht'!$F$11="",'Projektübersicht'!$F$13="",'Projektübersicht'!$F$11>'Projektübersicht'!$F$13),"",IF('Projektübersicht'!$F$11+75<='Projektübersicht'!$F$13,'Projektübersicht'!$F$11+75,"")) | AB77: =IF(OR('Projektübersicht'!$F$11="",'Projektübersicht'!$F$13="",'Projektübersicht'!$F$11>'Projektübersicht'!$F$13),"",IF(WORKDAY.INTL('Projektübersicht'!$F$11-1,76,"0000001")<='Projektübersicht'!$F$13,WORKDAY.INTL('Projektübersicht'!$F$11-1,76,"0000001"),""))
E78: 48340 | F78: Christi Himmelfahrt | G78: https://gesetze.berlin.de/perma?j=FeiertG_BE | Z78: =IF(OR('Projektübersicht'!$F$11="",'Projektübersicht'!$F$13="",'Projektübersicht'!$F$11>'Projektübersicht'!$F$13),"",IF('Projektübersicht'!$F$11+76<='Projektübersicht'!$F$13,'Projektübersicht'!$F$11+76,"")) | AB78: =IF(OR('Projektübersicht'!$F$11="",'Projektübersicht'!$F$13="",'Projektübersicht'!$F$11>'Projektübersicht'!$F$13),"",IF(WORKDAY.INTL('Projektübersicht'!$F$11-1,77,"0000001")<='Projektübersicht'!$F$13,WORKDAY.INTL('Projektübersicht'!$F$11-1,77,"0000001"),""))
E79: 48351 | F79: Pfingstmontag | G79: https://gesetze.berlin.de/perma?j=FeiertG_BE | Z79: =IF(OR('Projektübersicht'!$F$11="",'Projektübersicht'!$F$13="",'Projektübersicht'!$F$11>'Projektübersicht'!$F$13),"",IF('Projektübersicht'!$F$11+77<='Projektübersicht'!$F$13,'Projektübersicht'!$F$11+77,"")) | AB79: =IF(OR('Projektübersicht'!$F$11="",'Projektübersicht'!$F$13="",'Projektübersicht'!$F$11>'Projektübersicht'!$F$13),"",IF(WORKDAY.INTL('Projektübersicht'!$F$11-1,78,"0000001")<='Projektübersicht'!$F$13,WORKDAY.INTL('Projektübersicht'!$F$11-1,78,"0000001"),""))
E80: 48490 | F80: Tag der Deutschen Einheit | G80: https://gesetze.berlin.de/perma?j=FeiertG_BE | Z80: =IF(OR('Projektübersicht'!$F$11="",'Projektübersicht'!$F$13="",'Projektübersicht'!$F$11>'Projektübersicht'!$F$13),"",IF('Projektübersicht'!$F$11+78<='Projektübersicht'!$F$13,'Projektübersicht'!$F$11+78,"")) | AB80: =IF(OR('Projektübersicht'!$F$11="",'Projektübersicht'!$F$13="",'Projektübersicht'!$F$11>'Projektübersicht'!$F$13),"",IF(WORKDAY.INTL('Projektübersicht'!$F$11-1,79,"0000001")<='Projektübersicht'!$F$13,WORKDAY.INTL('Projektübersicht'!$F$11-1,79,"0000001"),""))
E81: 48573 | F81: 1. Weihnachtsfeiertag | G81: https://gesetze.berlin.de/perma?j=FeiertG_BE | Z81: =IF(OR('Projektübersicht'!$F$11="",'Projektübersicht'!$F$13="",'Projektübersicht'!$F$11>'Projektübersicht'!$F$13),"",IF('Projektübersicht'!$F$11+79<='Projektübersicht'!$F$13,'Projektübersicht'!$F$11+79,"")) | AB81: =IF(OR('Projektübersicht'!$F$11="",'Projektübersicht'!$F$13="",'Projektübersicht'!$F$11>'Projektübersicht'!$F$13),"",IF(WORKDAY.INTL('Projektübersicht'!$F$11-1,80,"0000001")<='Projektübersicht'!$F$13,WORKDAY.INTL('Projektübersicht'!$F$11-1,80,"0000001"),""))
E82: 48574 | F82: 2. Weihnachtsfeiertag | G82: https://gesetze.berlin.de/perma?j=FeiertG_BE | Z82: =IF(OR('Projektübersicht'!$F$11="",'Projektübersicht'!$F$13="",'Projektübersicht'!$F$11>'Projektübersicht'!$F$13),"",IF('Projektübersicht'!$F$11+80<='Projektübersicht'!$F$13,'Projektübersicht'!$F$11+80,"")) | AB82: =IF(OR('Projektübersicht'!$F$11="",'Projektübersicht'!$F$13="",'Projektübersicht'!$F$11>'Projektübersicht'!$F$13),"",IF(WORKDAY.INTL('Projektübersicht'!$F$11-1,81,"0000001")<='Projektübersicht'!$F$13,WORKDAY.INTL('Projektübersicht'!$F$11-1,81,"0000001"),""))
Z83: =IF(OR('Projektübersicht'!$F$11="",'Projektübersicht'!$F$13="",'Projektübersicht'!$F$11>'Projektübersicht'!$F$13),"",IF('Projektübersicht'!$F$11+81<='Projektübersicht'!$F$13,'Projektübersicht'!$F$11+81,"")) | AB83: =IF(OR('Projektübersicht'!$F$11="",'Projektübersicht'!$F$13="",'Projektübersicht'!$F$11>'Projektübersicht'!$F$13),"",IF(WORKDAY.INTL('Projektübersicht'!$F$11-1,82,"0000001")<='Projektübersicht'!$F$13,WORKDAY.INTL('Projektübersicht'!$F$11-1,82,"0000001"),""))
Z84: =IF(OR('Projektübersicht'!$F$11="",'Projektübersicht'!$F$13="",'Projektübersicht'!$F$11>'Projektübersicht'!$F$13),"",IF('Projektübersicht'!$F$11+82<='Projektübersicht'!$F$13,'Projektübersicht'!$F$11+82,"")) | AB84: =IF(OR('Projektübersicht'!$F$11="",'Projektübersicht'!$F$13="",'Projektübersicht'!$F$11>'Projektübersicht'!$F$13),"",IF(WORKDAY.INTL('Projektübersicht'!$F$11-1,83,"0000001")<='Projektübersicht'!$F$13,WORKDAY.INTL('Projektübersicht'!$F$11-1,83,"0000001"),""))
Z85: =IF(OR('Projektübersicht'!$F$11="",'Projektübersicht'!$F$13="",'Projektübersicht'!$F$11>'Projektübersicht'!$F$13),"",IF('Projektübersicht'!$F$11+83<='Projektübersicht'!$F$13,'Projektübersicht'!$F$11+83,"")) | AB85: =IF(OR('Projektübersicht'!$F$11="",'Projektübersicht'!$F$13="",'Projektübersicht'!$F$11>'Projektübersicht'!$F$13),"",IF(WORKDAY.INTL('Projektübersicht'!$F$11-1,84,"0000001")<='Projektübersicht'!$F$13,WORKDAY.INTL('Projektübersicht'!$F$11-1,84,"0000001"),""))
Z86: =IF(OR('Projektübersicht'!$F$11="",'Projektübersicht'!$F$13="",'Projektübersicht'!$F$11>'Projektübersicht'!$F$13),"",IF('Projektübersicht'!$F$11+84<='Projektübersicht'!$F$13,'Projektübersicht'!$F$11+84,"")) | AB86: =IF(OR('Projektübersicht'!$F$11="",'Projektübersicht'!$F$13="",'Projektübersicht'!$F$11>'Projektübersicht'!$F$13),"",IF(WORKDAY.INTL('Projektübersicht'!$F$11-1,85,"0000001")<='Projektübersicht'!$F$13,WORKDAY.INTL('Projektübersicht'!$F$11-1,85,"0000001"),""))
Z87: =IF(OR('Projektübersicht'!$F$11="",'Projektübersicht'!$F$13="",'Projektübersicht'!$F$11>'Projektübersicht'!$F$13),"",IF('Projektübersicht'!$F$11+85<='Projektübersicht'!$F$13,'Projektübersicht'!$F$11+85,"")) | AB87: =IF(OR('Projektübersicht'!$F$11="",'Projektübersicht'!$F$13="",'Projektübersicht'!$F$11>'Projektübersicht'!$F$13),"",IF(WORKDAY.INTL('Projektübersicht'!$F$11-1,86,"0000001")<='Projektübersicht'!$F$13,WORKDAY.INTL('Projektübersicht'!$F$11-1,86,"0000001"),""))
Z88: =IF(OR('Projektübersicht'!$F$11="",'Projektübersicht'!$F$13="",'Projektübersicht'!$F$11>'Projektübersicht'!$F$13),"",IF('Projektübersicht'!$F$11+86<='Projektübersicht'!$F$13,'Projektübersicht'!$F$11+86,"")) | AB88: =IF(OR('Projektübersicht'!$F$11="",'Projektübersicht'!$F$13="",'Projektübersicht'!$F$11>'Projektübersicht'!$F$13),"",IF(WORKDAY.INTL('Projektübersicht'!$F$11-1,87,"0000001")<='Projektübersicht'!$F$13,WORKDAY.INTL('Projektübersicht'!$F$11-1,87,"0000001"),""))
Z89: =IF(OR('Projektübersicht'!$F$11="",'Projektübersicht'!$F$13="",'Projektübersicht'!$F$11>'Projektübersicht'!$F$13),"",IF('Projektübersicht'!$F$11+87<='Projektübersicht'!$F$13,'Projektübersicht'!$F$11+87,"")) | AB89: =IF(OR('Projektübersicht'!$F$11="",'Projektübersicht'!$F$13="",'Projektübersicht'!$F$11>'Projektübersicht'!$F$13),"",IF(WORKDAY.INTL('Projektübersicht'!$F$11-1,88,"0000001")<='Projektübersicht'!$F$13,WORKDAY.INTL('Projektübersicht'!$F$11-1,88,"0000001"),""))
Z90: =IF(OR('Projektübersicht'!$F$11="",'Projektübersicht'!$F$13="",'Projektübersicht'!$F$11>'Projektübersicht'!$F$13),"",IF('Projektübersicht'!$F$11+88<='Projektübersicht'!$F$13,'Projektübersicht'!$F$11+88,"")) | AB90: =IF(OR('Projektübersicht'!$F$11="",'Projektübersicht'!$F$13="",'Projektübersicht'!$F$11>'Projektübersicht'!$F$13),"",IF(WORKDAY.INTL('Projektübersicht'!$F$11-1,89,"0000001")<='Projektübersicht'!$F$13,WORKDAY.INTL('Projektübersicht'!$F$11-1,89,"0000001"),""))
Z91: =IF(OR('Projektübersicht'!$F$11="",'Projektübersicht'!$F$13="",'Projektübersicht'!$F$11>'Projektübersicht'!$F$13),"",IF('Projektübersicht'!$F$11+89<='Projektübersicht'!$F$13,'Projektübersicht'!$F$11+89,"")) | AB91: =IF(OR('Projektübersicht'!$F$11="",'Projektübersicht'!$F$13="",'Projektübersicht'!$F$11>'Projektübersicht'!$F$13),"",IF(WORKDAY.INTL('Projektübersicht'!$F$11-1,90,"0000001")<='Projektübersicht'!$F$13,WORKDAY.INTL('Projektübersicht'!$F$11-1,90,"0000001"),""))
Z92: =IF(OR('Projektübersicht'!$F$11="",'Projektübersicht'!$F$13="",'Projektübersicht'!$F$11>'Projektübersicht'!$F$13),"",IF('Projektübersicht'!$F$11+90<='Projektübersicht'!$F$13,'Projektübersicht'!$F$11+90,"")) | AB92: =IF(OR('Projektübersicht'!$F$11="",'Projektübersicht'!$F$13="",'Projektübersicht'!$F$11>'Projektübersicht'!$F$13),"",IF(WORKDAY.INTL('Projektübersicht'!$F$11-1,91,"0000001")<='Projektübersicht'!$F$13,WORKDAY.INTL('Projektübersicht'!$F$11-1,91,"0000001"),""))
